Workbook

Sheet DUTY_2025
A1: HS | C1: NORM/SG | D1: SCL | E1: Current Rate/kg | F1: ICL/SLSI | G1: SCL Price | H1: Normal Price | I1: CIF Based | J1: DUTY | K1: CIF Value | L1: Net Weight | M1: MRP | N1: Unit | O1: Invoice Percent | P1: Preferential Duty | Q1: Gen Duty | R1: VAT | S1: PAL_GEN | T1: PAL_SG | U1: CESS_GEN | V1: CESS_SG | W1: EXCISE | X1: SSCL | Y1: Preferential Duty | Z1: Gen Duty | AA1: VAT | AB1: PAL_GEN | AC1: PAL_SG | AD1: CESS_GEN | AE1: CESS_SG | AF1: EXCISE | AG1: SSCL | AH1: Preferential Duty | AI1: Gen Duty | AJ1: VAT | AK1: PAL_GEN | AL1: PAL_SG | AM1: CESS_GEN | AN1: CESS_SG | AO1: EXCISE | AP1: SSCL | AQ1: Preferential Duty | AR1: Gen Duty | AS1: VAT | AT1: PAL_GEN | AU1: PAL_SG | AV1: CESS_GEN | AW1: CESS_SG | AX1: EXCISE | AY1: SSCL
A2: 04059000 | B2: GHEE | C2: NORM | D2: SCL | E2: =IF(D2="SCL",G2,H2) -> 2000 | G2: 2000 | H2: =ROUND(I2,0) -> 1933 | I2: =IF(AND(L2<>"",L2<>0),ROUND(J2/L2,0),0) -> 1933 | J2: =IF(C2="SG",ROUND((P2+Q2+R2+T2+V2+W2+X2),0),ROUND((P2+Q2+R2+S2+U2+W2+X2),0)) -> 730800 | K2: =SUMIF(ProductList!$F$4:$F$493,A2,ProductList!$BA$4:$BA$493) -> 1119892 | L2: =SUMIF(ProductList!$F$4:$F$493,A2,ProductList!$V$4:$V$493) -> 378 | M2: =SUMIF(ProductList!$F$4:$F$493,A2,ProductList!$K$4:$K$493) -> 0 | N2: KG | O2: =IF(D2="SCL",100,AZ2) -> 100 | P2: =IF((K2*Y2)>(L2*AH2),(K2*Y2),(L2*AH2)) -> 0 | Q2: =IF((K2*Z2)>(L2*AI2),(K2*Z2),(L2*AI2)) -> 264600 | R2: =IF(C2="SG", IF(((K2*1.1+P2+Q2+T2+V2)*AA2)>(L2*AJ2), (K2*1.1+P2+Q2+T2+V2)*AA2, L2*AJ2), IF(((K2*1.1+P2+Q2+S2+U2)*AA2)>(L2*AJ2), (K2*1.1+P2+Q2+S2+U2)*AA2, L2*AJ2) ) -> 293180.62 | S2: =IF((K2*AB2)>(L2*AK2),(K2*AB2),(L2*AK2)) -> 0 | T2: =IF((K2*AC2)>(L2*AL2),(K2*AC2),(L2*AL2)) -> 0 | U2: =IF((K2*AD2)>(L2*AM2),(K2*AD2),(L2*AM2)) -> 132300 | V2: =IF((K2*AE2)>(L2*AN2),(K2*AE2),(L2*AN2)) -> 0 | W2: =IF((K2*AF2)>(L2*AO2),(K2*AF2),(L2*AO2)) -> 0 | X2: =IF((((K2)*1.1+P2+Q2+S2+T2+U2+V2)*AG2)>(L2*AP2),(((K2)*1.1+P2+Q2+S2+T2+U2+V2)*AG2),(L2*AP2)) -> 40719.53 | Z2: 0.2 | AA2: 0.18 | AD2: 0.1 | AG2: 0.025 | AI2: 700 | AM2: 350 | AZ2: 80
A3: 04090000 | B3: HONEY | D3: NORM | E3: =IF(D3="SCL",G3,H3) -> 0 | H3: =ROUND(I3,0) -> 0 | I3: =IF(AND(L3<>"",L3<>0),ROUND(J3/L3,0),0) -> 0 | J3: =IF(C3="SG",ROUND((P3+Q3+R3+T3+V3+W3+X3),0),ROUND((P3+Q3+R3+S3+U3+W3+X3),0)) -> 0 | K3: =SUMIF(ProductList!$F$4:$F$493,A3,ProductList!$BA$4:$BA$493) -> 0 | L3: =SUMIF(ProductList!$F$4:$F$493,A3,ProductList!$V$4:$V$493) -> 0 | M3: =SUMIF(ProductList!$F$4:$F$493,A3,ProductList!$K$4:$K$493) -> 0 | N3: KG | O3: =IF(D3="SCL",100,AZ3) -> 80 | P3: =IF((K3*Y3)>(L3*AH3),(K3*Y3),(L3*AH3)) -> 0 | Q3: =IF((K3*Z3)>(L3*AI3),(K3*Z3),(L3*AI3)) -> 0 | R3: =IF(C3="SG", IF(((K3*1.1+P3+Q3+T3+V3)*AA3)>(L3*AJ3), (K3*1.1+P3+Q3+T3+V3)*AA3, L3*AJ3), IF(((K3*1.1+P3+Q3+S3+U3)*AA3)>(L3*AJ3), (K3*1.1+P3+Q3+S3+U3)*AA3, L3*AJ3) ) -> 0 | S3: =IF((K3*AB3)>(L3*AK3),(K3*AB3),(L3*AK3)) -> 0 | T3: =IF((K3*AC3)>(L3*AL3),(K3*AC3),(L3*AL3)) -> 0 | U3: =IF((K3*AD3)>(L3*AM3),(K3*AD3),(L3*AM3)) -> 0 | V3: =IF((K3*AE3)>(L3*AN3),(K3*AE3),(L3*AN3)) -> 0 | W3: =IF((K3*AF3)>(L3*AO3),(K3*AF3),(L3*AO3)) -> 0 | X3: =IF((((K3)*1.1+P3+Q3+S3+T3+U3+V3)*AG3)>(L3*AP3),(((K3)*1.1+P3+Q3+S3+T3+U3+V3)*AG3),(L3*AP3)) -> 0 | Z3: 0.2 | AA3: 0.18 | AB3: 0.1 | AD3: 0.1 | AG3: 0.025 | AZ3: =AZ2 -> 80
A4: 07133119 | B4: GREEN GRAM - OTHER | D4: SCL | E4: =IF(D4="SCL",G4,H4) -> 300 | G4: 300 | H4: =ROUND(I4,0) -> 0 | I4: =IF(AND(L4<>"",L4<>0),ROUND(J4/L4,0),0) -> 0 | J4: =IF(C4="SG",ROUND((P4+Q4+R4+T4+V4+W4+X4),0),ROUND((P4+Q4+R4+S4+U4+W4+X4),0)) -> 0 | K4: =SUMIF(ProductList!$F$4:$F$493,A4,ProductList!$BA$4:$BA$493) -> 0 | L4: =SUMIF(ProductList!$F$4:$F$493,A4,ProductList!$V$4:$V$493) -> 0 | M4: =SUMIF(ProductList!$F$4:$F$493,A4,ProductList!$K$4:$K$493) -> 0 | N4: KG | O4: =IF(D4="SCL",100,AZ4) -> 100 | P4: =IF((K4*Y4)>(L4*AH4),(K4*Y4),(L4*AH4)) -> 0 | Q4: =IF((K4*Z4)>(L4*AI4),(K4*Z4),(L4*AI4)) -> 0 | R4: =IF(C4="SG", IF(((K4*1.1+P4+Q4+T4+V4)*AA4)>(L4*AJ4), (K4*1.1+P4+Q4+T4+V4)*AA4, L4*AJ4), IF(((K4*1.1+P4+Q4+S4+U4)*AA4)>(L4*AJ4), (K4*1.1+P4+Q4+S4+U4)*AA4, L4*AJ4) ) -> 0 | S4: =IF((K4*AB4)>(L4*AK4),(K4*AB4),(L4*AK4)) -> 0 | T4: =IF((K4*AC4)>(L4*AL4),(K4*AC4),(L4*AL4)) -> 0 | U4: =IF((K4*AD4)>(L4*AM4),(K4*AD4),(L4*AM4)) -> 0 | V4: =IF((K4*AE4)>(L4*AN4),(K4*AE4),(L4*AN4)) -> 0 | W4: =IF((K4*AF4)>(L4*AO4),(K4*AF4),(L4*AO4)) -> 0 | X4: =IF((((K4)*1.1+P4+Q4+S4+T4+U4+V4)*AG4)>(L4*AP4),(((K4)*1.1+P4+Q4+S4+T4+U4+V4)*AG4),(L4*AP4)) -> 0 | AZ4: =AZ3 -> 80
A5: 07133129 | B5: BLACK GRAM | D5: SCL | E5: =IF(D5="SCL",G5,H5) -> 300 | G5: 300 | H5: =ROUND(I5,0) -> 0 | I5: =IF(AND(L5<>"",L5<>0),ROUND(J5/L5,0),0) -> 0 | J5: =IF(C5="SG",ROUND((P5+Q5+R5+T5+V5+W5+X5),0),ROUND((P5+Q5+R5+S5+U5+W5+X5),0)) -> 0 | K5: =SUMIF(ProductList!$F$4:$F$493,A5,ProductList!$BA$4:$BA$493) -> 0 | L5: =SUMIF(ProductList!$F$4:$F$493,A5,ProductList!$V$4:$V$493) -> 0 | M5: =SUMIF(ProductList!$F$4:$F$493,A5,ProductList!$K$4:$K$493) -> 0 | N5: KG | O5: =IF(D5="SCL",100,AZ5) -> 100 | P5: =IF((K5*Y5)>(L5*AH5),(K5*Y5),(L5*AH5)) -> 0 | Q5: =IF((K5*Z5)>(L5*AI5),(K5*Z5),(L5*AI5)) -> 0 | R5: =IF(C5="SG", IF(((K5*1.1+P5+Q5+T5+V5)*AA5)>(L5*AJ5), (K5*1.1+P5+Q5+T5+V5)*AA5, L5*AJ5), IF(((K5*1.1+P5+Q5+S5+U5)*AA5)>(L5*AJ5), (K5*1.1+P5+Q5+S5+U5)*AA5, L5*AJ5) ) -> 0 | S5: =IF((K5*AB5)>(L5*AK5),(K5*AB5),(L5*AK5)) -> 0 | T5: =IF((K5*AC5)>(L5*AL5),(K5*AC5),(L5*AL5)) -> 0 | U5: =IF((K5*AD5)>(L5*AM5),(K5*AD5),(L5*AM5)) -> 0 | V5: =IF((K5*AE5)>(L5*AN5),(K5*AE5),(L5*AN5)) -> 0 | W5: =IF((K5*AF5)>(L5*AO5),(K5*AF5),(L5*AO5)) -> 0 | X5: =IF((((K5)*1.1+P5+Q5+S5+T5+U5+V5)*AG5)>(L5*AP5),(((K5)*1.1+P5+Q5+S5+T5+U5+V5)*AG5),(L5*AP5)) -> 0 | AZ5: =AZ4 -> 80
A6: 07133990 | B6: BEANS - OTHERS | E6: =IF(D6="SCL",G6,H6) -> 0 | H6: =ROUND(I6,0) -> 0 | I6: =IF(AND(L6<>"",L6<>0),ROUND(J6/L6,0),0) -> 0 | J6: =IF(C6="SG",ROUND((P6+Q6+R6+T6+V6+W6+X6),0),ROUND((P6+Q6+R6+S6+U6+W6+X6),0)) -> 0 | K6: =SUMIF(ProductList!$F$4:$F$493,A6,ProductList!$BA$4:$BA$493) -> 0 | L6: =SUMIF(ProductList!$F$4:$F$493,A6,ProductList!$V$4:$V$493) -> 0 | M6: =SUMIF(ProductList!$F$4:$F$493,A6,ProductList!$K$4:$K$493) -> 0 | N6: KG | O6: =IF(D6="SCL",100,AZ6) -> 80 | P6: =IF((K6*Y6)>(L6*AH6),(K6*Y6),(L6*AH6)) -> 0 | Q6: =IF((K6*Z6)>(L6*AI6),(K6*Z6),(L6*AI6)) -> 0 | R6: =IF(C6="SG", IF(((K6*1.1+P6+Q6+T6+V6)*AA6)>(L6*AJ6), (K6*1.1+P6+Q6+T6+V6)*AA6, L6*AJ6), IF(((K6*1.1+P6+Q6+S6+U6)*AA6)>(L6*AJ6), (K6*1.1+P6+Q6+S6+U6)*AA6, L6*AJ6) ) -> 0 | S6: =IF((K6*AB6)>(L6*AK6),(K6*AB6),(L6*AK6)) -> 0 | T6: =IF((K6*AC6)>(L6*AL6),(K6*AC6),(L6*AL6)) -> 0 | U6: =IF((K6*AD6)>(L6*AM6),(K6*AD6),(L6*AM6)) -> 0 | V6: =IF((K6*AE6)>(L6*AN6),(K6*AE6),(L6*AN6)) -> 0 | W6: =IF((K6*AF6)>(L6*AO6),(K6*AF6),(L6*AO6)) -> 0 | X6: =IF((((K6)*1.1+P6+Q6+S6+T6+U6+V6)*AG6)>(L6*AP6),(((K6)*1.1+P6+Q6+S6+T6+U6+V6)*AG6),(L6*AP6)) -> 0 | Z6: 0.2 | AA6: 0.18 | AB6: 0.1 | AD6: 0.1 | AG6: 0.025 | AZ6: =AZ5 -> 80
A7: 07136010 | B7: TOOR DHAL | D7: NORM | E7: =IF(D7="SCL",G7,H7) -> 0 | H7: =ROUND(I7,0) -> 0 | I7: =IF(AND(L7<>"",L7<>0),ROUND(J7/L7,0),0) -> 0 | J7: =IF(C7="SG",ROUND((P7+Q7+R7+T7+V7+W7+X7),0),ROUND((P7+Q7+R7+S7+U7+W7+X7),0)) -> 0 | K7: =SUMIF(ProductList!$F$4:$F$493,A7,ProductList!$BA$4:$BA$493) -> 0 | L7: =SUMIF(ProductList!$F$4:$F$493,A7,ProductList!$V$4:$V$493) -> 0 | M7: =SUMIF(ProductList!$F$4:$F$493,A7,ProductList!$K$4:$K$493) -> 0 | N7: KG | O7: =IF(D7="SCL",100,AZ7) -> 80 | P7: =IF((K7*Y7)>(L7*AH7),(K7*Y7),(L7*AH7)) -> 0 | Q7: =IF((K7*Z7)>(L7*AI7),(K7*Z7),(L7*AI7)) -> 0 | R7: =IF(C7="SG", IF(((K7*1.1+P7+Q7+T7+V7)*AA7)>(L7*AJ7), (K7*1.1+P7+Q7+T7+V7)*AA7, L7*AJ7), IF(((K7*1.1+P7+Q7+S7+U7)*AA7)>(L7*AJ7), (K7*1.1+P7+Q7+S7+U7)*AA7, L7*AJ7) ) -> 0 | S7: =IF((K7*AB7)>(L7*AK7),(K7*AB7),(L7*AK7)) -> 0 | T7: =IF((K7*AC7)>(L7*AL7),(K7*AC7),(L7*AL7)) -> 0 | U7: =IF((K7*AD7)>(L7*AM7),(K7*AD7),(L7*AM7)) -> 0 | V7: =IF((K7*AE7)>(L7*AN7),(K7*AE7),(L7*AN7)) -> 0 | W7: =IF((K7*AF7)>(L7*AO7),(K7*AF7),(L7*AO7)) -> 0 | X7: =IF((((K7)*1.1+P7+Q7+S7+T7+U7+V7)*AG7)>(L7*AP7),(((K7)*1.1+P7+Q7+S7+T7+U7+V7)*AG7),(L7*AP7)) -> 0 | AA7: 0.18 | AB7: 0.1 | AC7: 0.06 | AG7: 0.025 | AI7: 45 | AZ7: =AZ6 -> 80
A8: 09019000 | B8: COFFEE ROASTED | D8: NORM | E8: =IF(D8="SCL",G8,H8) -> 0 | H8: =ROUND(I8,0) -> 0 | I8: =IF(AND(L8<>"",L8<>0),ROUND(J8/L8,0),0) -> 0 | J8: =IF(C8="SG",ROUND((P8+Q8+R8+T8+V8+W8+X8),0),ROUND((P8+Q8+R8+S8+U8+W8+X8),0)) -> 0 | K8: =SUMIF(ProductList!$F$4:$F$493,A8,ProductList!$BA$4:$BA$493) -> 0 | L8: =SUMIF(ProductList!$F$4:$F$493,A8,ProductList!$V$4:$V$493) -> 0 | M8: =SUMIF(ProductList!$F$4:$F$493,A8,ProductList!$K$4:$K$493) -> 0 | N8: KG | O8: =IF(D8="SCL",100,AZ8) -> 80 | P8: =IF((K8*Y8)>(L8*AH8),(K8*Y8),(L8*AH8)) -> 0 | Q8: =IF((K8*Z8)>(L8*AI8),(K8*Z8),(L8*AI8)) -> 0 | R8: =IF(C8="SG", IF(((K8*1.1+P8+Q8+T8+V8)*AA8)>(L8*AJ8), (K8*1.1+P8+Q8+T8+V8)*AA8, L8*AJ8), IF(((K8*1.1+P8+Q8+S8+U8)*AA8)>(L8*AJ8), (K8*1.1+P8+Q8+S8+U8)*AA8, L8*AJ8) ) -> 0 | S8: =IF((K8*AB8)>(L8*AK8),(K8*AB8),(L8*AK8)) -> 0 | T8: =IF((K8*AC8)>(L8*AL8),(K8*AC8),(L8*AL8)) -> 0 | U8: =IF((K8*AD8)>(L8*AM8),(K8*AD8),(L8*AM8)) -> 0 | V8: =IF((K8*AE8)>(L8*AN8),(K8*AE8),(L8*AN8)) -> 0 | W8: =IF((K8*AF8)>(L8*AO8),(K8*AF8),(L8*AO8)) -> 0 | X8: =IF((((K8)*1.1+P8+Q8+S8+T8+U8+V8)*AG8)>(L8*AP8),(((K8)*1.1+P8+Q8+S8+T8+U8+V8)*AG8),(L8*AP8)) -> 0 | Z8: 0.2 | AA8: 0.18 | AB8: 0.1 | AD8: 0.25 | AG8: 0.025 | AZ8: =AZ7 -> 80
A9: 09023021 | B9: FLAVOURED TEA | D9: NORM | E9: =IF(D9="SCL",G9,H9) -> 0 | H9: =ROUND(I9,0) -> 0 | I9: =IF(AND(L9<>"",L9<>0),ROUND(J9/L9,0),0) -> 0 | J9: =IF(C9="SG",ROUND((P9+Q9+R9+T9+V9+W9+X9),0),ROUND((P9+Q9+R9+S9+U9+W9+X9),0)) -> 0 | K9: =SUMIF(ProductList!$F$4:$F$493,A9,ProductList!$BA$4:$BA$493) -> 0 | L9: =SUMIF(ProductList!$F$4:$F$493,A9,ProductList!$V$4:$V$493) -> 0 | M9: =SUMIF(ProductList!$F$4:$F$493,A9,ProductList!$K$4:$K$493) -> 0 | N9: KG | O9: =IF(D9="SCL",100,AZ9) -> 80 | P9: =IF((K9*Y9)>(L9*AH9),(K9*Y9),(L9*AH9)) -> 0 | Q9: =IF((K9*Z9)>(L9*AI9),(K9*Z9),(L9*AI9)) -> 0 | R9: =IF(C9="SG", IF(((K9*1.1+P9+Q9+T9+V9)*AA9)>(L9*AJ9), (K9*1.1+P9+Q9+T9+V9)*AA9, L9*AJ9), IF(((K9*1.1+P9+Q9+S9+U9)*AA9)>(L9*AJ9), (K9*1.1+P9+Q9+S9+U9)*AA9, L9*AJ9) ) -> 0 | S9: =IF((K9*AB9)>(L9*AK9),(K9*AB9),(L9*AK9)) -> 0 | T9: =IF((K9*AC9)>(L9*AL9),(K9*AC9),(L9*AL9)) -> 0 | U9: =IF((K9*AD9)>(L9*AM9),(K9*AD9),(L9*AM9)) -> 0 | V9: =IF((K9*AE9)>(L9*AN9),(K9*AE9),(L9*AN9)) -> 0 | W9: =IF((K9*AF9)>(L9*AO9),(K9*AF9),(L9*AO9)) -> 0 | X9: =IF((((K9)*1.1+P9+Q9+S9+T9+U9+V9)*AG9)>(L9*AP9),(((K9)*1.1+P9+Q9+S9+T9+U9+V9)*AG9),(L9*AP9)) -> 0 | Z9: 0.2 | AA9: 0.18 | AB9: 0 | AC9: 0 | AD9: 0.1 | AG9: 0.025 | AZ9: =AZ8 -> 80
A10: 09042190 | B10: CHILLIES- OTHER | D10: NORM | E10: =IF(D10="SCL",G10,H10) -> 705 | H10: =ROUND(I10,0) -> 705 | I10: =IF(AND(L10<>"",L10<>0),ROUND(J10/L10,0),0) -> 705 | J10: =IF(C10="SG",ROUND((P10+Q10+R10+T10+V10+W10+X10),0),ROUND((P10+Q10+R10+S10+U10+W10+X10),0)) -> 754592 | K10: =SUMIF(ProductList!$F$4:$F$493,A10,ProductList!$BA$4:$BA$493) -> 849526.4 | L10: =SUMIF(ProductList!$F$4:$F$493,A10,ProductList!$V$4:$V$493) -> 1070 | M10: =SUMIF(ProductList!$F$4:$F$493,A10,ProductList!$K$4:$K$493) -> 0 | N10: KG | O10: =IF(D10="SCL",100,AZ10) -> 80 | P10: =IF((K10*Y10)>(L10*AH10),(K10*Y10),(L10*AH10)) -> 0 | Q10: =IF((K10*Z10)>(L10*AI10),(K10*Z10),(L10*AI10)) -> 169905.28 | R10: =IF(C10="SG", IF(((K10*1.1+P10+Q10+T10+V10)*AA10)>(L10*AJ10), (K10*1.1+P10+Q10+T10+V10)*AA10, L10*AJ10), IF(((K10*1.1+P10+Q10+S10+U10)*AA10)>(L10*AJ10), (K10*1.1+P10+Q10+S10+U10)*AA10, L10*AJ10) ) -> 252309.34 | S10: =IF((K10*AB10)>(L10*AK10),(K10*AB10),(L10*AK10)) -> 84952.64 | T10: =IF((K10*AC10)>(L10*AL10),(K10*AC10),(L10*AL10)) -> 0 | U10: =IF((K10*AD10)>(L10*AM10),(K10*AD10),(L10*AM10)) -> 212381.6 | V10: =IF((K10*AE10)>(L10*AN10),(K10*AE10),(L10*AN10)) -> 0 | W10: =IF((K10*AF10)>(L10*AO10),(K10*AF10),(L10*AO10)) -> 0 | X10: =IF((((K10)*1.1+P10+Q10+S10+T10+U10+V10)*AG10)>(L10*AP10),(((K10)*1.1+P10+Q10+S10+T10+U10+V10)*AG10),(L10*AP10)) -> 35042.964 | Z10: 0.2 | AA10: 0.18 | AB10: 0.1 | AD10: 0.25 | AG10: 0.025 | AZ10: =AZ9 -> 80
A11: 09042210 | B11: CHILLIES | D11: SCL | E11: =IF(D11="SCL",G11,H11) -> 125 | F11: S | G11: 125 | H11: =ROUND(I11,0) -> 0 | I11: =IF(AND(L11<>"",L11<>0),ROUND(J11/L11,0),0) -> 0 | J11: =IF(C11="SG",ROUND((P11+Q11+R11+T11+V11+W11+X11),0),ROUND((P11+Q11+R11+S11+U11+W11+X11),0)) -> 0 | K11: =SUMIF(ProductList!$F$4:$F$493,A11,ProductList!$BA$4:$BA$493) -> 0 | L11: =SUMIF(ProductList!$F$4:$F$493,A11,ProductList!$V$4:$V$493) -> 0 | M11: =SUMIF(ProductList!$F$4:$F$493,A11,ProductList!$K$4:$K$493) -> 0 | N11: KG | O11: =IF(D11="SCL",100,AZ11) -> 100 | P11: =IF((K11*Y11)>(L11*AH11),(K11*Y11),(L11*AH11)) -> 0 | Q11: =IF((K11*Z11)>(L11*AI11),(K11*Z11),(L11*AI11)) -> 0 | R11: =IF(C11="SG", IF(((K11*1.1+P11+Q11+T11+V11)*AA11)>(L11*AJ11), (K11*1.1+P11+Q11+T11+V11)*AA11, L11*AJ11), IF(((K11*1.1+P11+Q11+S11+U11)*AA11)>(L11*AJ11), (K11*1.1+P11+Q11+S11+U11)*AA11, L11*AJ11) ) -> 0 | S11: =IF((K11*AB11)>(L11*AK11),(K11*AB11),(L11*AK11)) -> 0 | T11: =IF((K11*AC11)>(L11*AL11),(K11*AC11),(L11*AL11)) -> 0 | U11: =IF((K11*AD11)>(L11*AM11),(K11*AD11),(L11*AM11)) -> 0 | V11: =IF((K11*AE11)>(L11*AN11),(K11*AE11),(L11*AN11)) -> 0 | W11: =IF((K11*AF11)>(L11*AO11),(K11*AF11),(L11*AO11)) -> 0 | X11: =IF((((K11)*1.1+P11+Q11+S11+T11+U11+V11)*AG11)>(L11*AP11),(((K11)*1.1+P11+Q11+S11+T11+U11+V11)*AG11),(L11*AP11)) -> 0 | AZ11: =AZ10 -> 80
A12: 09083290 | B12: CARDAMOM | D12: SCL | E12: =IF(D12="SCL",G12,H12) -> 2900 | G12: 2900 | H12: =ROUND(I12,0) -> 0 | I12: =IF(AND(L12<>"",L12<>0),ROUND(J12/L12,0),0) -> 0 | J12: =IF(C12="SG",ROUND((P12+Q12+R12+T12+V12+W12+X12),0),ROUND((P12+Q12+R12+S12+U12+W12+X12),0)) -> 0 | K12: =SUMIF(ProductList!$F$4:$F$493,A12,ProductList!$BA$4:$BA$493) -> 0 | L12: =SUMIF(ProductList!$F$4:$F$493,A12,ProductList!$V$4:$V$493) -> 0 | M12: =SUMIF(ProductList!$F$4:$F$493,A12,ProductList!$K$4:$K$493) -> 0 | N12: KG | O12: =IF(D12="SCL",100,AZ12) -> 100 | P12: =IF((K12*Y12)>(L12*AH12),(K12*Y12),(L12*AH12)) -> 0 | Q12: =IF((K12*Z12)>(L12*AI12),(K12*Z12),(L12*AI12)) -> 0 | R12: =IF(C12="SG", IF(((K12*1.1+P12+Q12+T12+V12)*AA12)>(L12*AJ12), (K12*1.1+P12+Q12+T12+V12)*AA12, L12*AJ12), IF(((K12*1.1+P12+Q12+S12+U12)*AA12)>(L12*AJ12), (K12*1.1+P12+Q12+S12+U12)*AA12, L12*AJ12) ) -> 0 | S12: =IF((K12*AB12)>(L12*AK12),(K12*AB12),(L12*AK12)) -> 0 | T12: =IF((K12*AC12)>(L12*AL12),(K12*AC12),(L12*AL12)) -> 0 | U12: =IF((K12*AD12)>(L12*AM12),(K12*AD12),(L12*AM12)) -> 0 | V12: =IF((K12*AE12)>(L12*AN12),(K12*AE12),(L12*AN12)) -> 0 | W12: =IF((K12*AF12)>(L12*AO12),(K12*AF12),(L12*AO12)) -> 0 | X12: =IF((((K12)*1.1+P12+Q12+S12+T12+U12+V12)*AG12)>(L12*AP12),(((K12)*1.1+P12+Q12+S12+T12+U12+V12)*AG12),(L12*AP12)) -> 0 | AZ12: =AZ11 -> 80
A13: 09092200 | B13: DHANIYA POWDER | D13: SCL | E13: =IF(D13="SCL",G13,H13) -> 52 | F13: S | G13: 52 | H13: =ROUND(I13,0) -> 421 | I13: =IF(AND(L13<>"",L13<>0),ROUND(J13/L13,0),0) -> 421 | J13: =IF(C13="SG",ROUND((P13+Q13+R13+T13+V13+W13+X13),0),ROUND((P13+Q13+R13+S13+U13+W13+X13),0)) -> 614924 | K13: =SUMIF(ProductList!$F$4:$F$493,A13,ProductList!$BA$4:$BA$493) -> 1318166 | L13: =SUMIF(ProductList!$F$4:$F$493,A13,ProductList!$V$4:$V$493) -> 1460 | M13: =SUMIF(ProductList!$F$4:$F$493,A13,ProductList!$K$4:$K$493) -> 0 | N13: KG | O13: =IF(D13="SCL",100,AZ13) -> 100 | P13: =IF((K13*Y13)>(L13*AH13),(K13*Y13),(L13*AH13)) -> 0 | Q13: =IF((K13*Z13)>(L13*AI13),(K13*Z13),(L13*AI13)) -> 263633.2 | R13: =IF(C13="SG", IF(((K13*1.1+P13+Q13+T13+V13)*AA13)>(L13*AJ13), (K13*1.1+P13+Q13+T13+V13)*AA13, L13*AJ13), IF(((K13*1.1+P13+Q13+S13+U13)*AA13)>(L13*AJ13), (K13*1.1+P13+Q13+S13+U13)*AA13, L13*AJ13) ) -> 308450.84 | S13: =IF((K13*AB13)>(L13*AK13),(K13*AB13),(L13*AK13)) -> 0 | T13: =IF((K13*AC13)>(L13*AL13),(K13*AC13),(L13*AL13)) -> 0 | U13: =IF((K13*AD13)>(L13*AM13),(K13*AD13),(L13*AM13)) -> 0 | V13: =IF((K13*AE13)>(L13*AN13),(K13*AE13),(L13*AN13)) -> 0 | W13: =IF((K13*AF13)>(L13*AO13),(K13*AF13),(L13*AO13)) -> 0 | X13: =IF((((K13)*1.1+P13+Q13+S13+T13+U13+V13)*AG13)>(L13*AP13),(((K13)*1.1+P13+Q13+S13+T13+U13+V13)*AG13),(L13*AP13)) -> 42840.395 | Z13: 0.2 | AA13: 0.18 | AG13: 0.025 | AZ13: =AZ12 -> 80
A14: 09093190 | B14: BLACK CUMIN | D14: NORM | E14: =IF(D14="SCL",G14,H14) -> 0 | G14: 162 | H14: =ROUND(I14,0) -> 0 | I14: =IF(AND(L14<>"",L14<>0),ROUND(J14/L14,0),0) -> 0 | J14: =IF(C14="SG",ROUND((P14+Q14+R14+T14+V14+W14+X14),0),ROUND((P14+Q14+R14+S14+U14+W14+X14),0)) -> 0 | K14: =SUMIF(ProductList!$F$4:$F$493,A14,ProductList!$BA$4:$BA$493) -> 0 | L14: =SUMIF(ProductList!$F$4:$F$493,A14,ProductList!$V$4:$V$493) -> 0 | M14: =SUMIF(ProductList!$F$4:$F$493,A14,ProductList!$K$4:$K$493) -> 0 | N14: KG | O14: =IF(D14="SCL",100,AZ14) -> 80 | P14: =IF((K14*Y14)>(L14*AH14),(K14*Y14),(L14*AH14)) -> 0 | Q14: =IF((K14*Z14)>(L14*AI14),(K14*Z14),(L14*AI14)) -> 0 | R14: =IF(C14="SG", IF(((K14*1.1+P14+Q14+T14+V14)*AA14)>(L14*AJ14), (K14*1.1+P14+Q14+T14+V14)*AA14, L14*AJ14), IF(((K14*1.1+P14+Q14+S14+U14)*AA14)>(L14*AJ14), (K14*1.1+P14+Q14+S14+U14)*AA14, L14*AJ14) ) -> 0 | S14: =IF((K14*AB14)>(L14*AK14),(K14*AB14),(L14*AK14)) -> 0 | T14: =IF((K14*AC14)>(L14*AL14),(K14*AC14),(L14*AL14)) -> 0 | U14: =IF((K14*AD14)>(L14*AM14),(K14*AD14),(L14*AM14)) -> 0 | V14: =IF((K14*AE14)>(L14*AN14),(K14*AE14),(L14*AN14)) -> 0 | W14: =IF((K14*AF14)>(L14*AO14),(K14*AF14),(L14*AO14)) -> 0 | X14: =IF((((K14)*1.1+P14+Q14+S14+T14+U14+V14)*AG14)>(L14*AP14),(((K14)*1.1+P14+Q14+S14+T14+U14+V14)*AG14),(L14*AP14)) -> 0 | AZ14: =AZ13 -> 80
A15: 09103010 | B15: TURMERIC | E15: =IF(D15="SCL",G15,H15) -> 0 | F15: L | H15: =ROUND(I15,0) -> 0 | I15: =IF(AND(L15<>"",L15<>0),ROUND(J15/L15,0),0) -> 0 | J15: =IF(C15="SG",ROUND((P15+Q15+R15+T15+V15+W15+X15),0),ROUND((P15+Q15+R15+S15+U15+W15+X15),0)) -> 0 | K15: =SUMIF(ProductList!$F$4:$F$493,A15,ProductList!$BA$4:$BA$493) -> 0 | L15: =SUMIF(ProductList!$F$4:$F$493,A15,ProductList!$V$4:$V$493) -> 0 | M15: =SUMIF(ProductList!$F$4:$F$493,A15,ProductList!$K$4:$K$493) -> 0 | N15: KG | O15: =IF(D15="SCL",100,AZ15) -> 80 | P15: =IF((K15*Y15)>(L15*AH15),(K15*Y15),(L15*AH15)) -> 0 | Q15: =IF((K15*Z15)>(L15*AI15),(K15*Z15),(L15*AI15)) -> 0 | R15: =IF(C15="SG", IF(((K15*1.1+P15+Q15+T15+V15)*AA15)>(L15*AJ15), (K15*1.1+P15+Q15+T15+V15)*AA15, L15*AJ15), IF(((K15*1.1+P15+Q15+S15+U15)*AA15)>(L15*AJ15), (K15*1.1+P15+Q15+S15+U15)*AA15, L15*AJ15) ) -> 0 | S15: =IF((K15*AB15)>(L15*AK15),(K15*AB15),(L15*AK15)) -> 0 | T15: =IF((K15*AC15)>(L15*AL15),(K15*AC15),(L15*AL15)) -> 0 | U15: =IF((K15*AD15)>(L15*AM15),(K15*AD15),(L15*AM15)) -> 0 | V15: =IF((K15*AE15)>(L15*AN15),(K15*AE15),(L15*AN15)) -> 0 | W15: =IF((K15*AF15)>(L15*AO15),(K15*AF15),(L15*AO15)) -> 0 | X15: =IF((((K15)*1.1+P15+Q15+S15+T15+U15+V15)*AG15)>(L15*AP15),(((K15)*1.1+P15+Q15+S15+T15+U15+V15)*AG15),(L15*AP15)) -> 0 | AZ15: =AZ14 -> 80
A16: 09109190 | B16: ASSORTED MASALA | D16: NORM | E16: =IF(D16="SCL",G16,H16) -> 0 | H16: =ROUND(I16,0) -> 0 | I16: =IF(AND(L16<>"",L16<>0),ROUND(J16/L16,0),0) -> 0 | J16: =IF(C16="SG",ROUND((P16+Q16+R16+T16+V16+W16+X16),0),ROUND((P16+Q16+R16+S16+U16+W16+X16),0)) -> 0 | K16: =SUMIF(ProductList!$F$4:$F$493,A16,ProductList!$BA$4:$BA$493) -> 0 | L16: =SUMIF(ProductList!$F$4:$F$493,A16,ProductList!$V$4:$V$493) -> 0 | M16: =SUMIF(ProductList!$F$4:$F$493,A16,ProductList!$K$4:$K$493) -> 0 | N16: KG | O16: =IF(D16="SCL",100,AZ16) -> 80 | P16: =IF((K16*Y16)>(L16*AH16),(K16*Y16),(L16*AH16)) -> 0 | Q16: =IF((K16*Z16)>(L16*AI16),(K16*Z16),(L16*AI16)) -> 0 | R16: =IF(C16="SG", IF(((K16*1.1+P16+Q16+T16+V16)*AA16)>(L16*AJ16), (K16*1.1+P16+Q16+T16+V16)*AA16, L16*AJ16), IF(((K16*1.1+P16+Q16+S16+U16)*AA16)>(L16*AJ16), (K16*1.1+P16+Q16+S16+U16)*AA16, L16*AJ16) ) -> 0 | S16: =IF((K16*AB16)>(L16*AK16),(K16*AB16),(L16*AK16)) -> 0 | T16: =IF((K16*AC16)>(L16*AL16),(K16*AC16),(L16*AL16)) -> 0 | U16: =IF((K16*AD16)>(L16*AM16),(K16*AD16),(L16*AM16)) -> 0 | V16: =IF((K16*AE16)>(L16*AN16),(K16*AE16),(L16*AN16)) -> 0 | W16: =IF((K16*AF16)>(L16*AO16),(K16*AF16),(L16*AO16)) -> 0 | X16: =IF((((K16)*1.1+P16+Q16+S16+T16+U16+V16)*AG16)>(L16*AP16),(((K16)*1.1+P16+Q16+S16+T16+U16+V16)*AG16),(L16*AP16)) -> 0 | Z16: 0.2 | AA16: 0.18 | AB16: 0.1 | AD16: 0.1 | AG16: 0.025 | AZ16: =AZ15 -> 80
A17: 09109913 | B17: KASTHURI METHI | D17: SCL | E17: =IF(D17="SCL",G17,H17) -> 1079 | G17: 1079 | H17: =ROUND(I17,0) -> 0 | I17: =IF(AND(L17<>"",L17<>0),ROUND(J17/L17,0),0) -> 0 | J17: =IF(C17="SG",ROUND((P17+Q17+R17+T17+V17+W17+X17),0),ROUND((P17+Q17+R17+S17+U17+W17+X17),0)) -> 0 | K17: =SUMIF(ProductList!$F$4:$F$493,A17,ProductList!$BA$4:$BA$493) -> 0 | L17: =SUMIF(ProductList!$F$4:$F$493,A17,ProductList!$V$4:$V$493) -> 0 | M17: =SUMIF(ProductList!$F$4:$F$493,A17,ProductList!$K$4:$K$493) -> 0 | N17: KG | O17: =IF(D17="SCL",100,AZ17) -> 100 | P17: =IF((K17*Y17)>(L17*AH17),(K17*Y17),(L17*AH17)) -> 0 | Q17: =IF((K17*Z17)>(L17*AI17),(K17*Z17),(L17*AI17)) -> 0 | R17: =IF(C17="SG", IF(((K17*1.1+P17+Q17+T17+V17)*AA17)>(L17*AJ17), (K17*1.1+P17+Q17+T17+V17)*AA17, L17*AJ17), IF(((K17*1.1+P17+Q17+S17+U17)*AA17)>(L17*AJ17), (K17*1.1+P17+Q17+S17+U17)*AA17, L17*AJ17) ) -> 0 | S17: =IF((K17*AB17)>(L17*AK17),(K17*AB17),(L17*AK17)) -> 0 | T17: =IF((K17*AC17)>(L17*AL17),(K17*AC17),(L17*AL17)) -> 0 | U17: =IF((K17*AD17)>(L17*AM17),(K17*AD17),(L17*AM17)) -> 0 | V17: =IF((K17*AE17)>(L17*AN17),(K17*AE17),(L17*AN17)) -> 0 | W17: =IF((K17*AF17)>(L17*AO17),(K17*AF17),(L17*AO17)) -> 0 | X17: =IF((((K17)*1.1+P17+Q17+S17+T17+U17+V17)*AG17)>(L17*AP17),(((K17)*1.1+P17+Q17+S17+T17+U17+V17)*AG17),(L17*AP17)) -> 0 | AZ17: =AZ16 -> 80
A18: 10063011 | B18: BASMATI RICE | E18: =IF(D18="SCL",G18,H18) -> 374 | G18: 268 | H18: =ROUND(I18,0) -> 374 | I18: =IF(AND(L18<>"",L18<>0),ROUND(J18/L18,0),0) -> 374 | J18: =IF(C18="SG",ROUND((P18+Q18+R18+T18+V18+W18+X18),0),ROUND((P18+Q18+R18+S18+U18+W18+X18),0)) -> 1781196 | K18: =SUMIF(ProductList!$F$4:$F$493,A18,ProductList!$BA$4:$BA$493) -> 2517592 | L18: =SUMIF(ProductList!$F$4:$F$493,A18,ProductList!$V$4:$V$493) -> 4760 | M18: =SUMIF(ProductList!$F$4:$F$493,A18,ProductList!$K$4:$K$493) -> 0 | N18: KG | O18: =IF(D18="SCL",100,AZ18) -> 80 | P18: =IF((K18*Y18)>(L18*AH18),(K18*Y18),(L18*AH18)) -> 0 | Q18: =IF((K18*Z18)>(L18*AI18),(K18*Z18),(L18*AI18)) -> 503518.4 | R18: =IF(C18="SG", IF(((K18*1.1+P18+Q18+T18+V18)*AA18)>(L18*AJ18), (K18*1.1+P18+Q18+T18+V18)*AA18, L18*AJ18), IF(((K18*1.1+P18+Q18+S18+U18)*AA18)>(L18*AJ18), (K18*1.1+P18+Q18+S18+U18)*AA18, L18*AJ18) ) -> 679749.84 | S18: =IF((K18*AB18)>(L18*AK18),(K18*AB18),(L18*AK18)) -> 251759.2 | T18: =IF((K18*AC18)>(L18*AL18),(K18*AC18),(L18*AL18)) -> 0 | U18: =IF((K18*AD18)>(L18*AM18),(K18*AD18),(L18*AM18)) -> 251759.2 | V18: =IF((K18*AE18)>(L18*AN18),(K18*AE18),(L18*AN18)) -> 0 | W18: =IF((K18*AF18)>(L18*AO18),(K18*AF18),(L18*AO18)) -> 0 | X18: =IF((((K18)*1.1+P18+Q18+S18+T18+U18+V18)*AG18)>(L18*AP18),(((K18)*1.1+P18+Q18+S18+T18+U18+V18)*AG18),(L18*AP18)) -> 94409.7 | Z18: 0.2 | AA18: 0.18 | AB18: 0.1 | AD18: 0.1 | AG18: 0.025 | AI18: 80 | AM18: 40 | AZ18: =AZ17 -> 80
A19: 10063019 | B19: RICE OTHERS | D19: SCL | E19: =IF(D19="SCL",G19,H19) -> 80 | F19: L | G19: 80 | H19: =ROUND(I19,0) -> 0 | I19: =IF(AND(L19<>"",L19<>0),ROUND(J19/L19,0),0) -> 0 | J19: =IF(C19="SG",ROUND((P19+Q19+R19+T19+V19+W19+X19),0),ROUND((P19+Q19+R19+S19+U19+W19+X19),0)) -> 0 | K19: =SUMIF(ProductList!$F$4:$F$493,A19,ProductList!$BA$4:$BA$493) -> 0 | L19: =SUMIF(ProductList!$F$4:$F$493,A19,ProductList!$V$4:$V$493) -> 0 | M19: =SUMIF(ProductList!$F$4:$F$493,A19,ProductList!$K$4:$K$493) -> 0 | N19: KG | O19: =IF(D19="SCL",100,AZ19) -> 100 | P19: =IF((K19*Y19)>(L19*AH19),(K19*Y19),(L19*AH19)) -> 0 | Q19: =IF((K19*Z19)>(L19*AI19),(K19*Z19),(L19*AI19)) -> 0 | R19: =IF(C19="SG", IF(((K19*1.1+P19+Q19+T19+V19)*AA19)>(L19*AJ19), (K19*1.1+P19+Q19+T19+V19)*AA19, L19*AJ19), IF(((K19*1.1+P19+Q19+S19+U19)*AA19)>(L19*AJ19), (K19*1.1+P19+Q19+S19+U19)*AA19, L19*AJ19) ) -> 0 | S19: =IF((K19*AB19)>(L19*AK19),(K19*AB19),(L19*AK19)) -> 0 | T19: =IF((K19*AC19)>(L19*AL19),(K19*AC19),(L19*AL19)) -> 0 | U19: =IF((K19*AD19)>(L19*AM19),(K19*AD19),(L19*AM19)) -> 0 | V19: =IF((K19*AE19)>(L19*AN19),(K19*AE19),(L19*AN19)) -> 0 | W19: =IF((K19*AF19)>(L19*AO19),(K19*AF19),(L19*AO19)) -> 0 | X19: =IF((((K19)*1.1+P19+Q19+S19+T19+U19+V19)*AG19)>(L19*AP19),(((K19)*1.1+P19+Q19+S19+T19+U19+V19)*AG19),(L19*AP19)) -> 0 | Z19: 0.2 | AA19: 0.18 | AB19: 0.1 | AD19: 0.1 | AG19: 0.025 | AI19: 80 | AM19: 40 | AZ19: =AZ18 -> 80
A20: 10082190 | B20: MILLETS - OTHERS | D20: SCL | E20: =IF(D20="SCL",G20,H20) -> 300 | G20: 300 | H20: =ROUND(I20,0) -> 0 | I20: =IF(AND(L20<>"",L20<>0),ROUND(J20/L20,0),0) -> 0 | J20: =IF(C20="SG",ROUND((P20+Q20+R20+T20+V20+W20+X20),0),ROUND((P20+Q20+R20+S20+U20+W20+X20),0)) -> 0 | K20: =SUMIF(ProductList!$F$4:$F$493,A20,ProductList!$BA$4:$BA$493) -> 0 | L20: =SUMIF(ProductList!$F$4:$F$493,A20,ProductList!$V$4:$V$493) -> 0 | M20: =SUMIF(ProductList!$F$4:$F$493,A20,ProductList!$K$4:$K$493) -> 0 | N20: KG | O20: =IF(D20="SCL",100,AZ20) -> 100 | P20: =IF((K20*Y20)>(L20*AH20),(K20*Y20),(L20*AH20)) -> 0 | Q20: =IF((K20*Z20)>(L20*AI20),(K20*Z20),(L20*AI20)) -> 0 | R20: =IF(C20="SG", IF(((K20*1.1+P20+Q20+T20+V20)*AA20)>(L20*AJ20), (K20*1.1+P20+Q20+T20+V20)*AA20, L20*AJ20), IF(((K20*1.1+P20+Q20+S20+U20)*AA20)>(L20*AJ20), (K20*1.1+P20+Q20+S20+U20)*AA20, L20*AJ20) ) -> 0 | S20: =IF((K20*AB20)>(L20*AK20),(K20*AB20),(L20*AK20)) -> 0 | T20: =IF((K20*AC20)>(L20*AL20),(K20*AC20),(L20*AL20)) -> 0 | U20: =IF((K20*AD20)>(L20*AM20),(K20*AD20),(L20*AM20)) -> 0 | V20: =IF((K20*AE20)>(L20*AN20),(K20*AE20),(L20*AN20)) -> 0 | W20: =IF((K20*AF20)>(L20*AO20),(K20*AF20),(L20*AO20)) -> 0 | X20: =IF((((K20)*1.1+P20+Q20+S20+T20+U20+V20)*AG20)>(L20*AP20),(((K20)*1.1+P20+Q20+S20+T20+U20+V20)*AG20),(L20*AP20)) -> 0 | Z20: 0.2 | AA20: 0.18 | AD20: 0.1 | AG20: 0.025 | AZ20: =AZ19 -> 80
A21: 10089090 | B21: MILLETS | E21: =IF(D21="SCL",G21,H21) -> 0 | G21: 107 | H21: =ROUND(I21,0) -> 0 | I21: =IF(AND(L21<>"",L21<>0),ROUND(J21/L21,0),0) -> 0 | J21: =IF(C21="SG",ROUND((P21+Q21+R21+T21+V21+W21+X21),0),ROUND((P21+Q21+R21+S21+U21+W21+X21),0)) -> 0 | K21: =SUMIF(ProductList!$F$4:$F$493,A21,ProductList!$BA$4:$BA$493) -> 0 | L21: =SUMIF(ProductList!$F$4:$F$493,A21,ProductList!$V$4:$V$493) -> 0 | M21: =SUMIF(ProductList!$F$4:$F$493,A21,ProductList!$K$4:$K$493) -> 0 | N21: KG | O21: =IF(D21="SCL",100,AZ21) -> 80 | P21: =IF((K21*Y21)>(L21*AH21),(K21*Y21),(L21*AH21)) -> 0 | Q21: =IF((K21*Z21)>(L21*AI21),(K21*Z21),(L21*AI21)) -> 0 | R21: =IF(C21="SG", IF(((K21*1.1+P21+Q21+T21+V21)*AA21)>(L21*AJ21), (K21*1.1+P21+Q21+T21+V21)*AA21, L21*AJ21), IF(((K21*1.1+P21+Q21+S21+U21)*AA21)>(L21*AJ21), (K21*1.1+P21+Q21+S21+U21)*AA21, L21*AJ21) ) -> 0 | S21: =IF((K21*AB21)>(L21*AK21),(K21*AB21),(L21*AK21)) -> 0 | T21: =IF((K21*AC21)>(L21*AL21),(K21*AC21),(L21*AL21)) -> 0 | U21: =IF((K21*AD21)>(L21*AM21),(K21*AD21),(L21*AM21)) -> 0 | V21: =IF((K21*AE21)>(L21*AN21),(K21*AE21),(L21*AN21)) -> 0 | W21: =IF((K21*AF21)>(L21*AO21),(K21*AF21),(L21*AO21)) -> 0 | X21: =IF((((K21)*1.1+P21+Q21+S21+T21+U21+V21)*AG21)>(L21*AP21),(((K21)*1.1+P21+Q21+S21+T21+U21+V21)*AG21),(L21*AP21)) -> 0 | AZ21: =AZ20 -> 80
A22: 11031110 | B22: WHEAT GROATS | D22: NORM | E22: =IF(D22="SCL",G22,H22) -> 0 | F22: L | G22: 159 | H22: =ROUND(I22,0) -> 0 | I22: =IF(AND(L22<>"",L22<>0),ROUND(J22/L22,0),0) -> 0 | J22: =IF(C22="SG",ROUND((P22+Q22+R22+T22+V22+W22+X22),0),ROUND((P22+Q22+R22+S22+U22+W22+X22),0)) -> 0 | K22: =SUMIF(ProductList!$F$4:$F$493,A22,ProductList!$BA$4:$BA$493) -> 0 | L22: =SUMIF(ProductList!$F$4:$F$493,A22,ProductList!$V$4:$V$493) -> 0 | M22: =SUMIF(ProductList!$F$4:$F$493,A22,ProductList!$K$4:$K$493) -> 0 | N22: KG | O22: =IF(D22="SCL",100,AZ22) -> 80 | P22: =IF((K22*Y22)>(L22*AH22),(K22*Y22),(L22*AH22)) -> 0 | Q22: =IF((K22*Z22)>(L22*AI22),(K22*Z22),(L22*AI22)) -> 0 | R22: =IF(C22="SG", IF(((K22*1.1+P22+Q22+T22+V22)*AA22)>(L22*AJ22), (K22*1.1+P22+Q22+T22+V22)*AA22, L22*AJ22), IF(((K22*1.1+P22+Q22+S22+U22)*AA22)>(L22*AJ22), (K22*1.1+P22+Q22+S22+U22)*AA22, L22*AJ22) ) -> 0 | S22: =IF((K22*AB22)>(L22*AK22),(K22*AB22),(L22*AK22)) -> 0 | T22: =IF((K22*AC22)>(L22*AL22),(K22*AC22),(L22*AL22)) -> 0 | U22: =IF((K22*AD22)>(L22*AM22),(K22*AD22),(L22*AM22)) -> 0 | V22: =IF((K22*AE22)>(L22*AN22),(K22*AE22),(L22*AN22)) -> 0 | W22: =IF((K22*AF22)>(L22*AO22),(K22*AF22),(L22*AO22)) -> 0 | X22: =IF((((K22)*1.1+P22+Q22+S22+T22+U22+V22)*AG22)>(L22*AP22),(((K22)*1.1+P22+Q22+S22+T22+U22+V22)*AG22),(L22*AP22)) -> 0 | Z22: 0.2 | AA22: 0.18 | AB22: 0.1 | AD22: 0.25 | AG22: 0.025 | AZ22: =AZ21 -> 80
A23: 11032000 | B23: RICE PELLETS | E23: =IF(D23="SCL",G23,H23) -> 0 | F23: L | H23: =ROUND(I23,0) -> 0 | I23: =IF(AND(L23<>"",L23<>0),ROUND(J23/L23,0),0) -> 0 | J23: =IF(C23="SG",ROUND((P23+Q23+R23+T23+V23+W23+X23),0),ROUND((P23+Q23+R23+S23+U23+W23+X23),0)) -> 0 | K23: =SUMIF(ProductList!$F$4:$F$493,A23,ProductList!$BA$4:$BA$493) -> 0 | L23: =SUMIF(ProductList!$F$4:$F$493,A23,ProductList!$V$4:$V$493) -> 0 | M23: =SUMIF(ProductList!$F$4:$F$493,A23,ProductList!$K$4:$K$493) -> 0 | N23: KG | O23: =IF(D23="SCL",100,AZ23) -> 80 | P23: =IF((K23*Y23)>(L23*AH23),(K23*Y23),(L23*AH23)) -> 0 | Q23: =IF((K23*Z23)>(L23*AI23),(K23*Z23),(L23*AI23)) -> 0 | R23: =IF(C23="SG", IF(((K23*1.1+P23+Q23+T23+V23)*AA23)>(L23*AJ23), (K23*1.1+P23+Q23+T23+V23)*AA23, L23*AJ23), IF(((K23*1.1+P23+Q23+S23+U23)*AA23)>(L23*AJ23), (K23*1.1+P23+Q23+S23+U23)*AA23, L23*AJ23) ) -> 0 | S23: =IF((K23*AB23)>(L23*AK23),(K23*AB23),(L23*AK23)) -> 0 | T23: =IF((K23*AC23)>(L23*AL23),(K23*AC23),(L23*AL23)) -> 0 | U23: =IF((K23*AD23)>(L23*AM23),(K23*AD23),(L23*AM23)) -> 0 | V23: =IF((K23*AE23)>(L23*AN23),(K23*AE23),(L23*AN23)) -> 0 | W23: =IF((K23*AF23)>(L23*AO23),(K23*AF23),(L23*AO23)) -> 0 | X23: =IF((((K23)*1.1+P23+Q23+S23+T23+U23+V23)*AG23)>(L23*AP23),(((K23)*1.1+P23+Q23+S23+T23+U23+V23)*AG23),(L23*AP23)) -> 0 | Z23: 0.2 | AA23: 0.18 | AD23: 0.1 | AG23: 0.025 | AZ23: =AZ22 -> 80
A24: 11042900 | E24: =IF(D24="SCL",G24,H24) -> 0 | G24: 334 | H24: =ROUND(I24,0) -> 0 | I24: =IF(AND(L24<>"",L24<>0),ROUND(J24/L24,0),0) -> 0 | J24: =IF(C24="SG",ROUND((P24+Q24+R24+T24+V24+W24+X24),0),ROUND((P24+Q24+R24+S24+U24+W24+X24),0)) -> 0 | K24: =SUMIF(ProductList!$F$4:$F$493,A24,ProductList!$BA$4:$BA$493) -> 0 | L24: =SUMIF(ProductList!$F$4:$F$493,A24,ProductList!$V$4:$V$493) -> 0 | M24: =SUMIF(ProductList!$F$4:$F$493,A24,ProductList!$K$4:$K$493) -> 0 | N24: KG | O24: =IF(D24="SCL",100,AZ24) -> 80 | P24: =IF((K24*Y24)>(L24*AH24),(K24*Y24),(L24*AH24)) -> 0 | Q24: =IF((K24*Z24)>(L24*AI24),(K24*Z24),(L24*AI24)) -> 0 | R24: =IF(C24="SG", IF(((K24*1.1+P24+Q24+T24+V24)*AA24)>(L24*AJ24), (K24*1.1+P24+Q24+T24+V24)*AA24, L24*AJ24), IF(((K24*1.1+P24+Q24+S24+U24)*AA24)>(L24*AJ24), (K24*1.1+P24+Q24+S24+U24)*AA24, L24*AJ24) ) -> 0 | S24: =IF((K24*AB24)>(L24*AK24),(K24*AB24),(L24*AK24)) -> 0 | T24: =IF((K24*AC24)>(L24*AL24),(K24*AC24),(L24*AL24)) -> 0 | U24: =IF((K24*AD24)>(L24*AM24),(K24*AD24),(L24*AM24)) -> 0 | V24: =IF((K24*AE24)>(L24*AN24),(K24*AE24),(L24*AN24)) -> 0 | W24: =IF((K24*AF24)>(L24*AO24),(K24*AF24),(L24*AO24)) -> 0 | X24: =IF((((K24)*1.1+P24+Q24+S24+T24+U24+V24)*AG24)>(L24*AP24),(((K24)*1.1+P24+Q24+S24+T24+U24+V24)*AG24),(L24*AP24)) -> 0 | AZ24: =AZ23 -> 80
A25: 11043000 | B25: GROUNDED CEREALS | D25: NORM | E25: =IF(D25="SCL",G25,H25) -> 0 | H25: =ROUND(I25,0) -> 0 | I25: =IF(AND(L25<>"",L25<>0),ROUND(J25/L25,0),0) -> 0 | J25: =IF(C25="SG",ROUND((P25+Q25+R25+T25+V25+W25+X25),0),ROUND((P25+Q25+R25+S25+U25+W25+X25),0)) -> 0 | K25: =SUMIF(ProductList!$F$4:$F$493,A25,ProductList!$BA$4:$BA$493) -> 0 | L25: =SUMIF(ProductList!$F$4:$F$493,A25,ProductList!$V$4:$V$493) -> 0 | M25: =SUMIF(ProductList!$F$4:$F$493,A25,ProductList!$K$4:$K$493) -> 0 | N25: KG | O25: =IF(D25="SCL",100,AZ25) -> 80 | P25: =IF((K25*Y25)>(L25*AH25),(K25*Y25),(L25*AH25)) -> 0 | Q25: =IF((K25*Z25)>(L25*AI25),(K25*Z25),(L25*AI25)) -> 0 | R25: =IF(C25="SG", IF(((K25*1.1+P25+Q25+T25+V25)*AA25)>(L25*AJ25), (K25*1.1+P25+Q25+T25+V25)*AA25, L25*AJ25), IF(((K25*1.1+P25+Q25+S25+U25)*AA25)>(L25*AJ25), (K25*1.1+P25+Q25+S25+U25)*AA25, L25*AJ25) ) -> 0 | S25: =IF((K25*AB25)>(L25*AK25),(K25*AB25),(L25*AK25)) -> 0 | T25: =IF((K25*AC25)>(L25*AL25),(K25*AC25),(L25*AL25)) -> 0 | U25: =IF((K25*AD25)>(L25*AM25),(K25*AD25),(L25*AM25)) -> 0 | V25: =IF((K25*AE25)>(L25*AN25),(K25*AE25),(L25*AN25)) -> 0 | W25: =IF((K25*AF25)>(L25*AO25),(K25*AF25),(L25*AO25)) -> 0 | X25: =IF((((K25)*1.1+P25+Q25+S25+T25+U25+V25)*AG25)>(L25*AP25),(((K25)*1.1+P25+Q25+S25+T25+U25+V25)*AG25),(L25*AP25)) -> 0 | Z25: 0.2 | AA25: 0.18 | AD25: 0.25 | AG25: 0.025 | AI25: 65 | AM25: 80 | AZ25: =AZ24 -> 80
A26: 11061010 | B26: BLACK - GRAM FLOUR | E26: =IF(D26="SCL",G26,H26) -> 0 | F26: L | H26: =ROUND(I26,0) -> 0 | I26: =IF(AND(L26<>"",L26<>0),ROUND(J26/L26,0),0) -> 0 | J26: =IF(C26="SG",ROUND((P26+Q26+R26+T26+V26+W26+X26),0),ROUND((P26+Q26+R26+S26+U26+W26+X26),0)) -> 0 | K26: =SUMIF(ProductList!$F$4:$F$493,A26,ProductList!$BA$4:$BA$493) -> 0 | L26: =SUMIF(ProductList!$F$4:$F$493,A26,ProductList!$V$4:$V$493) -> 0 | M26: =SUMIF(ProductList!$F$4:$F$493,A26,ProductList!$K$4:$K$493) -> 0 | N26: KG | O26: =IF(D26="SCL",100,AZ26) -> 80 | P26: =IF((K26*Y26)>(L26*AH26),(K26*Y26),(L26*AH26)) -> 0 | Q26: =IF((K26*Z26)>(L26*AI26),(K26*Z26),(L26*AI26)) -> 0 | R26: =IF(C26="SG", IF(((K26*1.1+P26+Q26+T26+V26)*AA26)>(L26*AJ26), (K26*1.1+P26+Q26+T26+V26)*AA26, L26*AJ26), IF(((K26*1.1+P26+Q26+S26+U26)*AA26)>(L26*AJ26), (K26*1.1+P26+Q26+S26+U26)*AA26, L26*AJ26) ) -> 0 | S26: =IF((K26*AB26)>(L26*AK26),(K26*AB26),(L26*AK26)) -> 0 | T26: =IF((K26*AC26)>(L26*AL26),(K26*AC26),(L26*AL26)) -> 0 | U26: =IF((K26*AD26)>(L26*AM26),(K26*AD26),(L26*AM26)) -> 0 | V26: =IF((K26*AE26)>(L26*AN26),(K26*AE26),(L26*AN26)) -> 0 | W26: =IF((K26*AF26)>(L26*AO26),(K26*AF26),(L26*AO26)) -> 0 | X26: =IF((((K26)*1.1+P26+Q26+S26+T26+U26+V26)*AG26)>(L26*AP26),(((K26)*1.1+P26+Q26+S26+T26+U26+V26)*AG26),(L26*AP26)) -> 0 | Z26: 0.2 | AA26: 0.18 | AG26: 0.025 | AZ26: =AZ25 -> 80
A27: 13012000 | B27: GUM ARABIC | D27: NORM | E27: =IF(D27="SCL",G27,H27) -> 1130 | H27: =ROUND(I27,0) -> 1130 | I27: =IF(AND(L27<>"",L27<>0),ROUND(J27/L27,0),0) -> 1130 | J27: =IF(C27="SG",ROUND((P27+Q27+R27+T27+V27+W27+X27),0),ROUND((P27+Q27+R27+S27+U27+W27+X27),0)) -> 67824 | K27: =SUMIF(ProductList!$F$4:$F$493,A27,ProductList!$BA$4:$BA$493) -> 195178.4 | L27: =SUMIF(ProductList!$F$4:$F$493,A27,ProductList!$V$4:$V$493) -> 60 | M27: =SUMIF(ProductList!$F$4:$F$493,A27,ProductList!$K$4:$K$493) -> 0 | N27: KG | O27: =IF(D27="SCL",100,AZ27) -> 80 | P27: =IF((K27*Y27)>(L27*AH27),(K27*Y27),(L27*AH27)) -> 0 | Q27: =IF((K27*Z27)>(L27*AI27),(K27*Z27),(L27*AI27)) -> 0 | R27: =IF(C27="SG", IF(((K27*1.1+P27+Q27+T27+V27)*AA27)>(L27*AJ27), (K27*1.1+P27+Q27+T27+V27)*AA27, L27*AJ27), IF(((K27*1.1+P27+Q27+S27+U27)*AA27)>(L27*AJ27), (K27*1.1+P27+Q27+S27+U27)*AA27, L27*AJ27) ) -> 42158.534 | S27: =IF((K27*AB27)>(L27*AK27),(K27*AB27),(L27*AK27)) -> 19517.84 | T27: =IF((K27*AC27)>(L27*AL27),(K27*AC27),(L27*AL27)) -> 11710.704 | U27: =IF((K27*AD27)>(L27*AM27),(K27*AD27),(L27*AM27)) -> 0 | V27: =IF((K27*AE27)>(L27*AN27),(K27*AE27),(L27*AN27)) -> 0 | W27: =IF((K27*AF27)>(L27*AO27),(K27*AF27),(L27*AO27)) -> 0 | X27: =IF((((K27)*1.1+P27+Q27+S27+T27+U27+V27)*AG27)>(L27*AP27),(((K27)*1.1+P27+Q27+S27+T27+U27+V27)*AG27),(L27*AP27)) -> 6148.1196 | AA27: 0.18 | AB27: 0.1 | AC27: 0.06 | AG27: 0.025 | AZ27: =AZ26 -> 80
A28: 15089000 | B28: GROUNDNUT OIL | D28: NORM | E28: =IF(D28="SCL",G28,H28) -> 0 | F28: S | H28: =ROUND(I28,0) -> 0 | I28: =IF(AND(L28<>"",L28<>0),ROUND(J28/L28,0),0) -> 0 | J28: =IF(C28="SG",ROUND((P28+Q28+R28+T28+V28+W28+X28),0),ROUND((P28+Q28+R28+S28+U28+W28+X28),0)) -> 0 | K28: =SUMIF(ProductList!$F$4:$F$493,A28,ProductList!$BA$4:$BA$493) -> 0 | L28: =SUMIF(ProductList!$F$4:$F$493,A28,ProductList!$V$4:$V$493) -> 0 | M28: =SUMIF(ProductList!$F$4:$F$493,A28,ProductList!$K$4:$K$493) -> 0 | N28: KG | O28: =IF(D28="SCL",100,AZ28) -> 80 | P28: =IF((K28*Y28)>(L28*AH28),(K28*Y28),(L28*AH28)) -> 0 | Q28: =IF((K28*Z28)>(L28*AI28),(K28*Z28),(L28*AI28)) -> 0 | R28: =IF(C28="SG", IF(((K28*1.1+P28+Q28+T28+V28)*AA28)>(L28*AJ28), (K28*1.1+P28+Q28+T28+V28)*AA28, L28*AJ28), IF(((K28*1.1+P28+Q28+S28+U28)*AA28)>(L28*AJ28), (K28*1.1+P28+Q28+S28+U28)*AA28, L28*AJ28) ) -> 0 | S28: =IF((K28*AB28)>(L28*AK28),(K28*AB28),(L28*AK28)) -> 0 | T28: =IF((K28*AC28)>(L28*AL28),(K28*AC28),(L28*AL28)) -> 0 | U28: =IF((K28*AD28)>(L28*AM28),(K28*AD28),(L28*AM28)) -> 0 | V28: =IF((K28*AE28)>(L28*AN28),(K28*AE28),(L28*AN28)) -> 0 | W28: =IF((K28*AF28)>(L28*AO28),(K28*AF28),(L28*AO28)) -> 0 | X28: =IF((((K28)*1.1+P28+Q28+S28+T28+U28+V28)*AG28)>(L28*AP28),(((K28)*1.1+P28+Q28+S28+T28+U28+V28)*AG28),(L28*AP28)) -> 0 | Z28: 0.2 | AA28: 0.18 | AD28: 0.1 | AI28: 105 | AM28: 75 | AZ28: =AZ27 -> 80
A29: 15149900 | B29: MUSTARD OIL | E29: =IF(D29="SCL",G29,H29) -> 0 | G29: 357 | H29: =ROUND(I29,0) -> 0 | I29: =IF(AND(L29<>"",L29<>0),ROUND(J29/L29,0),0) -> 0 | J29: =IF(C29="SG",ROUND((P29+Q29+R29+T29+V29+W29+X29),0),ROUND((P29+Q29+R29+S29+U29+W29+X29),0)) -> 0 | K29: =SUMIF(ProductList!$F$4:$F$493,A29,ProductList!$BA$4:$BA$493) -> 0 | L29: =SUMIF(ProductList!$F$4:$F$493,A29,ProductList!$V$4:$V$493) -> 0 | M29: =SUMIF(ProductList!$F$4:$F$493,A29,ProductList!$K$4:$K$493) -> 0 | N29: KG | O29: =IF(D29="SCL",100,AZ29) -> 80 | P29: =IF((K29*Y29)>(L29*AH29),(K29*Y29),(L29*AH29)) -> 0 | Q29: =IF((K29*Z29)>(L29*AI29),(K29*Z29),(L29*AI29)) -> 0 | R29: =IF(C29="SG", IF(((K29*1.1+P29+Q29+T29+V29)*AA29)>(L29*AJ29), (K29*1.1+P29+Q29+T29+V29)*AA29, L29*AJ29), IF(((K29*1.1+P29+Q29+S29+U29)*AA29)>(L29*AJ29), (K29*1.1+P29+Q29+S29+U29)*AA29, L29*AJ29) ) -> 0 | S29: =IF((K29*AB29)>(L29*AK29),(K29*AB29),(L29*AK29)) -> 0 | T29: =IF((K29*AC29)>(L29*AL29),(K29*AC29),(L29*AL29)) -> 0 | U29: =IF((K29*AD29)>(L29*AM29),(K29*AD29),(L29*AM29)) -> 0 | V29: =IF((K29*AE29)>(L29*AN29),(K29*AE29),(L29*AN29)) -> 0 | W29: =IF((K29*AF29)>(L29*AO29),(K29*AF29),(L29*AO29)) -> 0 | X29: =IF((((K29)*1.1+P29+Q29+S29+T29+U29+V29)*AG29)>(L29*AP29),(((K29)*1.1+P29+Q29+S29+T29+U29+V29)*AG29),(L29*AP29)) -> 0 | Z29: 0.2 | AA29: 0.18 | AB29: 0.1 | AD29: 0.1 | AG29: 0.025 | AI29: 110 | AM29: 75 | AZ29: =AZ28 -> 80
A30: 151530 | B30: CASTOR OIL AND ITS FRACTIONS | D30: NORM | E30: =IF(D30="SCL",G30,H30) -> 0 | H30: =ROUND(I30,0) -> 0 | I30: =IF(AND(L30<>"",L30<>0),ROUND(J30/L30,0),0) -> 0 | J30: =IF(C30="SG",ROUND((P30+Q30+R30+T30+V30+W30+X30),0),ROUND((P30+Q30+R30+S30+U30+W30+X30),0)) -> 0 | K30: =SUMIF(ProductList!$F$4:$F$493,A30,ProductList!$BA$4:$BA$493) -> 0 | L30: =SUMIF(ProductList!$F$4:$F$493,A30,ProductList!$V$4:$V$493) -> 0 | M30: =SUMIF(ProductList!$F$4:$F$493,A30,ProductList!$K$4:$K$493) -> 0 | N30: KG | O30: =IF(D30="SCL",100,AZ30) -> 80 | P30: =IF((K30*Y30)>(L30*AH30),(K30*Y30),(L30*AH30)) -> 0 | Q30: =IF((K30*Z30)>(L30*AI30),(K30*Z30),(L30*AI30)) -> 0 | R30: =IF(C30="SG", IF(((K30*1.1+P30+Q30+T30+V30)*AA30)>(L30*AJ30), (K30*1.1+P30+Q30+T30+V30)*AA30, L30*AJ30), IF(((K30*1.1+P30+Q30+S30+U30)*AA30)>(L30*AJ30), (K30*1.1+P30+Q30+S30+U30)*AA30, L30*AJ30) ) -> 0 | S30: =IF((K30*AB30)>(L30*AK30),(K30*AB30),(L30*AK30)) -> 0 | T30: =IF((K30*AC30)>(L30*AL30),(K30*AC30),(L30*AL30)) -> 0 | U30: =IF((K30*AD30)>(L30*AM30),(K30*AD30),(L30*AM30)) -> 0 | V30: =IF((K30*AE30)>(L30*AN30),(K30*AE30),(L30*AN30)) -> 0 | W30: =IF((K30*AF30)>(L30*AO30),(K30*AF30),(L30*AO30)) -> 0 | X30: =IF((((K30)*1.1+P30+Q30+S30+T30+U30+V30)*AG30)>(L30*AP30),(((K30)*1.1+P30+Q30+S30+T30+U30+V30)*AG30),(L30*AP30)) -> 0 | Z30: 0.2 | AA30: 0.18 | AB30: 0.1 | AC30: 0.06 | AD30: 0.1 | AG30: 0.025 | AM30: 110 | AN30: 12 | AZ30: =AZ29 -> 80
A31: 151550 | B31: GINGELLY OIL | D31: NORM | E31: =IF(D31="SCL",G31,H31) -> 0 | F31: S | G31: 507 | H31: =ROUND(I31,0) -> 0 | I31: =IF(AND(L31<>"",L31<>0),ROUND(J31/L31,0),0) -> 0 | J31: =IF(C31="SG",ROUND((P31+Q31+R31+T31+V31+W31+X31),0),ROUND((P31+Q31+R31+S31+U31+W31+X31),0)) -> 0 | K31: =SUMIF(ProductList!$F$4:$F$493,A31,ProductList!$BA$4:$BA$493) -> 0 | L31: =SUMIF(ProductList!$F$4:$F$493,A31,ProductList!$V$4:$V$493) -> 0 | M31: =SUMIF(ProductList!$F$4:$F$493,A31,ProductList!$K$4:$K$493) -> 0 | N31: KG | O31: =IF(D31="SCL",100,AZ31) -> 80 | P31: =IF((K31*Y31)>(L31*AH31),(K31*Y31),(L31*AH31)) -> 0 | Q31: =IF((K31*Z31)>(L31*AI31),(K31*Z31),(L31*AI31)) -> 0 | R31: =IF(C31="SG", IF(((K31*1.1+P31+Q31+T31+V31)*AA31)>(L31*AJ31), (K31*1.1+P31+Q31+T31+V31)*AA31, L31*AJ31), IF(((K31*1.1+P31+Q31+S31+U31)*AA31)>(L31*AJ31), (K31*1.1+P31+Q31+S31+U31)*AA31, L31*AJ31) ) -> 0 | S31: =IF((K31*AB31)>(L31*AK31),(K31*AB31),(L31*AK31)) -> 0 | T31: =IF((K31*AC31)>(L31*AL31),(K31*AC31),(L31*AL31)) -> 0 | U31: =IF((K31*AD31)>(L31*AM31),(K31*AD31),(L31*AM31)) -> 0 | V31: =IF((K31*AE31)>(L31*AN31),(K31*AE31),(L31*AN31)) -> 0 | W31: =IF((K31*AF31)>(L31*AO31),(K31*AF31),(L31*AO31)) -> 0 | X31: =IF((((K31)*1.1+P31+Q31+S31+T31+U31+V31)*AG31)>(L31*AP31),(((K31)*1.1+P31+Q31+S31+T31+U31+V31)*AG31),(L31*AP31)) -> 0 | Z31: 0.2 | AA31: 0.18 | AB31: 0.1 | AC31: 0.06 | AG31: 0.025 | AM31: 30 | AN31: 12 | AZ31: =AZ30 -> 80
A32: 15162000 | B32: DALDA | D32: SCL | E32: =IF(D32="SCL",G32,H32) -> 160 | G32: 160 | H32: =ROUND(I32,0) -> 0 | I32: =IF(AND(L32<>"",L32<>0),ROUND(J32/L32,0),0) -> 0 | J32: =IF(C32="SG",ROUND((P32+Q32+R32+T32+V32+W32+X32),0),ROUND((P32+Q32+R32+S32+U32+W32+X32),0)) -> 0 | K32: =SUMIF(ProductList!$F$4:$F$493,A32,ProductList!$BA$4:$BA$493) -> 0 | L32: =SUMIF(ProductList!$F$4:$F$493,A32,ProductList!$V$4:$V$493) -> 0 | M32: =SUMIF(ProductList!$F$4:$F$493,A32,ProductList!$K$4:$K$493) -> 0 | N32: KG | O32: =IF(D32="SCL",100,AZ32) -> 100 | P32: =IF((K32*Y32)>(L32*AH32),(K32*Y32),(L32*AH32)) -> 0 | Q32: =IF((K32*Z32)>(L32*AI32),(K32*Z32),(L32*AI32)) -> 0 | R32: =IF(C32="SG", IF(((K32*1.1+P32+Q32+T32+V32)*AA32)>(L32*AJ32), (K32*1.1+P32+Q32+T32+V32)*AA32, L32*AJ32), IF(((K32*1.1+P32+Q32+S32+U32)*AA32)>(L32*AJ32), (K32*1.1+P32+Q32+S32+U32)*AA32, L32*AJ32) ) -> 0 | S32: =IF((K32*AB32)>(L32*AK32),(K32*AB32),(L32*AK32)) -> 0 | T32: =IF((K32*AC32)>(L32*AL32),(K32*AC32),(L32*AL32)) -> 0 | U32: =IF((K32*AD32)>(L32*AM32),(K32*AD32),(L32*AM32)) -> 0 | V32: =IF((K32*AE32)>(L32*AN32),(K32*AE32),(L32*AN32)) -> 0 | W32: =IF((K32*AF32)>(L32*AO32),(K32*AF32),(L32*AO32)) -> 0 | X32: =IF((((K32)*1.1+P32+Q32+S32+T32+U32+V32)*AG32)>(L32*AP32),(((K32)*1.1+P32+Q32+S32+T32+U32+V32)*AG32),(L32*AP32)) -> 0 | Z32: 0.15 | AA32: 0.18 | AG32: 0.025 | AI32: 120 | AM32: 145 | AZ32: =AZ31 -> 80
A33: 17029021 | B33: JAGGARY AND JAGGARY POWDER, PALM SUGAR | C33: NORM | D33: NORM | E33: =IF(D33="SCL",G33,H33) -> 0 | G33: 364 | H33: =ROUND(I33,0) -> 0 | I33: =IF(AND(L33<>"",L33<>0),ROUND(J33/L33,0),0) -> 0 | J33: =IF(C33="SG",ROUND((P33+Q33+R33+T33+V33+W33+X33),0),ROUND((P33+Q33+R33+S33+U33+W33+X33),0)) -> 0 | K33: =SUMIF(ProductList!$F$4:$F$493,A33,ProductList!$BA$4:$BA$493) -> 0 | L33: =SUMIF(ProductList!$F$4:$F$493,A33,ProductList!$V$4:$V$493) -> 0 | M33: =SUMIF(ProductList!$F$4:$F$493,A33,ProductList!$K$4:$K$493) -> 0 | N33: KG | O33: =IF(D33="SCL",100,AZ33) -> 80 | P33: =IF((K33*Y33)>(L33*AH33),(K33*Y33),(L33*AH33)) -> 0 | Q33: =IF((K33*Z33)>(L33*AI33),(K33*Z33),(L33*AI33)) -> 0 | R33: =IF(C33="SG", IF(((K33*1.1+P33+Q33+T33+V33)*AA33)>(L33*AJ33), (K33*1.1+P33+Q33+T33+V33)*AA33, L33*AJ33), IF(((K33*1.1+P33+Q33+S33+U33)*AA33)>(L33*AJ33), (K33*1.1+P33+Q33+S33+U33)*AA33, L33*AJ33) ) -> 0 | S33: =IF((K33*AB33)>(L33*AK33),(K33*AB33),(L33*AK33)) -> 0 | T33: =IF((K33*AC33)>(L33*AL33),(K33*AC33),(L33*AL33)) -> 0 | U33: =IF((K33*AD33)>(L33*AM33),(K33*AD33),(L33*AM33)) -> 0 | V33: =IF((K33*AE33)>(L33*AN33),(K33*AE33),(L33*AN33)) -> 0 | W33: =IF((K33*AF33)>(L33*AO33),(K33*AF33),(L33*AO33)) -> 0 | X33: =IF((((K33)*1.1+P33+Q33+S33+T33+U33+V33)*AG33)>(L33*AP33),(((K33)*1.1+P33+Q33+S33+T33+U33+V33)*AG33),(L33*AP33)) -> 0 | Z33: 0.2 | AA33: 0.18 | AB33: 0.1 | AC33: 0.06 | AG33: 0.025 | AM33: 180 | AN33: 200 | AZ33: =AZ32 -> 80
A34: 17029090 | B34: SUGAR BASED SNACK ITEM | D34: NORM | E34: =IF(D34="SCL",G34,H34) -> 0 | H34: =ROUND(I34,0) -> 0 | I34: =IF(AND(L34<>"",L34<>0),ROUND(J34/L34,0),0) -> 0 | J34: =IF(C34="SG",ROUND((P34+Q34+R34+T34+V34+W34+X34),0),ROUND((P34+Q34+R34+S34+U34+W34+X34),0)) -> 0 | K34: =SUMIF(ProductList!$F$4:$F$493,A34,ProductList!$BA$4:$BA$493) -> 0 | L34: =SUMIF(ProductList!$F$4:$F$493,A34,ProductList!$V$4:$V$493) -> 0 | M34: =SUMIF(ProductList!$F$4:$F$493,A34,ProductList!$K$4:$K$493) -> 0 | N34: KG | O34: =IF(D34="SCL",100,AZ34) -> 80 | P34: =IF((K34*Y34)>(L34*AH34),(K34*Y34),(L34*AH34)) -> 0 | Q34: =IF((K34*Z34)>(L34*AI34),(K34*Z34),(L34*AI34)) -> 0 | R34: =IF(C34="SG", IF(((K34*1.1+P34+Q34+T34+V34)*AA34)>(L34*AJ34), (K34*1.1+P34+Q34+T34+V34)*AA34, L34*AJ34), IF(((K34*1.1+P34+Q34+S34+U34)*AA34)>(L34*AJ34), (K34*1.1+P34+Q34+S34+U34)*AA34, L34*AJ34) ) -> 0 | S34: =IF((K34*AB34)>(L34*AK34),(K34*AB34),(L34*AK34)) -> 0 | T34: =IF((K34*AC34)>(L34*AL34),(K34*AC34),(L34*AL34)) -> 0 | U34: =IF((K34*AD34)>(L34*AM34),(K34*AD34),(L34*AM34)) -> 0 | V34: =IF((K34*AE34)>(L34*AN34),(K34*AE34),(L34*AN34)) -> 0 | W34: =IF((K34*AF34)>(L34*AO34),(K34*AF34),(L34*AO34)) -> 0 | X34: =IF((((K34)*1.1+P34+Q34+S34+T34+U34+V34)*AG34)>(L34*AP34),(((K34)*1.1+P34+Q34+S34+T34+U34+V34)*AG34),(L34*AP34)) -> 0 | Z34: 0.2 | AA34: 0.18 | AB34: 0.1 | AC34: 0.06 | AG34: 0.025 | AM34: 180 | AN34: 200 | AZ34: =AZ33 -> 80
A35: 17049090 | B35: SUGAR CANDY | E35: =IF(D35="SCL",G35,H35) -> 0 | F35: S | H35: =ROUND(I35,0) -> 0 | I35: =IF(AND(L35<>"",L35<>0),ROUND(J35/L35,0),0) -> 0 | J35: =IF(C35="SG",ROUND((P35+Q35+R35+T35+V35+W35+X35),0),ROUND((P35+Q35+R35+S35+U35+W35+X35),0)) -> 0 | K35: =SUMIF(ProductList!$F$4:$F$493,A35,ProductList!$BA$4:$BA$493) -> 0 | L35: =SUMIF(ProductList!$F$4:$F$493,A35,ProductList!$V$4:$V$493) -> 0 | M35: =SUMIF(ProductList!$F$4:$F$493,A35,ProductList!$K$4:$K$493) -> 0 | N35: KG | O35: =IF(D35="SCL",100,AZ35) -> 80 | P35: =IF((K35*Y35)>(L35*AH35),(K35*Y35),(L35*AH35)) -> 0 | Q35: =IF((K35*Z35)>(L35*AI35),(K35*Z35),(L35*AI35)) -> 0 | R35: =IF(C35="SG", IF(((K35*1.1+P35+Q35+T35+V35)*AA35)>(L35*AJ35), (K35*1.1+P35+Q35+T35+V35)*AA35, L35*AJ35), IF(((K35*1.1+P35+Q35+S35+U35)*AA35)>(L35*AJ35), (K35*1.1+P35+Q35+S35+U35)*AA35, L35*AJ35) ) -> 0 | S35: =IF((K35*AB35)>(L35*AK35),(K35*AB35),(L35*AK35)) -> 0 | T35: =IF((K35*AC35)>(L35*AL35),(K35*AC35),(L35*AL35)) -> 0 | U35: =IF((K35*AD35)>(L35*AM35),(K35*AD35),(L35*AM35)) -> 0 | V35: =IF((K35*AE35)>(L35*AN35),(K35*AE35),(L35*AN35)) -> 0 | W35: =IF((K35*AF35)>(L35*AO35),(K35*AF35),(L35*AO35)) -> 0 | X35: =IF((((K35)*1.1+P35+Q35+S35+T35+U35+V35)*AG35)>(L35*AP35),(((K35)*1.1+P35+Q35+S35+T35+U35+V35)*AG35),(L35*AP35)) -> 0 | Z35: 0.2 | AA35: 0.18 | AB35: 0.1 | AD35: 0.45 | AG35: 0.025 | AI35: 100 | AM35: 260 | AZ35: =AZ34 -> 80
A36: 19019099 | B36: HEALTH DRINK | D36: NORM | E36: =IF(D36="SCL",G36,H36) -> 0 | H36: =ROUND(I36,0) -> 0 | I36: =IF(AND(L36<>"",L36<>0),ROUND(J36/L36,0),0) -> 0 | J36: =IF(C36="SG",ROUND((P36+Q36+R36+T36+V36+W36+X36),0),ROUND((P36+Q36+R36+S36+U36+W36+X36),0)) -> 0 | K36: =SUMIF(ProductList!$F$4:$F$493,A36,ProductList!$BA$4:$BA$493) -> 0 | L36: =SUMIF(ProductList!$F$4:$F$493,A36,ProductList!$V$4:$V$493) -> 0 | M36: =SUMIF(ProductList!$F$4:$F$493,A36,ProductList!$K$4:$K$493) -> 0 | N36: KG | O36: =IF(D36="SCL",100,AZ36) -> 80 | P36: =IF((K36*Y36)>(L36*AH36),(K36*Y36),(L36*AH36)) -> 0 | Q36: =IF((K36*Z36)>(L36*AI36),(K36*Z36),(L36*AI36)) -> 0 | R36: =IF(C36="SG", IF(((K36*1.1+P36+Q36+T36+V36)*AA36)>(L36*AJ36), (K36*1.1+P36+Q36+T36+V36)*AA36, L36*AJ36), IF(((K36*1.1+P36+Q36+S36+U36)*AA36)>(L36*AJ36), (K36*1.1+P36+Q36+S36+U36)*AA36, L36*AJ36) ) -> 0 | S36: =IF((K36*AB36)>(L36*AK36),(K36*AB36),(L36*AK36)) -> 0 | T36: =IF((K36*AC36)>(L36*AL36),(K36*AC36),(L36*AL36)) -> 0 | U36: =IF((K36*AD36)>(L36*AM36),(K36*AD36),(L36*AM36)) -> 0 | V36: =IF((K36*AE36)>(L36*AN36),(K36*AE36),(L36*AN36)) -> 0 | W36: =IF((K36*AF36)>(L36*AO36),(K36*AF36),(L36*AO36)) -> 0 | X36: =IF((((K36)*1.1+P36+Q36+S36+T36+U36+V36)*AG36)>(L36*AP36),(((K36)*1.1+P36+Q36+S36+T36+U36+V36)*AG36),(L36*AP36)) -> 0 | AA36: 0.18 | AB36: 0.1 | AC36: 0.06 | AD36: 0.05 | AE36: 0.04 | AG36: 0.025 | AZ36: =AZ35 -> 80
A37: 19021900 | B37: VERMICILLI | E37: =IF(D37="SCL",G37,H37) -> 0 | F37: S | H37: =ROUND(I37,0) -> 0 | I37: =IF(AND(L37<>"",L37<>0),ROUND(J37/L37,0),0) -> 0 | J37: =IF(C37="SG",ROUND((P37+Q37+R37+T37+V37+W37+X37),0),ROUND((P37+Q37+R37+S37+U37+W37+X37),0)) -> 0 | K37: =SUMIF(ProductList!$F$4:$F$493,A37,ProductList!$BA$4:$BA$493) -> 0 | L37: =SUMIF(ProductList!$F$4:$F$493,A37,ProductList!$V$4:$V$493) -> 0 | M37: =SUMIF(ProductList!$F$4:$F$493,A37,ProductList!$K$4:$K$493) -> 0 | N37: KG | O37: =IF(D37="SCL",100,AZ37) -> 80 | P37: =IF((K37*Y37)>(L37*AH37),(K37*Y37),(L37*AH37)) -> 0 | Q37: =IF((K37*Z37)>(L37*AI37),(K37*Z37),(L37*AI37)) -> 0 | R37: =IF(C37="SG", IF(((K37*1.1+P37+Q37+T37+V37)*AA37)>(L37*AJ37), (K37*1.1+P37+Q37+T37+V37)*AA37, L37*AJ37), IF(((K37*1.1+P37+Q37+S37+U37)*AA37)>(L37*AJ37), (K37*1.1+P37+Q37+S37+U37)*AA37, L37*AJ37) ) -> 0 | S37: =IF((K37*AB37)>(L37*AK37),(K37*AB37),(L37*AK37)) -> 0 | T37: =IF((K37*AC37)>(L37*AL37),(K37*AC37),(L37*AL37)) -> 0 | U37: =IF((K37*AD37)>(L37*AM37),(K37*AD37),(L37*AM37)) -> 0 | V37: =IF((K37*AE37)>(L37*AN37),(K37*AE37),(L37*AN37)) -> 0 | W37: =IF((K37*AF37)>(L37*AO37),(K37*AF37),(L37*AO37)) -> 0 | X37: =IF((((K37)*1.1+P37+Q37+S37+T37+U37+V37)*AG37)>(L37*AP37),(((K37)*1.1+P37+Q37+S37+T37+U37+V37)*AG37),(L37*AP37)) -> 0 | Z37: 0.2 | AA37: 0.18 | AB37: 0.1 | AC37: 0.06 | AD37: 0.3 | AE37: 0.24 | AG37: 0.025 | AI37: 160 | AM37: 140 | AN37: 64 | AZ37: =AZ36 -> 80
A38: 19041000 | B38: CEREALS OR CEREAL PRODUCTS | D38: NORM | E38: =IF(D38="SCL",G38,H38) -> 0 | H38: =ROUND(I38,0) -> 0 | I38: =IF(AND(L38<>"",L38<>0),ROUND(J38/L38,0),0) -> 0 | J38: =IF(C38="SG",ROUND((P38+Q38+R38+T38+V38+W38+X38),0),ROUND((P38+Q38+R38+S38+U38+W38+X38),0)) -> 0 | K38: =SUMIF(ProductList!$F$4:$F$493,A38,ProductList!$BA$4:$BA$493) -> 0 | L38: =SUMIF(ProductList!$F$4:$F$493,A38,ProductList!$V$4:$V$493) -> 0 | M38: =SUMIF(ProductList!$F$4:$F$493,A38,ProductList!$K$4:$K$493) -> 0 | N38: KG | O38: =IF(D38="SCL",100,AZ38) -> 80 | P38: =IF((K38*Y38)>(L38*AH38),(K38*Y38),(L38*AH38)) -> 0 | Q38: =IF((K38*Z38)>(L38*AI38),(K38*Z38),(L38*AI38)) -> 0 | R38: =IF(C38="SG", IF(((K38*1.1+P38+Q38+T38+V38)*AA38)>(L38*AJ38), (K38*1.1+P38+Q38+T38+V38)*AA38, L38*AJ38), IF(((K38*1.1+P38+Q38+S38+U38)*AA38)>(L38*AJ38), (K38*1.1+P38+Q38+S38+U38)*AA38, L38*AJ38) ) -> 0 | S38: =IF((K38*AB38)>(L38*AK38),(K38*AB38),(L38*AK38)) -> 0 | T38: =IF((K38*AC38)>(L38*AL38),(K38*AC38),(L38*AL38)) -> 0 | U38: =IF((K38*AD38)>(L38*AM38),(K38*AD38),(L38*AM38)) -> 0 | V38: =IF((K38*AE38)>(L38*AN38),(K38*AE38),(L38*AN38)) -> 0 | W38: =IF((K38*AF38)>(L38*AO38),(K38*AF38),(L38*AO38)) -> 0 | X38: =IF((((K38)*1.1+P38+Q38+S38+T38+U38+V38)*AG38)>(L38*AP38),(((K38)*1.1+P38+Q38+S38+T38+U38+V38)*AG38),(L38*AP38)) -> 0 | Z38: 0.2 | AA38: 0.18 | AB38: 0.1 | AC38: 0 | AD38: 0.3 | AG38: 0.025 | AI38: 230 | AM38: 140 | AZ38: =AZ37 -> 80
A39: 19049000 | B39: PREPARED FOOD PUFFED RICE | E39: =IF(D39="SCL",G39,H39) -> 0 | H39: =ROUND(I39,0) -> 0 | I39: =IF(AND(L39<>"",L39<>0),ROUND(J39/L39,0),0) -> 0 | J39: =IF(C39="SG",ROUND((P39+Q39+R39+T39+V39+W39+X39),0),ROUND((P39+Q39+R39+S39+U39+W39+X39),0)) -> 0 | K39: =SUMIF(ProductList!$F$4:$F$493,A39,ProductList!$BA$4:$BA$493) -> 0 | L39: =SUMIF(ProductList!$F$4:$F$493,A39,ProductList!$V$4:$V$493) -> 0 | M39: =SUMIF(ProductList!$F$4:$F$493,A39,ProductList!$K$4:$K$493) -> 0 | N39: KG | O39: =IF(D39="SCL",100,AZ39) -> 80 | P39: =IF((K39*Y39)>(L39*AH39),(K39*Y39),(L39*AH39)) -> 0 | Q39: =IF((K39*Z39)>(L39*AI39),(K39*Z39),(L39*AI39)) -> 0 | R39: =IF(C39="SG", IF(((K39*1.1+P39+Q39+T39+V39)*AA39)>(L39*AJ39), (K39*1.1+P39+Q39+T39+V39)*AA39, L39*AJ39), IF(((K39*1.1+P39+Q39+S39+U39)*AA39)>(L39*AJ39), (K39*1.1+P39+Q39+S39+U39)*AA39, L39*AJ39) ) -> 0 | S39: =IF((K39*AB39)>(L39*AK39),(K39*AB39),(L39*AK39)) -> 0 | T39: =IF((K39*AC39)>(L39*AL39),(K39*AC39),(L39*AL39)) -> 0 | U39: =IF((K39*AD39)>(L39*AM39),(K39*AD39),(L39*AM39)) -> 0 | V39: =IF((K39*AE39)>(L39*AN39),(K39*AE39),(L39*AN39)) -> 0 | W39: =IF((K39*AF39)>(L39*AO39),(K39*AF39),(L39*AO39)) -> 0 | X39: =IF((((K39)*1.1+P39+Q39+S39+T39+U39+V39)*AG39)>(L39*AP39),(((K39)*1.1+P39+Q39+S39+T39+U39+V39)*AG39),(L39*AP39)) -> 0 | Z39: 0.2 | AA39: 0.18 | AB39: 0.1 | AD39: 0.3 | AG39: 0.025 | AI39: 230 | AM39: 140 | AZ39: =AZ38 -> 80
A40: 19053100 | B40: SWEET BISCUITS | D40: NORM | E40: =IF(D40="SCL",G40,H40) -> 0 | H40: =ROUND(I40,0) -> 0 | I40: =IF(AND(L40<>"",L40<>0),ROUND(J40/L40,0),0) -> 0 | J40: =IF(C40="SG",ROUND((P40+Q40+R40+T40+V40+W40+X40),0),ROUND((P40+Q40+R40+S40+U40+W40+X40),0)) -> 0 | K40: =SUMIF(ProductList!$F$4:$F$493,A40,ProductList!$BA$4:$BA$493) -> 0 | L40: =SUMIF(ProductList!$F$4:$F$493,A40,ProductList!$V$4:$V$493) -> 0 | M40: =SUMIF(ProductList!$F$4:$F$493,A40,ProductList!$K$4:$K$493) -> 0 | N40: KG | O40: =IF(D40="SCL",100,AZ40) -> 80 | P40: =IF((K40*Y40)>(L40*AH40),(K40*Y40),(L40*AH40)) -> 0 | Q40: =IF((K40*Z40)>(L40*AI40),(K40*Z40),(L40*AI40)) -> 0 | R40: =IF(C40="SG", IF(((K40*1.1+P40+Q40+T40+V40)*AA40)>(L40*AJ40), (K40*1.1+P40+Q40+T40+V40)*AA40, L40*AJ40), IF(((K40*1.1+P40+Q40+S40+U40)*AA40)>(L40*AJ40), (K40*1.1+P40+Q40+S40+U40)*AA40, L40*AJ40) ) -> 0 | S40: =IF((K40*AB40)>(L40*AK40),(K40*AB40),(L40*AK40)) -> 0 | T40: =IF((K40*AC40)>(L40*AL40),(K40*AC40),(L40*AL40)) -> 0 | U40: =IF((K40*AD40)>(L40*AM40),(K40*AD40),(L40*AM40)) -> 0 | V40: =IF((K40*AE40)>(L40*AN40),(K40*AE40),(L40*AN40)) -> 0 | W40: =IF((K40*AF40)>(L40*AO40),(K40*AF40),(L40*AO40)) -> 0 | X40: =IF((((K40)*1.1+P40+Q40+S40+T40+U40+V40)*AG40)>(L40*AP40),(((K40)*1.1+P40+Q40+S40+T40+U40+V40)*AG40),(L40*AP40)) -> 0 | Z40: 0.2 | AA40: 0.18 | AB40: 0.1 | AD40: 0.35 | AG40: 0.025 | AI40: 160 | AW40: =35%*65% -> 0.2275 | AZ40: =AZ39 -> 80
A41: 19054010 | B41: RUSK | D41: NORM | E41: =IF(D41="SCL",G41,H41) -> 0 | H41: =ROUND(I41,0) -> 0 | I41: =IF(AND(L41<>"",L41<>0),ROUND(J41/L41,0),0) -> 0 | J41: =IF(C41="SG",ROUND((P41+Q41+R41+T41+V41+W41+X41),0),ROUND((P41+Q41+R41+S41+U41+W41+X41),0)) -> 0 | K41: =SUMIF(ProductList!$F$4:$F$493,A41,ProductList!$BA$4:$BA$493) -> 0 | L41: =SUMIF(ProductList!$F$4:$F$493,A41,ProductList!$V$4:$V$493) -> 0 | M41: =SUMIF(ProductList!$F$4:$F$493,A41,ProductList!$K$4:$K$493) -> 0 | N41: KG | O41: =IF(D41="SCL",100,AZ41) -> 80 | P41: =IF((K41*Y41)>(L41*AH41),(K41*Y41),(L41*AH41)) -> 0 | Q41: =IF((K41*Z41)>(L41*AI41),(K41*Z41),(L41*AI41)) -> 0 | R41: =IF(C41="SG", IF(((K41*1.1+P41+Q41+T41+V41)*AA41)>(L41*AJ41), (K41*1.1+P41+Q41+T41+V41)*AA41, L41*AJ41), IF(((K41*1.1+P41+Q41+S41+U41)*AA41)>(L41*AJ41), (K41*1.1+P41+Q41+S41+U41)*AA41, L41*AJ41) ) -> 0 | S41: =IF((K41*AB41)>(L41*AK41),(K41*AB41),(L41*AK41)) -> 0 | T41: =IF((K41*AC41)>(L41*AL41),(K41*AC41),(L41*AL41)) -> 0 | U41: =IF((K41*AD41)>(L41*AM41),(K41*AD41),(L41*AM41)) -> 0 | V41: =IF((K41*AE41)>(L41*AN41),(K41*AE41),(L41*AN41)) -> 0 | W41: =IF((K41*AF41)>(L41*AO41),(K41*AF41),(L41*AO41)) -> 0 | X41: =IF((((K41)*1.1+P41+Q41+S41+T41+U41+V41)*AG41)>(L41*AP41),(((K41)*1.1+P41+Q41+S41+T41+U41+V41)*AG41),(L41*AP41)) -> 0 | Z41: 0.2 | AA41: 0.18 | AB41: 0.1 | AD41: 0.35 | AG41: 0.025 | AI41: 350 | AM41: 160 | AZ41: =AZ40 -> 80
A42: 19059090 | B42: PANI PURI KIT | D42: NORM | E42: =IF(D42="SCL",G42,H42) -> 0 | G42: 448 | H42: =ROUND(I42,0) -> 0 | I42: =IF(AND(L42<>"",L42<>0),ROUND(J42/L42,0),0) -> 0 | J42: =IF(C42="SG",ROUND((P42+Q42+R42+T42+V42+W42+X42),0),ROUND((P42+Q42+R42+S42+U42+W42+X42),0)) -> 0 | K42: =SUMIF(ProductList!$F$4:$F$493,A42,ProductList!$BA$4:$BA$493) -> 0 | L42: =SUMIF(ProductList!$F$4:$F$493,A42,ProductList!$V$4:$V$493) -> 0 | M42: =SUMIF(ProductList!$F$4:$F$493,A42,ProductList!$K$4:$K$493) -> 0 | N42: KG | O42: =IF(D42="SCL",100,AZ42) -> 80 | P42: =IF((K42*Y42)>(L42*AH42),(K42*Y42),(L42*AH42)) -> 0 | Q42: =IF((K42*Z42)>(L42*AI42),(K42*Z42),(L42*AI42)) -> 0 | R42: =IF(C42="SG", IF(((K42*1.1+P42+Q42+T42+V42)*AA42)>(L42*AJ42), (K42*1.1+P42+Q42+T42+V42)*AA42, L42*AJ42), IF(((K42*1.1+P42+Q42+S42+U42)*AA42)>(L42*AJ42), (K42*1.1+P42+Q42+S42+U42)*AA42, L42*AJ42) ) -> 0 | S42: =IF((K42*AB42)>(L42*AK42),(K42*AB42),(L42*AK42)) -> 0 | T42: =IF((K42*AC42)>(L42*AL42),(K42*AC42),(L42*AL42)) -> 0 | U42: =IF((K42*AD42)>(L42*AM42),(K42*AD42),(L42*AM42)) -> 0 | V42: =IF((K42*AE42)>(L42*AN42),(K42*AE42),(L42*AN42)) -> 0 | W42: =IF((K42*AF42)>(L42*AO42),(K42*AF42),(L42*AO42)) -> 0 | X42: =IF((((K42)*1.1+P42+Q42+S42+T42+U42+V42)*AG42)>(L42*AP42),(((K42)*1.1+P42+Q42+S42+T42+U42+V42)*AG42),(L42*AP42)) -> 0 | Z42: 0.2 | AA42: 0.18 | AB42: 0.1 | AD42: 0.35 | AG42: 0.025 | AM42: 160 | AZ42: =AZ41 -> 80
A43: 20019000 | B43: ASSORTED PICKLES | D43: NORM | E43: =IF(D43="SCL",G43,H43) -> 561 | G43: 574 | H43: =ROUND(I43,0) -> 561 | I43: =IF(AND(L43<>"",L43<>0),ROUND(J43/L43,0),0) -> 561 | J43: =IF(C43="SG",ROUND((P43+Q43+R43+T43+V43+W43+X43),0),ROUND((P43+Q43+R43+S43+U43+W43+X43),0)) -> 716510 | K43: =SUMIF(ProductList!$F$4:$F$493,A43,ProductList!$BA$4:$BA$493) -> 578590.4 | L43: =SUMIF(ProductList!$F$4:$F$493,A43,ProductList!$V$4:$V$493) -> 1278 | M43: =SUMIF(ProductList!$F$4:$F$493,A43,ProductList!$K$4:$K$493) -> 0 | N43: KG | O43: =IF(D43="SCL",100,AZ43) -> 80 | P43: =IF((K43*Y43)>(L43*AH43),(K43*Y43),(L43*AH43)) -> 0 | Q43: =IF((K43*Z43)>(L43*AI43),(K43*Z43),(L43*AI43)) -> 115718.08 | R43: =IF(C43="SG", IF(((K43*1.1+P43+Q43+T43+V43)*AA43)>(L43*AJ43), (K43*1.1+P43+Q43+T43+V43)*AA43, L43*AJ43), IF(((K43*1.1+P43+Q43+S43+U43)*AA43)>(L43*AJ43), (K43*1.1+P43+Q43+S43+U43)*AA43, L43*AJ43) ) -> 202101.75 | S43: =IF((K43*AB43)>(L43*AK43),(K43*AB43),(L43*AK43)) -> 0 | T43: =IF((K43*AC43)>(L43*AL43),(K43*AC43),(L43*AL43)) -> 0 | U43: =IF((K43*AD43)>(L43*AM43),(K43*AD43),(L43*AM43)) -> 370620 | V43: =IF((K43*AE43)>(L43*AN43),(K43*AE43),(L43*AN43)) -> 0 | W43: =IF((K43*AF43)>(L43*AO43),(K43*AF43),(L43*AO43)) -> 0 | X43: =IF((((K43)*1.1+P43+Q43+S43+T43+U43+V43)*AG43)>(L43*AP43),(((K43)*1.1+P43+Q43+S43+T43+U43+V43)*AG43),(L43*AP43)) -> 28069.688 | Z43: 0.2 | AA43: 0.18 | AD43: 0.45 | AG43: 0.025 | AI43: 70 | AM43: 290 | AZ43: =AZ42 -> 80
A44: 20052000 | B44: POTATO CHIPS | D44: NORM | E44: =IF(D44="SCL",G44,H44) -> 0 | H44: =ROUND(I44,0) -> 0 | I44: =IF(AND(L44<>"",L44<>0),ROUND(J44/L44,0),0) -> 0 | J44: =IF(C44="SG",ROUND((P44+Q44+R44+T44+V44+W44+X44),0),ROUND((P44+Q44+R44+S44+U44+W44+X44),0)) -> 0 | K44: =SUMIF(ProductList!$F$4:$F$493,A44,ProductList!$BA$4:$BA$493) -> 0 | L44: =SUMIF(ProductList!$F$4:$F$493,A44,ProductList!$V$4:$V$493) -> 0 | M44: =SUMIF(ProductList!$F$4:$F$493,A44,ProductList!$K$4:$K$493) -> 0 | N44: KG | O44: =IF(D44="SCL",100,AZ44) -> 80 | P44: =IF((K44*Y44)>(L44*AH44),(K44*Y44),(L44*AH44)) -> 0 | Q44: =IF((K44*Z44)>(L44*AI44),(K44*Z44),(L44*AI44)) -> 0 | R44: =IF(C44="SG", IF(((K44*1.1+P44+Q44+T44+V44)*AA44)>(L44*AJ44), (K44*1.1+P44+Q44+T44+V44)*AA44, L44*AJ44), IF(((K44*1.1+P44+Q44+S44+U44)*AA44)>(L44*AJ44), (K44*1.1+P44+Q44+S44+U44)*AA44, L44*AJ44) ) -> 0 | S44: =IF((K44*AB44)>(L44*AK44),(K44*AB44),(L44*AK44)) -> 0 | T44: =IF((K44*AC44)>(L44*AL44),(K44*AC44),(L44*AL44)) -> 0 | U44: =IF((K44*AD44)>(L44*AM44),(K44*AD44),(L44*AM44)) -> 0 | V44: =IF((K44*AE44)>(L44*AN44),(K44*AE44),(L44*AN44)) -> 0 | W44: =IF((K44*AF44)>(L44*AO44),(K44*AF44),(L44*AO44)) -> 0 | X44: =IF((((K44)*1.1+P44+Q44+S44+T44+U44+V44)*AG44)>(L44*AP44),(((K44)*1.1+P44+Q44+S44+T44+U44+V44)*AG44),(L44*AP44)) -> 0 | Z44: 0.2 | AA44: 0.18 | AB44: 0.1 | AD44: 0.45 | AG44: 0.025 | AI44: 370 | AM44: 450 | AZ44: =AZ43 -> 80
A45: 21011200 | B45: CHUKKU MALLI | D45: NORM | E45: =IF(D45="SCL",G45,H45) -> 0 | G45: 1622 | H45: =ROUND(I45,0) -> 0 | I45: =IF(AND(L45<>"",L45<>0),ROUND(J45/L45,0),0) -> 0 | J45: =IF(C45="SG",ROUND((P45+Q45+R45+T45+V45+W45+X45),0),ROUND((P45+Q45+R45+S45+U45+W45+X45),0)) -> 0 | K45: =SUMIF(ProductList!$F$4:$F$493,A45,ProductList!$BA$4:$BA$493) -> 0 | L45: =SUMIF(ProductList!$F$4:$F$493,A45,ProductList!$V$4:$V$493) -> 0 | M45: =SUMIF(ProductList!$F$4:$F$493,A45,ProductList!$K$4:$K$493) -> 0 | N45: KG | O45: =IF(D45="SCL",100,AZ45) -> 80 | P45: =IF((K45*Y45)>(L45*AH45),(K45*Y45),(L45*AH45)) -> 0 | Q45: =IF((K45*Z45)>(L45*AI45),(K45*Z45),(L45*AI45)) -> 0 | R45: =IF(C45="SG", IF(((K45*1.1+P45+Q45+T45+V45)*AA45)>(L45*AJ45), (K45*1.1+P45+Q45+T45+V45)*AA45, L45*AJ45), IF(((K45*1.1+P45+Q45+S45+U45)*AA45)>(L45*AJ45), (K45*1.1+P45+Q45+S45+U45)*AA45, L45*AJ45) ) -> 0 | S45: =IF((K45*AB45)>(L45*AK45),(K45*AB45),(L45*AK45)) -> 0 | T45: =IF((K45*AC45)>(L45*AL45),(K45*AC45),(L45*AL45)) -> 0 | U45: =IF((K45*AD45)>(L45*AM45),(K45*AD45),(L45*AM45)) -> 0 | V45: =IF((K45*AE45)>(L45*AN45),(K45*AE45),(L45*AN45)) -> 0 | W45: =IF((K45*AF45)>(L45*AO45),(K45*AF45),(L45*AO45)) -> 0 | X45: =IF((((K45)*1.1+P45+Q45+S45+T45+U45+V45)*AG45)>(L45*AP45),(((K45)*1.1+P45+Q45+S45+T45+U45+V45)*AG45),(L45*AP45)) -> 0 | Z45: 0.2 | AA45: 0.18 | AB45: 0.1 | AD45: 0.25 | AG45: 0.025 | AI45: 550 | AM45: 500 | AZ45: =AZ44 -> 80
A46: 21011200 | B46: COFFEE MIX | D46: NORM | E46: =IF(D46="SCL",G46,H46) -> 0 | H46: =ROUND(I46,0) -> 0 | I46: =IF(AND(L46<>"",L46<>0),ROUND(J46/L46,0),0) -> 0 | J46: =IF(C46="SG",ROUND((P46+Q46+R46+T46+V46+W46+X46),0),ROUND((P46+Q46+R46+S46+U46+W46+X46),0)) -> 0 | K46: =SUMIF(ProductList!$F$4:$F$493,A46,ProductList!$BA$4:$BA$493) -> 0 | L46: =SUMIF(ProductList!$F$4:$F$493,A46,ProductList!$V$4:$V$493) -> 0 | M46: =SUMIF(ProductList!$F$4:$F$493,A46,ProductList!$K$4:$K$493) -> 0 | N46: KG | O46: =IF(D46="SCL",100,AZ46) -> 80 | P46: =IF((K46*Y46)>(L46*AH46),(K46*Y46),(L46*AH46)) -> 0 | Q46: =IF((K46*Z46)>(L46*AI46),(K46*Z46),(L46*AI46)) -> 0 | R46: =IF(C46="SG", IF(((K46*1.1+P46+Q46+T46+V46)*AA46)>(L46*AJ46), (K46*1.1+P46+Q46+T46+V46)*AA46, L46*AJ46), IF(((K46*1.1+P46+Q46+S46+U46)*AA46)>(L46*AJ46), (K46*1.1+P46+Q46+S46+U46)*AA46, L46*AJ46) ) -> 0 | S46: =IF((K46*AB46)>(L46*AK46),(K46*AB46),(L46*AK46)) -> 0 | T46: =IF((K46*AC46)>(L46*AL46),(K46*AC46),(L46*AL46)) -> 0 | U46: =IF((K46*AD46)>(L46*AM46),(K46*AD46),(L46*AM46)) -> 0 | V46: =IF((K46*AE46)>(L46*AN46),(K46*AE46),(L46*AN46)) -> 0 | W46: =IF((K46*AF46)>(L46*AO46),(K46*AF46),(L46*AO46)) -> 0 | X46: =IF((((K46)*1.1+P46+Q46+S46+T46+U46+V46)*AG46)>(L46*AP46),(((K46)*1.1+P46+Q46+S46+T46+U46+V46)*AG46),(L46*AP46)) -> 0 | Z46: 0.2 | AA46: 0.18 | AB46: 0.1 | AD46: 0.25 | AG46: 0.025 | AI46: 550 | AM46: 500 | AZ46: =AZ45 -> 80
A47: 21012011 | B47: INSTANT TEA | D47: NORM | E47: =IF(D47="SCL",G47,H47) -> 0 | H47: =ROUND(I47,0) -> 0 | I47: =IF(AND(L47<>"",L47<>0),ROUND(J47/L47,0),0) -> 0 | J47: =IF(C47="SG",ROUND((P47+Q47+R47+T47+V47+W47+X47),0),ROUND((P47+Q47+R47+S47+U47+W47+X47),0)) -> 0 | K47: =SUMIF(ProductList!$F$4:$F$493,A47,ProductList!$BA$4:$BA$493) -> 0 | L47: =SUMIF(ProductList!$F$4:$F$493,A47,ProductList!$V$4:$V$493) -> 0 | M47: =SUMIF(ProductList!$F$4:$F$493,A47,ProductList!$K$4:$K$493) -> 0 | N47: KG | O47: =IF(D47="SCL",100,AZ47) -> 80 | P47: =IF((K47*Y47)>(L47*AH47),(K47*Y47),(L47*AH47)) -> 0 | Q47: =IF((K47*Z47)>(L47*AI47),(K47*Z47),(L47*AI47)) -> 0 | R47: =IF(C47="SG", IF(((K47*1.1+P47+Q47+T47+V47)*AA47)>(L47*AJ47), (K47*1.1+P47+Q47+T47+V47)*AA47, L47*AJ47), IF(((K47*1.1+P47+Q47+S47+U47)*AA47)>(L47*AJ47), (K47*1.1+P47+Q47+S47+U47)*AA47, L47*AJ47) ) -> 0 | S47: =IF((K47*AB47)>(L47*AK47),(K47*AB47),(L47*AK47)) -> 0 | T47: =IF((K47*AC47)>(L47*AL47),(K47*AC47),(L47*AL47)) -> 0 | U47: =IF((K47*AD47)>(L47*AM47),(K47*AD47),(L47*AM47)) -> 0 | V47: =IF((K47*AE47)>(L47*AN47),(K47*AE47),(L47*AN47)) -> 0 | W47: =IF((K47*AF47)>(L47*AO47),(K47*AF47),(L47*AO47)) -> 0 | X47: =IF((((K47)*1.1+P47+Q47+S47+T47+U47+V47)*AG47)>(L47*AP47),(((K47)*1.1+P47+Q47+S47+T47+U47+V47)*AG47),(L47*AP47)) -> 0 | Z47: 0.2 | AA47: 0.18 | AB47: 0.1 | AD47: 0.1 | AG47: 0.025 | AI47: 1500 | AM47: 600 | AZ47: =AZ46 -> 80
A48: 21039090 | B48: ASSORTED MASALA | D48: NORM | E48: =IF(D48="SCL",G48,H48) -> 0 | G48: 370 | H48: =ROUND(I48,0) -> 0 | I48: =IF(AND(L48<>"",L48<>0),ROUND(J48/L48,0),0) -> 0 | J48: =IF(C48="SG",ROUND((P48+Q48+R48+T48+V48+W48+X48),0),ROUND((P48+Q48+R48+S48+U48+W48+X48),0)) -> 0 | K48: =SUMIF(ProductList!$F$4:$F$493,A48,ProductList!$BA$4:$BA$493) -> 0 | L48: =SUMIF(ProductList!$F$4:$F$493,A48,ProductList!$V$4:$V$493) -> 0 | M48: =SUMIF(ProductList!$F$4:$F$493,A48,ProductList!$K$4:$K$493) -> 0 | N48: KG | O48: =IF(D48="SCL",100,AZ48) -> 80 | P48: =IF((K48*Y48)>(L48*AH48),(K48*Y48),(L48*AH48)) -> 0 | Q48: =IF((K48*Z48)>(L48*AI48),(K48*Z48),(L48*AI48)) -> 0 | R48: =IF(C48="SG", IF(((K48*1.1+P48+Q48+T48+V48)*AA48)>(L48*AJ48), (K48*1.1+P48+Q48+T48+V48)*AA48, L48*AJ48), IF(((K48*1.1+P48+Q48+S48+U48)*AA48)>(L48*AJ48), (K48*1.1+P48+Q48+S48+U48)*AA48, L48*AJ48) ) -> 0 | S48: =IF((K48*AB48)>(L48*AK48),(K48*AB48),(L48*AK48)) -> 0 | T48: =IF((K48*AC48)>(L48*AL48),(K48*AC48),(L48*AL48)) -> 0 | U48: =IF((K48*AD48)>(L48*AM48),(K48*AD48),(L48*AM48)) -> 0 | V48: =IF((K48*AE48)>(L48*AN48),(K48*AE48),(L48*AN48)) -> 0 | W48: =IF((K48*AF48)>(L48*AO48),(K48*AF48),(L48*AO48)) -> 0 | X48: =IF((((K48)*1.1+P48+Q48+S48+T48+U48+V48)*AG48)>(L48*AP48),(((K48)*1.1+P48+Q48+S48+T48+U48+V48)*AG48),(L48*AP48)) -> 0 | Z48: 0.2 | AA48: 0.18 | AB48: 0.1 | AC48: 0.06 | AD48: 0.25 | AE48: 0.24 | AG48: 0.025 | AM48: 160 | AN48: 100 | AZ48: =AZ47 -> 80
A49: 21069060 | B49: PAPADS - OTHERS | D49: NORM | E49: =IF(D49="SCL",G49,H49) -> 1120 | H49: =ROUND(I49,0) -> 1120 | I49: =IF(AND(L49<>"",L49<>0),ROUND(J49/L49,0),0) -> 1120 | J49: =IF(C49="SG",ROUND((P49+Q49+R49+T49+V49+W49+X49),0),ROUND((P49+Q49+R49+S49+U49+W49+X49),0)) -> 534440 | K49: =SUMIF(ProductList!$F$4:$F$493,A49,ProductList!$BA$4:$BA$493) -> 316660 | L49: =SUMIF(ProductList!$F$4:$F$493,A49,ProductList!$V$4:$V$493) -> 477.04 | M49: =SUMIF(ProductList!$F$4:$F$493,A49,ProductList!$K$4:$K$493) -> 0 | N49: KG | O49: =IF(D49="SCL",100,AZ49) -> 80 | P49: =IF((K49*Y49)>(L49*AH49),(K49*Y49),(L49*AH49)) -> 0 | Q49: =IF((K49*Z49)>(L49*AI49),(K49*Z49),(L49*AI49)) -> 166964 | R49: =IF(C49="SG", IF(((K49*1.1+P49+Q49+T49+V49)*AA49)>(L49*AJ49), (K49*1.1+P49+Q49+T49+V49)*AA49, L49*AJ49), IF(((K49*1.1+P49+Q49+S49+U49)*AA49)>(L49*AJ49), (K49*1.1+P49+Q49+S49+U49)*AA49, L49*AJ49) ) -> 131392.44 | S49: =IF((K49*AB49)>(L49*AK49),(K49*AB49),(L49*AK49)) -> 0 | T49: =IF((K49*AC49)>(L49*AL49),(K49*AC49),(L49*AL49)) -> 126664 | U49: =IF((K49*AD49)>(L49*AM49),(K49*AD49),(L49*AM49)) -> 214668 | V49: =IF((K49*AE49)>(L49*AN49),(K49*AE49),(L49*AN49)) -> 0 | W49: =IF((K49*AF49)>(L49*AO49),(K49*AF49),(L49*AO49)) -> 0 | X49: =IF((((K49)*1.1+P49+Q49+S49+T49+U49+V49)*AG49)>(L49*AP49),(((K49)*1.1+P49+Q49+S49+T49+U49+V49)*AG49),(L49*AP49)) -> 21415.55 | Z49: 0.2 | AA49: 0.18 | AC49: 0.4 | AG49: 0.025 | AI49: 350 | AM49: 450 | AZ49: =AZ48 -> 80
A50: 21069099 | B50: HEALTH MIXES | D50: NORM | E50: =IF(D50="SCL",G50,H50) -> 570 | G50: 539 | H50: =ROUND(I50,0) -> 570 | I50: =IF(AND(L50<>"",L50<>0),ROUND(J50/L50,0),0) -> 570 | J50: =IF(C50="SG",ROUND((P50+Q50+R50+T50+V50+W50+X50),0),ROUND((P50+Q50+R50+S50+U50+W50+X50),0)) -> 1049869 | K50: =SUMIF(ProductList!$F$4:$F$493,A50,ProductList!$BA$4:$BA$493) -> 1100492 | L50: =SUMIF(ProductList!$F$4:$F$493,A50,ProductList!$V$4:$V$493) -> 1841.6 | M50: =SUMIF(ProductList!$F$4:$F$493,A50,ProductList!$K$4:$K$493) -> 0 | N50: KG | O50: =IF(D50="SCL",100,AZ50) -> 80 | P50: =IF((K50*Y50)>(L50*AH50),(K50*Y50),(L50*AH50)) -> 0 | Q50: =IF((K50*Z50)>(L50*AI50),(K50*Z50),(L50*AI50)) -> 220098.4 | R50: =IF(C50="SG", IF(((K50*1.1+P50+Q50+T50+V50)*AA50)>(L50*AJ50), (K50*1.1+P50+Q50+T50+V50)*AA50, L50*AJ50), IF(((K50*1.1+P50+Q50+S50+U50)*AA50)>(L50*AJ50), (K50*1.1+P50+Q50+S50+U50)*AA50, L50*AJ50) ) -> 336750.55 | S50: =IF((K50*AB50)>(L50*AK50),(K50*AB50),(L50*AK50)) -> 110049.2 | T50: =IF((K50*AC50)>(L50*AL50),(K50*AC50),(L50*AL50)) -> 66029.52 | U50: =IF((K50*AD50)>(L50*AM50),(K50*AD50),(L50*AM50)) -> 330147.6 | V50: =IF((K50*AE50)>(L50*AN50),(K50*AE50),(L50*AN50)) -> 176078.72 | W50: =IF((K50*AF50)>(L50*AO50),(K50*AF50),(L50*AO50)) -> 0 | X50: =IF((((K50)*1.1+P50+Q50+S50+T50+U50+V50)*AG50)>(L50*AP50),(((K50)*1.1+P50+Q50+S50+T50+U50+V50)*AG50),(L50*AP50)) -> 52823.616 | Z50: 0.2 | AA50: 0.18 | AB50: 0.1 | AC50: 0.06 | AD50: 0.3 | AE50: 0.16 | AG50: 0.025 | AZ50: =AZ49 -> 80
A51: 30049011 | B51: MEDICAMENTS | E51: =IF(D51="SCL",G51,H51) -> 0 | F51: L | H51: =ROUND(I51,0) -> 0 | I51: =IF(AND(L51<>"",L51<>0),ROUND(J51/L51,0),0) -> 0 | J51: =IF(C51="SG",ROUND((P51+Q51+R51+T51+V51+W51+X51),0),ROUND((P51+Q51+R51+S51+U51+W51+X51),0)) -> 0 | K51: =SUMIF(ProductList!$F$4:$F$493,A51,ProductList!$BA$4:$BA$493) -> 0 | L51: =SUMIF(ProductList!$F$4:$F$493,A51,ProductList!$V$4:$V$493) -> 0 | M51: =SUMIF(ProductList!$F$4:$F$493,A51,ProductList!$K$4:$K$493) -> 0 | N51: KG | O51: =IF(D51="SCL",100,AZ51) -> 80 | P51: =IF((K51*Y51)>(L51*AH51),(K51*Y51),(L51*AH51)) -> 0 | Q51: =IF((K51*Z51)>(L51*AI51),(K51*Z51),(L51*AI51)) -> 0 | R51: =IF(C51="SG", IF(((K51*1.1+P51+Q51+T51+V51)*AA51)>(L51*AJ51), (K51*1.1+P51+Q51+T51+V51)*AA51, L51*AJ51), IF(((K51*1.1+P51+Q51+S51+U51)*AA51)>(L51*AJ51), (K51*1.1+P51+Q51+S51+U51)*AA51, L51*AJ51) ) -> 0 | S51: =IF((K51*AB51)>(L51*AK51),(K51*AB51),(L51*AK51)) -> 0 | T51: =IF((K51*AC51)>(L51*AL51),(K51*AC51),(L51*AL51)) -> 0 | U51: =IF((K51*AD51)>(L51*AM51),(K51*AD51),(L51*AM51)) -> 0 | V51: =IF((K51*AE51)>(L51*AN51),(K51*AE51),(L51*AN51)) -> 0 | W51: =IF((K51*AF51)>(L51*AO51),(K51*AF51),(L51*AO51)) -> 0 | X51: =IF((((K51)*1.1+P51+Q51+S51+T51+U51+V51)*AG51)>(L51*AP51),(((K51)*1.1+P51+Q51+S51+T51+U51+V51)*AG51),(L51*AP51)) -> 0 | AA51: 0.18 | AD51: 0.25 | AE51: 0.24 | AM51: 2000 | AN51: 1000 | AZ51: =AZ50 -> 80
A52: 32030010 | B52: FOOD COLOURS | D52: NORM | E52: =IF(D52="SCL",G52,H52) -> 0 | H52: =ROUND(I52,0) -> 0 | I52: =IF(AND(L52<>"",L52<>0),ROUND(J52/L52,0),0) -> 0 | J52: =IF(C52="SG",ROUND((P52+Q52+R52+T52+V52+W52+X52),0),ROUND((P52+Q52+R52+S52+U52+W52+X52),0)) -> 0 | K52: =SUMIF(ProductList!$F$4:$F$493,A52,ProductList!$BA$4:$BA$493) -> 0 | L52: =SUMIF(ProductList!$F$4:$F$493,A52,ProductList!$V$4:$V$493) -> 0 | M52: =SUMIF(ProductList!$F$4:$F$493,A52,ProductList!$K$4:$K$493) -> 0 | N52: KG | O52: =IF(D52="SCL",100,AZ52) -> 80 | P52: =IF((K52*Y52)>(L52*AH52),(K52*Y52),(L52*AH52)) -> 0 | Q52: =IF((K52*Z52)>(L52*AI52),(K52*Z52),(L52*AI52)) -> 0 | R52: =IF(C52="SG", IF(((K52*1.1+P52+Q52+T52+V52)*AA52)>(L52*AJ52), (K52*1.1+P52+Q52+T52+V52)*AA52, L52*AJ52), IF(((K52*1.1+P52+Q52+S52+U52)*AA52)>(L52*AJ52), (K52*1.1+P52+Q52+S52+U52)*AA52, L52*AJ52) ) -> 0 | S52: =IF((K52*AB52)>(L52*AK52),(K52*AB52),(L52*AK52)) -> 0 | T52: =IF((K52*AC52)>(L52*AL52),(K52*AC52),(L52*AL52)) -> 0 | U52: =IF((K52*AD52)>(L52*AM52),(K52*AD52),(L52*AM52)) -> 0 | V52: =IF((K52*AE52)>(L52*AN52),(K52*AE52),(L52*AN52)) -> 0 | W52: =IF((K52*AF52)>(L52*AO52),(K52*AF52),(L52*AO52)) -> 0 | X52: =IF((((K52)*1.1+P52+Q52+S52+T52+U52+V52)*AG52)>(L52*AP52),(((K52)*1.1+P52+Q52+S52+T52+U52+V52)*AG52),(L52*AP52)) -> 0 | AA52: 0.18 | AB52: 0.1 | AC52: 0.06 | AG52: 0.025 | AZ52: =AZ51 -> 80
A53: 33019099 | B53: ESSENTIAL OIL | D53: NORM | E53: =IF(D53="SCL",G53,H53) -> 0 | H53: =ROUND(I53,0) -> 0 | I53: =IF(AND(L53<>"",L53<>0),ROUND(J53/L53,0),0) -> 0 | J53: =IF(C53="SG",ROUND((P53+Q53+R53+T53+V53+W53+X53),0),ROUND((P53+Q53+R53+S53+U53+W53+X53),0)) -> 0 | K53: =SUMIF(ProductList!$F$4:$F$493,A53,ProductList!$BA$4:$BA$493) -> 0 | L53: =SUMIF(ProductList!$F$4:$F$493,A53,ProductList!$V$4:$V$493) -> 0 | M53: =SUMIF(ProductList!$F$4:$F$493,A53,ProductList!$K$4:$K$493) -> 0 | N53: KG | O53: =IF(D53="SCL",100,AZ53) -> 80 | P53: =IF((K53*Y53)>(L53*AH53),(K53*Y53),(L53*AH53)) -> 0 | Q53: =IF((K53*Z53)>(L53*AI53),(K53*Z53),(L53*AI53)) -> 0 | R53: =IF(C53="SG", IF(((K53*1.1+P53+Q53+T53+V53)*AA53)>(L53*AJ53), (K53*1.1+P53+Q53+T53+V53)*AA53, L53*AJ53), IF(((K53*1.1+P53+Q53+S53+U53)*AA53)>(L53*AJ53), (K53*1.1+P53+Q53+S53+U53)*AA53, L53*AJ53) ) -> 0 | S53: =IF((K53*AB53)>(L53*AK53),(K53*AB53),(L53*AK53)) -> 0 | T53: =IF((K53*AC53)>(L53*AL53),(K53*AC53),(L53*AL53)) -> 0 | U53: =IF((K53*AD53)>(L53*AM53),(K53*AD53),(L53*AM53)) -> 0 | V53: =IF((K53*AE53)>(L53*AN53),(K53*AE53),(L53*AN53)) -> 0 | W53: =IF((K53*AF53)>(L53*AO53),(K53*AF53),(L53*AO53)) -> 0 | X53: =IF((((K53)*1.1+P53+Q53+S53+T53+U53+V53)*AG53)>(L53*AP53),(((K53)*1.1+P53+Q53+S53+T53+U53+V53)*AG53),(L53*AP53)) -> 0 | AA53: 0.18 | AB53: 0.1 | AC53: 0.06 | AG53: 0.025 | AZ53: =AZ52 -> 80
A54: 33079090 | B54: POOJA POWDER | D54: NORM | E54: =IF(D54="SCL",G54,H54) -> 0 | H54: =ROUND(I54,0) -> 0 | I54: =IF(AND(L54<>"",L54<>0),ROUND(J54/L54,0),0) -> 0 | J54: =IF(C54="SG",ROUND((P54+Q54+R54+T54+V54+W54+X54),0),ROUND((P54+Q54+R54+S54+U54+W54+X54),0)) -> 0 | K54: =SUMIF(ProductList!$F$4:$F$493,A54,ProductList!$BA$4:$BA$493) -> 0 | L54: =SUMIF(ProductList!$F$4:$F$493,A54,ProductList!$V$4:$V$493) -> 0 | M54: =SUMIF(ProductList!$F$4:$F$493,A54,ProductList!$K$4:$K$493) -> 0 | N54: KG | O54: =IF(D54="SCL",100,AZ54) -> 80 | P54: =IF((K54*Y54)>(L54*AH54),(K54*Y54),(L54*AH54)) -> 0 | Q54: =IF((K54*Z54)>(L54*AI54),(K54*Z54),(L54*AI54)) -> 0 | R54: =IF(C54="SG", IF(((K54*1.1+P54+Q54+T54+V54)*AA54)>(L54*AJ54), (K54*1.1+P54+Q54+T54+V54)*AA54, L54*AJ54), IF(((K54*1.1+P54+Q54+S54+U54)*AA54)>(L54*AJ54), (K54*1.1+P54+Q54+S54+U54)*AA54, L54*AJ54) ) -> 0 | S54: =IF((K54*AB54)>(L54*AK54),(K54*AB54),(L54*AK54)) -> 0 | T54: =IF((K54*AC54)>(L54*AL54),(K54*AC54),(L54*AL54)) -> 0 | U54: =IF((K54*AD54)>(L54*AM54),(K54*AD54),(L54*AM54)) -> 0 | V54: =IF((K54*AE54)>(L54*AN54),(K54*AE54),(L54*AN54)) -> 0 | W54: =IF((K54*AF54)>(L54*AO54),(K54*AF54),(L54*AO54)) -> 0 | X54: =IF((((K54)*1.1+P54+Q54+S54+T54+U54+V54)*AG54)>(L54*AP54),(((K54)*1.1+P54+Q54+S54+T54+U54+V54)*AG54),(L54*AP54)) -> 0 | AA54: 0.18 | AG54: 0.025 | AI54: 200 | AM54: 500 | AZ54: =AZ53 -> 80
A55: 34054090 | B55: SCOURING PASTE AND POWDERS | D55: NORM | E55: =IF(D55="SCL",G55,H55) -> 0 | H55: =ROUND(I55,0) -> 0 | I55: =IF(AND(L55<>"",L55<>0),ROUND(J55/L55,0),0) -> 0 | J55: =IF(C55="SG",ROUND((P55+Q55+R55+T55+V55+W55+X55),0),ROUND((P55+Q55+R55+S55+U55+W55+X55),0)) -> 0 | K55: =SUMIF(ProductList!$F$4:$F$493,A55,ProductList!$BA$4:$BA$493) -> 0 | L55: =SUMIF(ProductList!$F$4:$F$493,A55,ProductList!$V$4:$V$493) -> 0 | M55: =SUMIF(ProductList!$F$4:$F$493,A55,ProductList!$K$4:$K$493) -> 0 | N55: KG | O55: =IF(D55="SCL",100,AZ55) -> 80 | P55: =IF((K55*Y55)>(L55*AH55),(K55*Y55),(L55*AH55)) -> 0 | Q55: =IF((K55*Z55)>(L55*AI55),(K55*Z55),(L55*AI55)) -> 0 | R55: =IF(C55="SG", IF(((K55*1.1+P55+Q55+T55+V55)*AA55)>(L55*AJ55), (K55*1.1+P55+Q55+T55+V55)*AA55, L55*AJ55), IF(((K55*1.1+P55+Q55+S55+U55)*AA55)>(L55*AJ55), (K55*1.1+P55+Q55+S55+U55)*AA55, L55*AJ55) ) -> 0 | S55: =IF((K55*AB55)>(L55*AK55),(K55*AB55),(L55*AK55)) -> 0 | T55: =IF((K55*AC55)>(L55*AL55),(K55*AC55),(L55*AL55)) -> 0 | U55: =IF((K55*AD55)>(L55*AM55),(K55*AD55),(L55*AM55)) -> 0 | V55: =IF((K55*AE55)>(L55*AN55),(K55*AE55),(L55*AN55)) -> 0 | W55: =IF((K55*AF55)>(L55*AO55),(K55*AF55),(L55*AO55)) -> 0 | X55: =IF((((K55)*1.1+P55+Q55+S55+T55+U55+V55)*AG55)>(L55*AP55),(((K55)*1.1+P55+Q55+S55+T55+U55+V55)*AG55),(L55*AP55)) -> 0 | Z55: 0.2 | AA55: 0.18 | AB55: 0.1 | AC55: 0.06 | AD55: 0.3 | AE55: 0.12 | AG55: 0.025 | AM55: 160 | AN55: 24 | AZ55: =AZ54 -> 80
A56: 39269099 | B56: PLASTICS - OTHERS | D56: NORM | E56: =IF(D56="SCL",G56,H56) -> 0 | H56: =ROUND(I56,0) -> 0 | I56: =IF(AND(L56<>"",L56<>0),ROUND(J56/L56,0),0) -> 0 | J56: =IF(C56="SG",ROUND((P56+Q56+R56+T56+V56+W56+X56),0),ROUND((P56+Q56+R56+S56+U56+W56+X56),0)) -> 0 | K56: =SUMIF(ProductList!$F$4:$F$493,A56,ProductList!$BA$4:$BA$493) -> 0 | L56: =SUMIF(ProductList!$F$4:$F$493,A56,ProductList!$V$4:$V$493) -> 0 | M56: =SUMIF(ProductList!$F$4:$F$493,A56,ProductList!$K$4:$K$493) -> 0 | N56: KG | O56: =IF(D56="SCL",100,AZ56) -> 80 | P56: =IF((K56*Y56)>(L56*AH56),(K56*Y56),(L56*AH56)) -> 0 | Q56: =IF((K56*Z56)>(L56*AI56),(K56*Z56),(L56*AI56)) -> 0 | R56: =IF(C56="SG", IF(((K56*1.1+P56+Q56+T56+V56)*AA56)>(L56*AJ56), (K56*1.1+P56+Q56+T56+V56)*AA56, L56*AJ56), IF(((K56*1.1+P56+Q56+S56+U56)*AA56)>(L56*AJ56), (K56*1.1+P56+Q56+S56+U56)*AA56, L56*AJ56) ) -> 0 | S56: =IF((K56*AB56)>(L56*AK56),(K56*AB56),(L56*AK56)) -> 0 | T56: =IF((K56*AC56)>(L56*AL56),(K56*AC56),(L56*AL56)) -> 0 | U56: =IF((K56*AD56)>(L56*AM56),(K56*AD56),(L56*AM56)) -> 0 | V56: =IF((K56*AE56)>(L56*AN56),(K56*AE56),(L56*AN56)) -> 0 | W56: =IF((K56*AF56)>(L56*AO56),(K56*AF56),(L56*AO56)) -> 0 | X56: =IF((((K56)*1.1+P56+Q56+S56+T56+U56+V56)*AG56)>(L56*AP56),(((K56)*1.1+P56+Q56+S56+T56+U56+V56)*AG56),(L56*AP56)) -> 0 | Z56: 0.2 | AA56: 0.18 | AB56: 0.1 | AC56: 0.06 | AD56: 0.1 | AE56: 0.12 | AG56: 0.025 | AI56: 60 | AM56: 16 | AZ56: =AZ55 -> 80
A57: 56079090 | B57: POOJA ROPE | D57: NORM | E57: =IF(D57="SCL",G57,H57) -> 0 | H57: =ROUND(I57,0) -> 0 | I57: =IF(AND(L57<>"",L57<>0),ROUND(J57/L57,0),0) -> 0 | J57: =IF(C57="SG",ROUND((P57+Q57+R57+T57+V57+W57+X57),0),ROUND((P57+Q57+R57+S57+U57+W57+X57),0)) -> 0 | K57: =SUMIF(ProductList!$F$4:$F$493,A57,ProductList!$BA$4:$BA$493) -> 0 | L57: =SUMIF(ProductList!$F$4:$F$493,A57,ProductList!$V$4:$V$493) -> 0 | M57: =SUMIF(ProductList!$F$4:$F$493,A57,ProductList!$K$4:$K$493) -> 0 | N57: KG | O57: =IF(D57="SCL",100,AZ57) -> 80 | P57: =IF((K57*Y57)>(L57*AH57),(K57*Y57),(L57*AH57)) -> 0 | Q57: =IF((K57*Z57)>(L57*AI57),(K57*Z57),(L57*AI57)) -> 0 | R57: =IF(C57="SG", IF(((K57*1.1+P57+Q57+T57+V57)*AA57)>(L57*AJ57), (K57*1.1+P57+Q57+T57+V57)*AA57, L57*AJ57), IF(((K57*1.1+P57+Q57+S57+U57)*AA57)>(L57*AJ57), (K57*1.1+P57+Q57+S57+U57)*AA57, L57*AJ57) ) -> 0 | S57: =IF((K57*AB57)>(L57*AK57),(K57*AB57),(L57*AK57)) -> 0 | T57: =IF((K57*AC57)>(L57*AL57),(K57*AC57),(L57*AL57)) -> 0 | U57: =IF((K57*AD57)>(L57*AM57),(K57*AD57),(L57*AM57)) -> 0 | V57: =IF((K57*AE57)>(L57*AN57),(K57*AE57),(L57*AN57)) -> 0 | W57: =IF((K57*AF57)>(L57*AO57),(K57*AF57),(L57*AO57)) -> 0 | X57: =IF((((K57)*1.1+P57+Q57+S57+T57+U57+V57)*AG57)>(L57*AP57),(((K57)*1.1+P57+Q57+S57+T57+U57+V57)*AG57),(L57*AP57)) -> 0 | Z57: 0.2 | AA57: 0.18 | AB57: 0.1 | AC57: 0.06 | AD57: 0.15 | AG57: 0.025 | AI57: 130 | AM57: 70 | AZ57: =AZ56 -> 80
A58: 84818090 | B58: TAPS, COOKS, VALES AND SIMILAR APPLIANCES | D58: NORM | E58: =IF(D58="SCL",G58,H58) -> 0 | H58: =ROUND(I58,0) -> 0 | I58: =IF(AND(L58<>"",L58<>0),ROUND(J58/L58,0),0) -> 0 | J58: =IF(C58="SG",ROUND((P58+Q58+R58+T58+V58+W58+X58),0),ROUND((P58+Q58+R58+S58+U58+W58+X58),0)) -> 0 | K58: =SUMIF(ProductList!$F$4:$F$493,A58,ProductList!$BA$4:$BA$493) -> 0 | L58: =SUMIF(ProductList!$F$4:$F$493,A58,ProductList!$V$4:$V$493) -> 0 | M58: =SUMIF(ProductList!$F$4:$F$493,A58,ProductList!$K$4:$K$493) -> 0 | N58: KG | O58: =IF(D58="SCL",100,AZ58) -> 80 | P58: =IF((K58*Y58)>(L58*AH58),(K58*Y58),(L58*AH58)) -> 0 | Q58: =IF((K58*Z58)>(L58*AI58),(K58*Z58),(L58*AI58)) -> 0 | R58: =IF(C58="SG", IF(((K58*1.1+P58+Q58+T58+V58)*AA58)>(L58*AJ58), (K58*1.1+P58+Q58+T58+V58)*AA58, L58*AJ58), IF(((K58*1.1+P58+Q58+S58+U58)*AA58)>(L58*AJ58), (K58*1.1+P58+Q58+S58+U58)*AA58, L58*AJ58) ) -> 0 | S58: =IF((K58*AB58)>(L58*AK58),(K58*AB58),(L58*AK58)) -> 0 | T58: =IF((K58*AC58)>(L58*AL58),(K58*AC58),(L58*AL58)) -> 0 | U58: =IF((K58*AD58)>(L58*AM58),(K58*AD58),(L58*AM58)) -> 0 | V58: =IF((K58*AE58)>(L58*AN58),(K58*AE58),(L58*AN58)) -> 0 | W58: =IF((K58*AF58)>(L58*AO58),(K58*AF58),(L58*AO58)) -> 0 | X58: =IF((((K58)*1.1+P58+Q58+S58+T58+U58+V58)*AG58)>(L58*AP58),(((K58)*1.1+P58+Q58+S58+T58+U58+V58)*AG58),(L58*AP58)) -> 0 | AA58: 0.18 | AB58: 0.075 | AC58: 0.06 | AG58: 0.025 | AZ58: =AZ57 -> 80
A59: 23024090 | B59: BIRD FOOD | D59: NORM | E59: =IF(D59="SCL",G59,H59) -> 0 | H59: =ROUND(I59,0) -> 0 | I59: =IF(AND(L59<>"",L59<>0),ROUND(J59/L59,0),0) -> 0 | J59: =IF(C59="SG",ROUND((P59+Q59+R59+T59+V59+W59+X59),0),ROUND((P59+Q59+R59+S59+U59+W59+X59),0)) -> 0 | K59: =SUMIF(ProductList!$F$4:$F$493,A59,ProductList!$BA$4:$BA$493) -> 0 | L59: =SUMIF(ProductList!$F$4:$F$493,A59,ProductList!$V$4:$V$493) -> 0 | M59: =SUMIF(ProductList!$F$4:$F$493,A59,ProductList!$K$4:$K$493) -> 0 | N59: KG | O59: =IF(D59="SCL",100,AZ59) -> 80 | P59: =IF((K59*Y59)>(L59*AH59),(K59*Y59),(L59*AH59)) -> 0 | Q59: =IF((K59*Z59)>(L59*AI59),(K59*Z59),(L59*AI59)) -> 0 | R59: =IF(C59="SG", IF(((K59*1.1+P59+Q59+T59+V59)*AA59)>(L59*AJ59), (K59*1.1+P59+Q59+T59+V59)*AA59, L59*AJ59), IF(((K59*1.1+P59+Q59+S59+U59)*AA59)>(L59*AJ59), (K59*1.1+P59+Q59+S59+U59)*AA59, L59*AJ59) ) -> 0 | S59: =IF((K59*AB59)>(L59*AK59),(K59*AB59),(L59*AK59)) -> 0 | T59: =IF((K59*AC59)>(L59*AL59),(K59*AC59),(L59*AL59)) -> 0 | U59: =IF((K59*AD59)>(L59*AM59),(K59*AD59),(L59*AM59)) -> 0 | V59: =IF((K59*AE59)>(L59*AN59),(K59*AE59),(L59*AN59)) -> 0 | W59: =IF((K59*AF59)>(L59*AO59),(K59*AF59),(L59*AO59)) -> 0 | X59: =IF((((K59)*1.1+P59+Q59+S59+T59+U59+V59)*AG59)>(L59*AP59),(((K59)*1.1+P59+Q59+S59+T59+U59+V59)*AG59),(L59*AP59)) -> 0 | Z59: 0.2 | AA59: 0.18 | AG59: 0.025 | AZ59: =AZ58 -> 80
A60: 11010090 | B60: RAVA | D60: NORM | E60: =IF(D60="SCL",G60,H60) -> 0 | H60: =ROUND(I60,0) -> 0 | I60: =IF(AND(L60<>"",L60<>0),ROUND(J60/L60,0),0) -> 0 | J60: =IF(C60="SG",ROUND((P60+Q60+R60+T60+V60+W60+X60),0),ROUND((P60+Q60+R60+S60+U60+W60+X60),0)) -> 0 | K60: =SUMIF(ProductList!$F$4:$F$493,A60,ProductList!$BA$4:$BA$493) -> 0 | L60: =SUMIF(ProductList!$F$4:$F$493,A60,ProductList!$V$4:$V$493) -> 0 | M60: =SUMIF(ProductList!$F$4:$F$493,A60,ProductList!$K$4:$K$493) -> 0 | N60: KG | O60: =IF(D60="SCL",100,AZ60) -> 80 | P60: =IF((K60*Y60)>(L60*AH60),(K60*Y60),(L60*AH60)) -> 0 | Q60: =IF((K60*Z60)>(L60*AI60),(K60*Z60),(L60*AI60)) -> 0 | R60: =IF(C60="SG", IF(((K60*1.1+P60+Q60+T60+V60)*AA60)>(L60*AJ60), (K60*1.1+P60+Q60+T60+V60)*AA60, L60*AJ60), IF(((K60*1.1+P60+Q60+S60+U60)*AA60)>(L60*AJ60), (K60*1.1+P60+Q60+S60+U60)*AA60, L60*AJ60) ) -> 0 | S60: =IF((K60*AB60)>(L60*AK60),(K60*AB60),(L60*AK60)) -> 0 | T60: =IF((K60*AC60)>(L60*AL60),(K60*AC60),(L60*AL60)) -> 0 | U60: =IF((K60*AD60)>(L60*AM60),(K60*AD60),(L60*AM60)) -> 0 | V60: =IF((K60*AE60)>(L60*AN60),(K60*AE60),(L60*AN60)) -> 0 | W60: =IF((K60*AF60)>(L60*AO60),(K60*AF60),(L60*AO60)) -> 0 | X60: =IF((((K60)*1.1+P60+Q60+S60+T60+U60+V60)*AG60)>(L60*AP60),(((K60)*1.1+P60+Q60+S60+T60+U60+V60)*AG60),(L60*AP60)) -> 0 | Z60: 0.2 | AA60: 0.18 | AB60: 0.1 | AG60: 0.025 | AZ60: =AZ59 -> 80
A61: 11042200 | B61: OATS | D61: NORM | E61: =IF(D61="SCL",G61,H61) -> 441 | H61: =ROUND(I61,0) -> 441 | I61: =IF(AND(L61<>"",L61<>0),ROUND(J61/L61,0),0) -> 441 | J61: =IF(C61="SG",ROUND((P61+Q61+R61+T61+V61+W61+X61),0),ROUND((P61+Q61+R61+S61+U61+W61+X61),0)) -> 95211 | K61: =SUMIF(ProductList!$F$4:$F$493,A61,ProductList!$BA$4:$BA$493) -> 98845.6 | L61: =SUMIF(ProductList!$F$4:$F$493,A61,ProductList!$V$4:$V$493) -> 216 | M61: =SUMIF(ProductList!$F$4:$F$493,A61,ProductList!$K$4:$K$493) -> 0 | N61: KG | O61: =IF(D61="SCL",100,AZ61) -> 80 | P61: =IF((K61*Y61)>(L61*AH61),(K61*Y61),(L61*AH61)) -> 0 | Q61: =IF((K61*Z61)>(L61*AI61),(K61*Z61),(L61*AI61)) -> 25920 | R61: =IF(C61="SG", IF(((K61*1.1+P61+Q61+T61+V61)*AA61)>(L61*AJ61), (K61*1.1+P61+Q61+T61+V61)*AA61, L61*AJ61), IF(((K61*1.1+P61+Q61+S61+U61)*AA61)>(L61*AJ61), (K61*1.1+P61+Q61+S61+U61)*AA61, L61*AJ61) ) -> 30464.302 | S61: =IF((K61*AB61)>(L61*AK61),(K61*AB61),(L61*AK61)) -> 9884.56 | T61: =IF((K61*AC61)>(L61*AL61),(K61*AC61),(L61*AL61)) -> 0 | U61: =IF((K61*AD61)>(L61*AM61),(K61*AD61),(L61*AM61)) -> 24711.4 | V61: =IF((K61*AE61)>(L61*AN61),(K61*AE61),(L61*AN61)) -> 0 | W61: =IF((K61*AF61)>(L61*AO61),(K61*AF61),(L61*AO61)) -> 0 | X61: =IF((((K61)*1.1+P61+Q61+S61+T61+U61+V61)*AG61)>(L61*AP61),(((K61)*1.1+P61+Q61+S61+T61+U61+V61)*AG61),(L61*AP61)) -> 4231.153 | Z61: 0.2 | AA61: 0.18 | AB61: 0.1 | AD61: 0.25 | AG61: 0.025 | AI61: 120 | AM61: 100 | AZ61: =AZ60 -> 80
A62: 19023000 | B62: NOODLE, PASTA | D62: NORM | E62: =IF(D62="SCL",G62,H62) -> 0 | F62: S | H62: =ROUND(I62,0) -> 0 | I62: =IF(AND(L62<>"",L62<>0),ROUND(J62/L62,0),0) -> 0 | J62: =IF(C62="SG",ROUND((P62+Q62+R62+T62+V62+W62+X62),0),ROUND((P62+Q62+R62+S62+U62+W62+X62),0)) -> 0 | K62: =SUMIF(ProductList!$F$4:$F$493,A62,ProductList!$BA$4:$BA$493) -> 0 | L62: =SUMIF(ProductList!$F$4:$F$493,A62,ProductList!$V$4:$V$493) -> 0 | M62: =SUMIF(ProductList!$F$4:$F$493,A62,ProductList!$K$4:$K$493) -> 0 | N62: KG | O62: =IF(D62="SCL",100,AZ62) -> 80 | P62: =IF((K62*Y62)>(L62*AH62),(K62*Y62),(L62*AH62)) -> 0 | Q62: =IF((K62*Z62)>(L62*AI62),(K62*Z62),(L62*AI62)) -> 0 | R62: =IF(C62="SG", IF(((K62*1.1+P62+Q62+T62+V62)*AA62)>(L62*AJ62), (K62*1.1+P62+Q62+T62+V62)*AA62, L62*AJ62), IF(((K62*1.1+P62+Q62+S62+U62)*AA62)>(L62*AJ62), (K62*1.1+P62+Q62+S62+U62)*AA62, L62*AJ62) ) -> 0 | S62: =IF((K62*AB62)>(L62*AK62),(K62*AB62),(L62*AK62)) -> 0 | T62: =IF((K62*AC62)>(L62*AL62),(K62*AC62),(L62*AL62)) -> 0 | U62: =IF((K62*AD62)>(L62*AM62),(K62*AD62),(L62*AM62)) -> 0 | V62: =IF((K62*AE62)>(L62*AN62),(K62*AE62),(L62*AN62)) -> 0 | W62: =IF((K62*AF62)>(L62*AO62),(K62*AF62),(L62*AO62)) -> 0 | X62: =IF((((K62)*1.1+P62+Q62+S62+T62+U62+V62)*AG62)>(L62*AP62),(((K62)*1.1+P62+Q62+S62+T62+U62+V62)*AG62),(L62*AP62)) -> 0 | Z62: 0.2 | AA62: 0.18 | AB62: 0.1 | AD62: 0.3 | AE62: 0.24 | AG62: 0.025 | AI62: 160 | AM62: 140 | AN62: 64 | AZ62: =AZ61 -> 80
A63: 07119090 | B63: PRESERVED VEGGIES | D63: NORM | E63: =IF(D63="SCL",G63,H63) -> 0 | H63: =ROUND(I63,0) -> 0 | I63: =IF(AND(L63<>"",L63<>0),ROUND(J63/L63,0),0) -> 0 | J63: =IF(C63="SG",ROUND((P63+Q63+R63+T63+V63+W63+X63),0),ROUND((P63+Q63+R63+S63+U63+W63+X63),0)) -> 0 | K63: =SUMIF(ProductList!$F$4:$F$493,A63,ProductList!$BA$4:$BA$493) -> 0 | L63: =SUMIF(ProductList!$F$4:$F$493,A63,ProductList!$V$4:$V$493) -> 0 | M63: =SUMIF(ProductList!$F$4:$F$493,A63,ProductList!$K$4:$K$493) -> 0 | N63: KG | O63: =IF(D63="SCL",100,AZ63) -> 80 | P63: =IF((K63*Y63)>(L63*AH63),(K63*Y63),(L63*AH63)) -> 0 | Q63: =IF((K63*Z63)>(L63*AI63),(K63*Z63),(L63*AI63)) -> 0 | R63: =IF(C63="SG", IF(((K63*1.1+P63+Q63+T63+V63)*AA63)>(L63*AJ63), (K63*1.1+P63+Q63+T63+V63)*AA63, L63*AJ63), IF(((K63*1.1+P63+Q63+S63+U63)*AA63)>(L63*AJ63), (K63*1.1+P63+Q63+S63+U63)*AA63, L63*AJ63) ) -> 0 | S63: =IF((K63*AB63)>(L63*AK63),(K63*AB63),(L63*AK63)) -> 0 | T63: =IF((K63*AC63)>(L63*AL63),(K63*AC63),(L63*AL63)) -> 0 | U63: =IF((K63*AD63)>(L63*AM63),(K63*AD63),(L63*AM63)) -> 0 | V63: =IF((K63*AE63)>(L63*AN63),(K63*AE63),(L63*AN63)) -> 0 | W63: =IF((K63*AF63)>(L63*AO63),(K63*AF63),(L63*AO63)) -> 0 | X63: =IF((((K63)*1.1+P63+Q63+S63+T63+U63+V63)*AG63)>(L63*AP63),(((K63)*1.1+P63+Q63+S63+T63+U63+V63)*AG63),(L63*AP63)) -> 0 | Z63: 0.2 | AA63: 0.18 | AB63: 0.1 | AD63: 0.4 | AG63: 0.025 | AM63: 270 | AZ63: =AZ62 -> 80
A64: 04069000 | B64: PANEER | D64: NORM | E64: =IF(D64="SCL",G64,H64) -> 0 | H64: =ROUND(I64,0) -> 0 | I64: =IF(AND(L64<>"",L64<>0),ROUND(J64/L64,0),0) -> 0 | J64: =IF(C64="SG",ROUND((P64+Q64+R64+T64+V64+W64+X64),0),ROUND((P64+Q64+R64+S64+U64+W64+X64),0)) -> 0 | K64: =SUMIF(ProductList!$F$4:$F$493,A64,ProductList!$BA$4:$BA$493) -> 0 | L64: =SUMIF(ProductList!$F$4:$F$493,A64,ProductList!$V$4:$V$493) -> 0 | M64: =SUMIF(ProductList!$F$4:$F$493,A64,ProductList!$K$4:$K$493) -> 0 | N64: KG | O64: =IF(D64="SCL",100,AZ64) -> 80 | P64: =IF((K64*Y64)>(L64*AH64),(K64*Y64),(L64*AH64)) -> 0 | Q64: =IF((K64*Z64)>(L64*AI64),(K64*Z64),(L64*AI64)) -> 0 | R64: =IF(C64="SG", IF(((K64*1.1+P64+Q64+T64+V64)*AA64)>(L64*AJ64), (K64*1.1+P64+Q64+T64+V64)*AA64, L64*AJ64), IF(((K64*1.1+P64+Q64+S64+U64)*AA64)>(L64*AJ64), (K64*1.1+P64+Q64+S64+U64)*AA64, L64*AJ64) ) -> 0 | S64: =IF((K64*AB64)>(L64*AK64),(K64*AB64),(L64*AK64)) -> 0 | T64: =IF((K64*AC64)>(L64*AL64),(K64*AC64),(L64*AL64)) -> 0 | U64: =IF((K64*AD64)>(L64*AM64),(K64*AD64),(L64*AM64)) -> 0 | V64: =IF((K64*AE64)>(L64*AN64),(K64*AE64),(L64*AN64)) -> 0 | W64: =IF((K64*AF64)>(L64*AO64),(K64*AF64),(L64*AO64)) -> 0 | X64: =IF((((K64)*1.1+P64+Q64+S64+T64+U64+V64)*AG64)>(L64*AP64),(((K64)*1.1+P64+Q64+S64+T64+U64+V64)*AG64),(L64*AP64)) -> 0 | Z64: 0.2 | AA64: 0.18 | AB64: 0.1 | AD64: 0.4 | AG64: 0.025 | AI64: 650 | AM64: 800 | AZ64: =AZ63 -> 80
A65: 04039000 | B65: CREAM | D65: NORM | E65: =IF(D65="SCL",G65,H65) -> 0 | H65: =ROUND(I65,0) -> 0 | I65: =IF(AND(L65<>"",L65<>0),ROUND(J65/L65,0),0) -> 0 | J65: =IF(C65="SG",ROUND((P65+Q65+R65+T65+V65+W65+X65),0),ROUND((P65+Q65+R65+S65+U65+W65+X65),0)) -> 0 | K65: =SUMIF(ProductList!$F$4:$F$493,A65,ProductList!$BA$4:$BA$493) -> 0 | L65: =SUMIF(ProductList!$F$4:$F$493,A65,ProductList!$V$4:$V$493) -> 0 | M65: =SUMIF(ProductList!$F$4:$F$493,A65,ProductList!$K$4:$K$493) -> 0 | N65: KG | O65: =IF(D65="SCL",100,AZ65) -> 80 | P65: =IF((K65*Y65)>(L65*AH65),(K65*Y65),(L65*AH65)) -> 0 | Q65: =IF((K65*Z65)>(L65*AI65),(K65*Z65),(L65*AI65)) -> 0 | R65: =IF(C65="SG", IF(((K65*1.1+P65+Q65+T65+V65)*AA65)>(L65*AJ65), (K65*1.1+P65+Q65+T65+V65)*AA65, L65*AJ65), IF(((K65*1.1+P65+Q65+S65+U65)*AA65)>(L65*AJ65), (K65*1.1+P65+Q65+S65+U65)*AA65, L65*AJ65) ) -> 0 | S65: =IF((K65*AB65)>(L65*AK65),(K65*AB65),(L65*AK65)) -> 0 | T65: =IF((K65*AC65)>(L65*AL65),(K65*AC65),(L65*AL65)) -> 0 | U65: =IF((K65*AD65)>(L65*AM65),(K65*AD65),(L65*AM65)) -> 0 | V65: =IF((K65*AE65)>(L65*AN65),(K65*AE65),(L65*AN65)) -> 0 | W65: =IF((K65*AF65)>(L65*AO65),(K65*AF65),(L65*AO65)) -> 0 | X65: =IF((((K65)*1.1+P65+Q65+S65+T65+U65+V65)*AG65)>(L65*AP65),(((K65)*1.1+P65+Q65+S65+T65+U65+V65)*AG65),(L65*AP65)) -> 0 | Z65: 0.2 | AA65: 0.18 | AD65: 0.1 | AG65: 0.025 | AI65: 750 | AM65: 400 | AZ65: =AZ64 -> 80
A66: 08134090 | B66: FRUITES DRIED - OTHER | D66: NORM | E66: =IF(D66="SCL",G66,H66) -> 636 | H66: =ROUND(I66,0) -> 636 | I66: =IF(AND(L66<>"",L66<>0),ROUND(J66/L66,0),0) -> 636 | J66: =IF(C66="SG",ROUND((P66+Q66+R66+T66+V66+W66+X66),0),ROUND((P66+Q66+R66+S66+U66+W66+X66),0)) -> 127130 | K66: =SUMIF(ProductList!$F$4:$F$493,A66,ProductList!$BA$4:$BA$493) -> 109828.8 | L66: =SUMIF(ProductList!$F$4:$F$493,A66,ProductList!$V$4:$V$493) -> 200 | M66: =SUMIF(ProductList!$F$4:$F$493,A66,ProductList!$K$4:$K$493) -> 0 | N66: KG | O66: =IF(D66="SCL",100,AZ66) -> 80 | P66: =IF((K66*Y66)>(L66*AH66),(K66*Y66),(L66*AH66)) -> 0 | Q66: =IF((K66*Z66)>(L66*AI66),(K66*Z66),(L66*AI66)) -> 21965.76 | R66: =IF(C66="SG", IF(((K66*1.1+P66+Q66+T66+V66)*AA66)>(L66*AJ66), (K66*1.1+P66+Q66+T66+V66)*AA66, L66*AJ66), IF(((K66*1.1+P66+Q66+S66+U66)*AA66)>(L66*AJ66), (K66*1.1+P66+Q66+S66+U66)*AA66, L66*AJ66) ) -> 37036.858 | S66: =IF((K66*AB66)>(L66*AK66),(K66*AB66),(L66*AK66)) -> 10982.88 | T66: =IF((K66*AC66)>(L66*AL66),(K66*AC66),(L66*AL66)) -> 0 | U66: =IF((K66*AD66)>(L66*AM66),(K66*AD66),(L66*AM66)) -> 52000 | V66: =IF((K66*AE66)>(L66*AN66),(K66*AE66),(L66*AN66)) -> 0 | W66: =IF((K66*AF66)>(L66*AO66),(K66*AF66),(L66*AO66)) -> 0 | X66: =IF((((K66)*1.1+P66+Q66+S66+T66+U66+V66)*AG66)>(L66*AP66),(((K66)*1.1+P66+Q66+S66+T66+U66+V66)*AG66),(L66*AP66)) -> 5144.008 | Z66: 0.2 | AA66: 0.18 | AB66: 0.1 | AD66: 0.4 | AG66: 0.025 | AM66: 260 | AZ66: =AZ65 -> 80
A67: 08134010 | B67: TAMARIND | D67: NORM | E67: =IF(D67="SCL",G67,H67) -> 0 | H67: =ROUND(I67,0) -> 0 | I67: =IF(AND(L67<>"",L67<>0),ROUND(J67/L67,0),0) -> 0 | J67: =IF(C67="SG",ROUND((P67+Q67+R67+T67+V67+W67+X67),0),ROUND((P67+Q67+R67+S67+U67+W67+X67),0)) -> 0 | K67: =SUMIF(ProductList!$F$4:$F$493,A67,ProductList!$BA$4:$BA$493) -> 0 | L67: =SUMIF(ProductList!$F$4:$F$493,A67,ProductList!$V$4:$V$493) -> 0 | M67: =SUMIF(ProductList!$F$4:$F$493,A67,ProductList!$K$4:$K$493) -> 0 | N67: KG | O67: =IF(D67="SCL",100,AZ67) -> 80 | P67: =IF((K67*Y67)>(L67*AH67),(K67*Y67),(L67*AH67)) -> 0 | Q67: =IF((K67*Z67)>(L67*AI67),(K67*Z67),(L67*AI67)) -> 0 | R67: =IF(C67="SG", IF(((K67*1.1+P67+Q67+T67+V67)*AA67)>(L67*AJ67), (K67*1.1+P67+Q67+T67+V67)*AA67, L67*AJ67), IF(((K67*1.1+P67+Q67+S67+U67)*AA67)>(L67*AJ67), (K67*1.1+P67+Q67+S67+U67)*AA67, L67*AJ67) ) -> 0 | S67: =IF((K67*AB67)>(L67*AK67),(K67*AB67),(L67*AK67)) -> 0 | T67: =IF((K67*AC67)>(L67*AL67),(K67*AC67),(L67*AL67)) -> 0 | U67: =IF((K67*AD67)>(L67*AM67),(K67*AD67),(L67*AM67)) -> 0 | V67: =IF((K67*AE67)>(L67*AN67),(K67*AE67),(L67*AN67)) -> 0 | W67: =IF((K67*AF67)>(L67*AO67),(K67*AF67),(L67*AO67)) -> 0 | X67: =IF((((K67)*1.1+P67+Q67+S67+T67+U67+V67)*AG67)>(L67*AP67),(((K67)*1.1+P67+Q67+S67+T67+U67+V67)*AG67),(L67*AP67)) -> 0 | Z67: 0.2 | AA67: 0.18 | AD67: 0.25 | AG67: 0.025 | AM67: 275 | AZ67: =AZ66 -> 80
A68: 70109010 | B68: MT BOTTLES | D68: NORM | E68: =IF(D68="SCL",G68,H68) -> 0 | H68: =ROUND(I68,0) -> 0 | I68: =IF(AND(L68<>"",L68<>0),ROUND(J68/L68,0),0) -> 0 | J68: =IF(C68="SG",ROUND((P68+Q68+R68+T68+V68+W68+X68),0),ROUND((P68+Q68+R68+S68+U68+W68+X68),0)) -> 0 | K68: =SUMIF(ProductList!$F$4:$F$493,A68,ProductList!$BA$4:$BA$493) -> 0 | L68: =SUMIF(ProductList!$F$4:$F$493,A68,ProductList!$V$4:$V$493) -> 0 | M68: =SUMIF(ProductList!$F$4:$F$493,A68,ProductList!$K$4:$K$493) -> 0 | N68: KG | O68: =IF(D68="SCL",100,AZ68) -> 80 | P68: =IF((K68*Y68)>(L68*AH68),(K68*Y68),(L68*AH68)) -> 0 | Q68: =IF((K68*Z68)>(L68*AI68),(K68*Z68),(L68*AI68)) -> 0 | R68: =IF(C68="SG", IF(((K68*1.1+P68+Q68+T68+V68)*AA68)>(L68*AJ68), (K68*1.1+P68+Q68+T68+V68)*AA68, L68*AJ68), IF(((K68*1.1+P68+Q68+S68+U68)*AA68)>(L68*AJ68), (K68*1.1+P68+Q68+S68+U68)*AA68, L68*AJ68) ) -> 0 | S68: =IF((K68*AB68)>(L68*AK68),(K68*AB68),(L68*AK68)) -> 0 | T68: =IF((K68*AC68)>(L68*AL68),(K68*AC68),(L68*AL68)) -> 0 | U68: =IF((K68*AD68)>(L68*AM68),(K68*AD68),(L68*AM68)) -> 0 | V68: =IF((K68*AE68)>(L68*AN68),(K68*AE68),(L68*AN68)) -> 0 | W68: =IF((K68*AF68)>(L68*AO68),(K68*AF68),(L68*AO68)) -> 0 | X68: =IF((((K68)*1.1+P68+Q68+S68+T68+U68+V68)*AG68)>(L68*AP68),(((K68)*1.1+P68+Q68+S68+T68+U68+V68)*AG68),(L68*AP68)) -> 0 | AA68: 0.18 | AB68: 0.1 | AC68: 0.06 | AG68: 0.025 | AZ68: =AZ67 -> 80
A69: 08021190 | B69: ALMOND | D69: NORM | E69: =IF(D69="SCL",G69,H69) -> 0 | G69: 556 | H69: =ROUND(I69,0) -> 0 | I69: =IF(AND(L69<>"",L69<>0),ROUND(J69/L69,0),0) -> 0 | J69: =IF(C69="SG",ROUND((P69+Q69+R69+T69+V69+W69+X69),0),ROUND((P69+Q69+R69+S69+U69+W69+X69),0)) -> 0 | K69: =SUMIF(ProductList!$F$4:$F$493,A69,ProductList!$BA$4:$BA$493) -> 0 | L69: =SUMIF(ProductList!$F$4:$F$493,A69,ProductList!$V$4:$V$493) -> 0 | M69: =SUMIF(ProductList!$F$4:$F$493,A69,ProductList!$K$4:$K$493) -> 0 | N69: KG | O69: =IF(D69="SCL",100,AZ69) -> 80 | P69: =IF((K69*Y69)>(L69*AH69),(K69*Y69),(L69*AH69)) -> 0 | Q69: =IF((K69*Z69)>(L69*AI69),(K69*Z69),(L69*AI69)) -> 0 | R69: =IF(C69="SG", IF(((K69*1.1+P69+Q69+T69+V69)*AA69)>(L69*AJ69), (K69*1.1+P69+Q69+T69+V69)*AA69, L69*AJ69), IF(((K69*1.1+P69+Q69+S69+U69)*AA69)>(L69*AJ69), (K69*1.1+P69+Q69+S69+U69)*AA69, L69*AJ69) ) -> 0 | S69: =IF((K69*AB69)>(L69*AK69),(K69*AB69),(L69*AK69)) -> 0 | T69: =IF((K69*AC69)>(L69*AL69),(K69*AC69),(L69*AL69)) -> 0 | U69: =IF((K69*AD69)>(L69*AM69),(K69*AD69),(L69*AM69)) -> 0 | V69: =IF((K69*AE69)>(L69*AN69),(K69*AE69),(L69*AN69)) -> 0 | W69: =IF((K69*AF69)>(L69*AO69),(K69*AF69),(L69*AO69)) -> 0 | X69: =IF((((K69)*1.1+P69+Q69+S69+T69+U69+V69)*AG69)>(L69*AP69),(((K69)*1.1+P69+Q69+S69+T69+U69+V69)*AG69),(L69*AP69)) -> 0 | Z69: 0.2 | AA69: 0.18 | AB69: 0.19 | AC69: 0.06 | AD69: 0.25 | AE69: 0.24 | AG69: 0.025 | AM69: 180 | AN69: 88 | AZ69: =AZ68 -> 80
A70: 09011190 | B70: COFFEE SEEDS | D70: NORM | E70: =IF(D70="SCL",G70,H70) -> 0 | G70: 556 | H70: =ROUND(I70,0) -> 0 | I70: =IF(AND(L70<>"",L70<>0),ROUND(J70/L70,0),0) -> 0 | J70: =IF(C70="SG",ROUND((P70+Q70+R70+T70+V70+W70+X70),0),ROUND((P70+Q70+R70+S70+U70+W70+X70),0)) -> 0 | K70: =SUMIF(ProductList!$F$4:$F$493,A70,ProductList!$BA$4:$BA$493) -> 0 | L70: =SUMIF(ProductList!$F$4:$F$493,A70,ProductList!$V$4:$V$493) -> 0 | M70: =SUMIF(ProductList!$F$4:$F$493,A70,ProductList!$K$4:$K$493) -> 0 | N70: KG | O70: =IF(D70="SCL",100,AZ70) -> 80 | P70: =IF((K70*Y70)>(L70*AH70),(K70*Y70),(L70*AH70)) -> 0 | Q70: =IF((K70*Z70)>(L70*AI70),(K70*Z70),(L70*AI70)) -> 0 | R70: =IF(C70="SG", IF(((K70*1.1+P70+Q70+T70+V70)*AA70)>(L70*AJ70), (K70*1.1+P70+Q70+T70+V70)*AA70, L70*AJ70), IF(((K70*1.1+P70+Q70+S70+U70)*AA70)>(L70*AJ70), (K70*1.1+P70+Q70+S70+U70)*AA70, L70*AJ70) ) -> 0 | S70: =IF((K70*AB70)>(L70*AK70),(K70*AB70),(L70*AK70)) -> 0 | T70: =IF((K70*AC70)>(L70*AL70),(K70*AC70),(L70*AL70)) -> 0 | U70: =IF((K70*AD70)>(L70*AM70),(K70*AD70),(L70*AM70)) -> 0 | V70: =IF((K70*AE70)>(L70*AN70),(K70*AE70),(L70*AN70)) -> 0 | W70: =IF((K70*AF70)>(L70*AO70),(K70*AF70),(L70*AO70)) -> 0 | X70: =IF((((K70)*1.1+P70+Q70+S70+T70+U70+V70)*AG70)>(L70*AP70),(((K70)*1.1+P70+Q70+S70+T70+U70+V70)*AG70),(L70*AP70)) -> 0 | Z70: 0.2 | AA70: 0.18 | AD70: 0.25 | AG70: 0.025 | AZ70: =AZ69 -> 80
A71: 11029020 | B71: KURAKKAN FLOUR | D71: NORM | E71: =IF(D71="SCL",G71,H71) -> 107 | F71: L | G71: 556 | H71: =ROUND(I71,0) -> 107 | I71: =IF(AND(L71<>"",L71<>0),ROUND(J71/L71,0),0) -> 107 | J71: =IF(C71="SG",ROUND((P71+Q71+R71+T71+V71+W71+X71),0),ROUND((P71+Q71+R71+S71+U71+W71+X71),0)) -> 10671 | K71: =SUMIF(ProductList!$F$4:$F$493,A71,ProductList!$BA$4:$BA$493) -> 18178.4 | L71: =SUMIF(ProductList!$F$4:$F$493,A71,ProductList!$V$4:$V$493) -> 100 | M71: =SUMIF(ProductList!$F$4:$F$493,A71,ProductList!$K$4:$K$493) -> 0 | N71: KG | O71: =IF(D71="SCL",100,AZ71) -> 80 | P71: =IF((K71*Y71)>(L71*AH71),(K71*Y71),(L71*AH71)) -> 0 | Q71: =IF((K71*Z71)>(L71*AI71),(K71*Z71),(L71*AI71)) -> 3635.68 | R71: =IF(C71="SG", IF(((K71*1.1+P71+Q71+T71+V71)*AA71)>(L71*AJ71), (K71*1.1+P71+Q71+T71+V71)*AA71, L71*AJ71), IF(((K71*1.1+P71+Q71+S71+U71)*AA71)>(L71*AJ71), (K71*1.1+P71+Q71+S71+U71)*AA71, L71*AJ71) ) -> 4580.9568 | S71: =IF((K71*AB71)>(L71*AK71),(K71*AB71),(L71*AK71)) -> 0 | T71: =IF((K71*AC71)>(L71*AL71),(K71*AC71),(L71*AL71)) -> 0 | U71: =IF((K71*AD71)>(L71*AM71),(K71*AD71),(L71*AM71)) -> 1817.84 | V71: =IF((K71*AE71)>(L71*AN71),(K71*AE71),(L71*AN71)) -> 0 | W71: =IF((K71*AF71)>(L71*AO71),(K71*AF71),(L71*AO71)) -> 0 | X71: =IF((((K71)*1.1+P71+Q71+S71+T71+U71+V71)*AG71)>(L71*AP71),(((K71)*1.1+P71+Q71+S71+T71+U71+V71)*AG71),(L71*AP71)) -> 636.244 | Z71: 0.2 | AA71: 0.18 | AD71: 0.1 | AG71: 0.025 | AZ71: =AZ70 -> 80
A72: 250100 | B72: SALT | D72: SCL | E72: =IF(D72="SCL",G72,H72) -> 40 | F72: L/S | G72: 40 | H72: =ROUND(I72,0) -> 0 | I72: =IF(AND(L72<>"",L72<>0),ROUND(J72/L72,0),0) -> 0 | J72: =IF(C72="SG",ROUND((P72+Q72+R72+T72+V72+W72+X72),0),ROUND((P72+Q72+R72+S72+U72+W72+X72),0)) -> 0 | K72: =SUMIF(ProductList!$F$4:$F$493,A72,ProductList!$BA$4:$BA$493) -> 0 | L72: =SUMIF(ProductList!$F$4:$F$493,A72,ProductList!$V$4:$V$493) -> 0 | N72: KG | O72: =IF(D72="SCL",100,AZ72) -> 100 | P72: =IF((K72*Y72)>(L72*AH72),(K72*Y72),(L72*AH72)) -> 0 | Q72: =IF((K72*Z72)>(L72*AI72),(K72*Z72),(L72*AI72)) -> 0 | R72: =IF(C72="SG", IF(((K72*1.1+P72+Q72+T72+V72)*AA72)>(L72*AJ72), (K72*1.1+P72+Q72+T72+V72)*AA72, L72*AJ72), IF(((K72*1.1+P72+Q72+S72+U72)*AA72)>(L72*AJ72), (K72*1.1+P72+Q72+S72+U72)*AA72, L72*AJ72) ) -> 0 | S72: =IF((K72*AB72)>(L72*AK72),(K72*AB72),(L72*AK72)) -> 0 | T72: =IF((K72*AC72)>(L72*AL72),(K72*AC72),(L72*AL72)) -> 0 | U72: =IF((K72*AD72)>(L72*AM72),(K72*AD72),(L72*AM72)) -> 0 | V72: =IF((K72*AE72)>(L72*AN72),(K72*AE72),(L72*AN72)) -> 0 | W72: =IF((K72*AF72)>(L72*AO72),(K72*AF72),(L72*AO72)) -> 0 | X72: =IF((((K72)*1.1+P72+Q72+S72+T72+U72+V72)*AG72)>(L72*AP72),(((K72)*1.1+P72+Q72+S72+T72+U72+V72)*AG72),(L72*AP72)) -> 0 | Z72: 0.2 | AA72: 0.18 | AD72: 0.2 | AG72: 0.025 | AI72: 40 | AM72: 40 | AZ72: =AZ71 -> 80
A73: 20081990 | B73: DRIED VEGGIES | D73: NORM | E73: =IF(D73="SCL",G73,H73) -> 0 | F73: L/S | G73: 40 | H73: =ROUND(I73,0) -> 0 | I73: =IF(AND(L73<>"",L73<>0),ROUND(J73/L73,0),0) -> 0 | J73: =IF(C73="SG",ROUND((P73+Q73+R73+T73+V73+W73+X73),0),ROUND((P73+Q73+R73+S73+U73+W73+X73),0)) -> 0 | K73: =SUMIF(ProductList!$F$4:$F$493,A73,ProductList!$BA$4:$BA$493) -> 0 | L73: =SUMIF(ProductList!$F$4:$F$493,A73,ProductList!$V$4:$V$493) -> 0 | N73: KG | O73: =IF(D73="SCL",100,AZ73) -> 80 | P73: =IF((K73*Y73)>(L73*AH73),(K73*Y73),(L73*AH73)) -> 0 | Q73: =IF((K73*Z73)>(L73*AI73),(K73*Z73),(L73*AI73)) -> 0 | R73: =IF(C73="SG", IF(((K73*1.1+P73+Q73+T73+V73)*AA73)>(L73*AJ73), (K73*1.1+P73+Q73+T73+V73)*AA73, L73*AJ73), IF(((K73*1.1+P73+Q73+S73+U73)*AA73)>(L73*AJ73), (K73*1.1+P73+Q73+S73+U73)*AA73, L73*AJ73) ) -> 0 | S73: =IF((K73*AB73)>(L73*AK73),(K73*AB73),(L73*AK73)) -> 0 | T73: =IF((K73*AC73)>(L73*AL73),(K73*AC73),(L73*AL73)) -> 0 | U73: =IF((K73*AD73)>(L73*AM73),(K73*AD73),(L73*AM73)) -> 0 | V73: =IF((K73*AE73)>(L73*AN73),(K73*AE73),(L73*AN73)) -> 0 | W73: =IF((K73*AF73)>(L73*AO73),(K73*AF73),(L73*AO73)) -> 0 | X73: =IF((((K73)*1.1+P73+Q73+S73+T73+U73+V73)*AG73)>(L73*AP73),(((K73)*1.1+P73+Q73+S73+T73+U73+V73)*AG73),(L73*AP73)) -> 0 | Z73: 0.2 | AA73: 0.18 | AB73: 0.1 | AD73: 0.45 | AG73: 0.025 | AI73: 260 | AM73: 360 | AZ73: =AZ72 -> 80
A74: 48194090 | B74: SACKS - GIFT COVERS | D74: NORM | E74: =IF(D74="SCL",G74,H74) -> 103 | H74: =ROUND(I74,0) -> 103 | I74: =IF(AND(L74<>"",L74<>0),ROUND(J74/L74,0),0) -> 103 | J74: =IF(C74="SG",ROUND((P74+Q74+R74+T74+V74+W74+X74),0),ROUND((P74+Q74+R74+S74+U74+W74+X74),0)) -> 975 | K74: =SUMIF(ProductList!$F$4:$F$493,A74,ProductList!$BA$4:$BA$493) -> 1375.2 | L74: =SUMIF(ProductList!$F$4:$F$493,A74,ProductList!$V$4:$V$493) -> 9.5 | N74: KG | O74: =IF(D74="SCL",100,AZ74) -> 80 | P74: =IF((K74*Y74)>(L74*AH74),(K74*Y74),(L74*AH74)) -> 0 | Q74: =IF((K74*Z74)>(L74*AI74),(K74*Z74),(L74*AI74)) -> 275.04 | R74: =IF(C74="SG", IF(((K74*1.1+P74+Q74+T74+V74)*AA74)>(L74*AJ74), (K74*1.1+P74+Q74+T74+V74)*AA74, L74*AJ74), IF(((K74*1.1+P74+Q74+S74+U74)*AA74)>(L74*AJ74), (K74*1.1+P74+Q74+S74+U74)*AA74, L74*AJ74) ) -> 371.304 | S74: =IF((K74*AB74)>(L74*AK74),(K74*AB74),(L74*AK74)) -> 137.52 | T74: =IF((K74*AC74)>(L74*AL74),(K74*AC74),(L74*AL74)) -> 82.512 | U74: =IF((K74*AD74)>(L74*AM74),(K74*AD74),(L74*AM74)) -> 137.52 | V74: =IF((K74*AE74)>(L74*AN74),(K74*AE74),(L74*AN74)) -> 0 | W74: =IF((K74*AF74)>(L74*AO74),(K74*AF74),(L74*AO74)) -> 0 | X74: =IF((((K74)*1.1+P74+Q74+S74+T74+U74+V74)*AG74)>(L74*AP74),(((K74)*1.1+P74+Q74+S74+T74+U74+V74)*AG74),(L74*AP74)) -> 53.6328 | Z74: 0.2 | AA74: 0.18 | AB74: 0.1 | AC74: 0.06 | AD74: 0.1 | AG74: 0.025 | AZ74: =AZ73 -> 80
A75: 73239900 | B75: PLATES | D75: NORM | E75: =IF(D75="SCL",G75,H75) -> 1304 | G75: 40 | H75: =ROUND(I75,0) -> 1304 | I75: =IF(AND(L75<>"",L75<>0),ROUND(J75/L75,0),0) -> 1304 | J75: =IF(C75="SG",ROUND((P75+Q75+R75+T75+V75+W75+X75),0),ROUND((P75+Q75+R75+S75+U75+W75+X75),0)) -> 67808 | K75: =SUMIF(ProductList!$F$4:$F$493,A75,ProductList!$BA$4:$BA$493) -> 75869.6 | L75: =SUMIF(ProductList!$F$4:$F$493,A75,ProductList!$V$4:$V$493) -> 52 | N75: KG | O75: =IF(D75="SCL",100,AZ75) -> 80 | P75: =IF((K75*Y75)>(L75*AH75),(K75*Y75),(L75*AH75)) -> 0 | Q75: =IF((K75*Z75)>(L75*AI75),(K75*Z75),(L75*AI75)) -> 15173.92 | R75: =IF(C75="SG", IF(((K75*1.1+P75+Q75+T75+V75)*AA75)>(L75*AJ75), (K75*1.1+P75+Q75+T75+V75)*AA75, L75*AJ75), IF(((K75*1.1+P75+Q75+S75+U75)*AA75)>(L75*AJ75), (K75*1.1+P75+Q75+S75+U75)*AA75, L75*AJ75) ) -> 22533.271 | S75: =IF((K75*AB75)>(L75*AK75),(K75*AB75),(L75*AK75)) -> 7586.96 | T75: =IF((K75*AC75)>(L75*AL75),(K75*AC75),(L75*AL75)) -> 4552.176 | U75: =IF((K75*AD75)>(L75*AM75),(K75*AD75),(L75*AM75)) -> 18967.4 | V75: =IF((K75*AE75)>(L75*AN75),(K75*AE75),(L75*AN75)) -> 12139.136 | W75: =IF((K75*AF75)>(L75*AO75),(K75*AF75),(L75*AO75)) -> 0 | X75: =IF((((K75)*1.1+P75+Q75+S75+T75+U75+V75)*AG75)>(L75*AP75),(((K75)*1.1+P75+Q75+S75+T75+U75+V75)*AG75),(L75*AP75)) -> 3546.9038 | Z75: 0.2 | AA75: 0.18 | AB75: 0.1 | AC75: 0.06 | AD75: 0.25 | AE75: 0.16 | AG75: 0.025 | AI75: 70 | AM75: 40 | AZ75: =AZ74 -> 80

Sheet SI
B2: 2026_6_2_NATRAJ
Q4: CUST ID | R4: GROUP
B5: DATE | C5: CAPITAL | D5: SHIPMENT | E5: DETAILS | F5: PURCHASE | G5: EXPENSES | H5: INVESTED | I5: SALES | J5: LOSSES | K5: TT ADJ | L5: GST CLAIM | M5: P/L | N5: P/L (%) | Q5: 1 | R5: NOODLES | T5: NOODLES
F6: =C21 -> 2574356 | G6: =C30 -> 2483298 | H6: =F6+G6 -> 5057654 | I6: =C33 -> 6113256 | J6: =C42 -> 135223 | K6: =C39 -> 135223 | L6: =C36 -> 128715 | M6: =I6-(H6+J6+K6)+L6 -> 913871 | N6: =ROUND(M6*100/(H6+J6+K6),2) -> 17.15 | Q6: 2 | R6: RICE | T6: HONEY
R7: GHEE | T7: GHEE
R8: COFFEE POWDER | T8: MUSTARD OIL
B9: LKR Conversion Rate | C9: 3.52 | F9: SETTLEMENT | G9: Settlement No | H9: 1 | I9: 2 | R9: PAPADS | T9: PAPADS
B10: $ Conversion Rate | C10: 95.19 | G10: Date | R10: TEA POWDER | T10: HEALTH DRINK
B11: Margin Config | C11: 15 | G11: Rate | R11: ASSORTED CURRY MASALA | T11: ASSORTED CURRY MASALA
B12: Invoice Margin | C12: 30 | G12: LKR | R12: ASSORTED MANIMARK SNACKS | T12: ASSORTED MANIMARK SNACKS
B13: Shipping Clearance Amount India (INR) | C13: 200000 | G13: INR | J13: =IF(AND(J12<>"",J11<>""),J12/J11,"") | K13: =IF(AND(K12<>"",K11<>""),K12/K11,"") | L13: =IF(AND(L12<>"",L11<>""),L12/L11,"") | M13: =IF(AND(M12<>"",M11<>""),M12/M11,"") | N13: =IF(AND(N12<>"",N11<>""),N12/N11,"") | R13: ASSORTED HALDIRAMS SNACKS | T13: ASSORTED HALDIRAMS SNACKS
B14: Shipping Clearance Amount Srilanka (LKR) | C14: 2000000 | G14: FROM | R14: MILLETS | T14: MILLETS
R15: ASSORTED PICKLES | T15: ASSORTED PICKLES
B16: PARTICULARS | C16: TOTAL | G16: 1 | K16: 2 | R16: HEALTH MIXES | T16: HEALTH MIXES
C17: INR | E17: LKR | G17: INR | I17: LKR | K17: INR | M17: LKR | R17: ASSORTED COFFEE POWDER | T17: ASSORTED COFFEE POWDER
C18: PREDICTED | D18: ACTUAL | E18: PREDICTED | F18: ACTUAL | G18: PREDICTED | H18: ACTUAL | I18: PREDICTED | J18: ACTUAL | K18: PREDICTED | L18: ACTUAL | M18: PREDICTED | N18: ACTUAL | R18: ASSORTED PAYASAM MIXES | T18: ASSORTED CHILLI POWDER
B19: PURCHASE | C19: =SUM(G19+K19) -> 2574356 | D19: =SUM(H19+L19) -> 2574356 | E19: =ROUND(C19*$C$9,0) -> 9061733 | F19: =ROUND(D19*$C$9,0) -> 9061733 | G19: =SUMIF(ProductList!$C$5:$C$493,G16,ProductList!$AA$5:$AA$493) -> 2574356 | H19: =SUMIF(ProductList!$C$5:$C$493,G16,ProductList!$AA$5:$AA$493) -> 2574356 | I19: =ROUND(G19*$C$9,0) -> 9061733 | J19: =ROUND(H19*$C$9,0) -> 9061733 | K19: =SUMIF(ProductList!$C$5:$C$493,K16,ProductList!$AA$5:$AA$493) -> 0 | L19: =SUMIF(ProductList!$C$5:$C$493,K16,ProductList!$AA$5:$AA$493) -> 0 | M19: =ROUND(K19*$C$9,0) -> 0 | N19: =ROUND(L19*$C$9,0) -> 0 | R19: OATS | T19: FOOD COLOUR
B20: GST | C20: =SUM(G20+K20) -> 128715 | D20: =SUM(H20+L20) -> 128715 | E20: =ROUND(C20*$C$9,0) -> 453077 | F20: =ROUND(D20*$C$9,0) -> 453077 | G20: =ROUND(SUMIF(ProductList!$C$5:$C$493,G16,ProductList!$AB$5:$AB$493),0) -> 128715 | H20: =ROUND(SUMIF(ProductList!$C$5:$C$493,G16,ProductList!$AB$5:$AB$493),0) -> 128715 | I20: =ROUND(G20*$C$9,0) -> 453077 | J20: =ROUND(H20*$C$9,0) -> 453077 | K20: =ROUND(SUMIF(ProductList!$C$5:$C$493,K16,ProductList!$AB$5:$AB$493),0) -> 0 | L20: =ROUND(SUMIF(ProductList!$C$5:$C$493,K16,ProductList!$AB$5:$AB$493),0) -> 0 | M20: =ROUND(K20*$C$9,0) -> 0 | N20: =ROUND(L20*$C$9,0) -> 0
B21: (Leavning GST) Net Purchase | C21: =ROUND(C19,0) -> 2574356 | D21: =ROUND(D19,0) -> 2574356 | E21: =ROUND(E19,0) -> 9061733 | F21: =ROUND(F19,0) -> 9061733 | G21: =ROUND(G19,0) -> 2574356 | H21: =ROUND(H19,0) -> 2574356 | I21: =ROUND(I19,0) -> 9061733 | J21: =ROUND(J19,0) -> 9061733 | ... N21: =ROUND(N19,0) -> 0
B23: Shipping & Clearing Expenses India | C23: =C13 -> 200000 | D23: =C13 -> 200000 | E23: =C23*$C$9 -> 704000 | F23: =D23*$C$9 -> 704000 | G23: =C13 -> 200000 | H23: =C13 -> 200000 | I23: =ROUND(SUMIF(ProductList!$C$5:$C$493,G$16,ProductList!$AE$5:$AE$493),0) -> 703998 | J23: =ROUND(SUMIF(ProductList!$C$5:$C$493,G$16,ProductList!$AE$5:$AE$493),0) -> 703998 | M23: =ROUND(SUMIF(ProductList!$C$5:$C$493,K$16,ProductList!$AE$5:$AE$493),0) -> 0
B24: CIF Value (100%) | C24: =C23+C21 -> 2774356 | D24: =D23+D21 -> 2774356 | E24: =E23+E21 -> 9765733 | F24: =F23+F21 -> 9765733 | G24: =G23+G21 -> 2774356 | H24: =H23+H21 -> 2774356 | I24: =I23+I21 -> 9765731 | J24: =J23+J21 -> 9765731 | ... N24: =N23+N21 -> 0
B25: INVOICE VALUE in USD | C25: =SUMIF(ProductList!$C$5:$C$493,G16,ProductList!$BB$5:$BB$493) -> 24771.61
B27: SriLanka Duty | C27: =SUM(G27+K27) -> 1715116 | D27: =SUM(H27+L27) -> 1676136 | E27: =SUM(I27+M27) -> 6037207 | F27: =SUM(J27+N27) -> 5900000 | G27: =ROUND(SUMIF(ProductList!$C$5:$C$493,G16,ProductList!$AP$5:$AP$493),0) -> 1715116 | H27: =ROUND(J27/$C$9,0) -> 1676136 | I27: =ROUND(SUMIF(ProductList!$C$5:$C$493,G16,ProductList!$AG$5:$AG$493),0) -> 6037207 | J27: 5900000 | K27: =ROUND(SUMIF(ProductList!$C$5:$C$493,K16,ProductList!$AP$5:$AP$493),0) -> 0 | L27: =ROUND(N27/$C$9,0) -> 0 | M27: =ROUND(SUMIF(ProductList!$C$5:$C$493,K16,ProductList!$AG$5:$AG$493),0) -> 0 | N27: 0
B28: Clearing Expenses | C28: =ROUND($C$14/$C$9,0) -> 568182 | D28: =SUM(H28+L28) -> 568182 | E28: =ROUND(C28*$C$9,0) -> 2000001 | F28: =J28+N28 -> 2000000 | G28: =ROUND(SUMIF(ProductList!$C$5:$C$493,G16,ProductList!$AR$5:$AR$493),0) -> 568181 | H28: =ROUND(J28/$C$9,0) -> 568182 | I28: =ROUND(SUMIF(ProductList!$C$5:$C$493,G16,ProductList!$AI$5:$AI$493),0) -> 1999998 | J28: 2000000 | L28: =ROUND(N28/$C$9,0) -> 0
B29: Expenses Colombo (Duty + clearnce) | C29: =SUM(C27:C28) -> 2283298 | D29: =SUM(H29+L29) -> 2244318 | E29: =SUM(I29+M29) -> 8037205 | F29: =SUM(J29+N29) -> 7900000 | G29: =SUM(G27:G28) -> 2283297 | H29: =ROUND(J29/$C$9,0) -> 2244318 | I29: =SUM(I27:I28) -> 8037205 | J29: =SUM(J27:J28) -> 7900000 | K29: =SUM(K27:K28) -> 0 | L29: =ROUND(N29/$C$9,0) -> 0 | M29: =SUM(M27:M28) -> 0 | N29: =SUM(N27:N28) -> 0
B30: Expenses Total (India + Colombo) | C30: =C29+C23 -> 2483298 | D30: =SUM(H30+L30) -> 2444318 | E30: =E23+E28 -> 2704001 | F30: =SUM(J30+N30) -> 8603998 | G30: =G29+G23 -> 2483297 | H30: =ROUND(J30/$C$9,0) -> 2444318 | I30: =I29+I23 -> 8741203 | J30: =J29+J23 -> 8603998 | K30: =K29+K23 -> 0 | L30: =ROUND(N30/$C$9,0) -> 0 | M30: =M29+M23 -> 0 | N30: =N29+N23 -> 0
B32: TOTAL INVESTMENT (Net Purchase + ExpensesTotal) | C32: =C21+C30 -> 5057654 | D32: =D21+D30 -> 5018674 | E32: =E21+E30 -> 11765734 | F32: =F21+F30 -> 17665731 | G32: =G21+G30 -> 5057653 | H32: =H21+H30 -> 5018674 | I32: =I21+I30 -> 17802936 | J32: =J21+J30 -> 17665731 | ... N32: =N21+N30 -> 0
B33: SALES | C33: =SUM(G33+K33) -> 6113256 | D33: =SUM(H33+L33) -> 6113256 | E33: =SUM(I33+M33) -> 21518660 | F33: =SUM(J33+N33) -> 21518660 | G33: =ROUND(I33/$C$9,0) -> 6113256 | H33: =ROUND(J33/$C$9,0) -> 6113256 | I33: =ROUND(SUM(INDIRECT("'P_"&G16&"'!$l$5:$l$494")),0) -> 21518660 | J33: =ROUND(SUM(INDIRECT("'P_"&G$16&"'!$l$5:$l$494")),0) -> 21518660 | K33: =ROUND(M33/$C$9,0) -> 0 | L33: =ROUND(N33/$C$9,0) -> 0 | M33: =ROUND(SUM(INDIRECT("'P_"&K16&"'!$l$5:$l$494")),0) -> 0 | N33: =ROUND(SUM(INDIRECT("'P_"&K$16&"'!$s$5:$s$494")),0) -> 0
B35: Balance | C35: =SUM(G35+K35) -> 1055603 | D35: =SUM(H35+L35) -> 1094582 | E35: =SUM(I35+M35) -> 3715724 | F35: =SUM(J35+N35) -> 3852929 | G35: =G33-G32 -> 1055603 | H35: =H33-H32 -> 1094582 | I35: =I33-I32 -> 3715724 | J35: =J33-J32 -> 3852929 | K35: =K33-K32 -> 0 | L35: =L33-L32 -> 0 | M35: =M33-M32 -> 0 | N35: =N33-N32 -> 0
B36: GST Claim | C36: =C20 -> 128715 | D36: =D20 -> 128715 | E36: =E20 -> 453077 | F36: =F20 -> 453077 | G36: =G20 -> 128715 | H36: =H20 -> 128715 | I36: =I20 -> 453077 | J36: =J20 -> 453077 | ... N36: =N20 -> 0
B37: Gross Profit | C37: =C36+C35 -> 1184318 | D37: =D36+D35 -> 1223297 | E37: =E36+E35 -> 4168801 | F37: =F36+F35 -> 4306006 | G37: =G36+G35 -> 1184318 | H37: =H36+H35 -> 1223297 | I37: =I36+I35 -> 4168801 | J37: =J36+J35 -> 4306006 | ... N37: =N36+N35 -> 0
B39: TT Loss | C39: =SUM(G39+K39) -> 135223 | D39: =SUM(H39+L39) -> 9083 | E39: =SUM(I39+M39) -> 475985 | F39: =SUM(J39+N39) -> 31972 | G39: =ROUND(SUMIF(ProductList!$C$4:$C$493,G16,ProductList!$AQ$4:$AQ$493),0) -> 135223 | H39: =ROUND(J39/$C$9,0) -> 9083 | I39: =ROUND(SUMIF(ProductList!$C$4:$C$493,G16,ProductList!$AH$4:$AH$493),0) -> 475985 | J39: 31972 | K39: =ROUND(SUMIF(ProductList!$C$5:$C$493,K16,ProductList!$AQ$5:$AQ$493),0) -> 0 | M39: =ROUND(SUMIF(ProductList!$C$5:$C$493,K16,ProductList!$AH$5:$AH$493),0) -> 0
B40: Material Loss | C40: =G40+K40 -> 0 | D40: =H40+L40 -> 8884 | E40: =I40+M40 -> 0 | F40: =J40+N40 -> 31270 | G40: 0 | H40: =ROUND(J40/$C$9,0) -> 8884 | I40: 0 | J40: 31270 | K40: 0 | L40: =ROUND(N40/$C$9,0) -> 0 | M40: 0 | N40: =ROUND(SUM(INDIRECT("'P_"&K16&"'!$R$5:$R$494")),0) -> 0
B41: Discounts | C41: 0 | D41: =H41+L41 -> 0 | E41: 0 | F41: =J41+N41 -> 0 | G41: 0 | H41: =ROUND(J41/$C$9,0) -> 0 | I41: 0 | J41: =ROUND(SUM(INDIRECT("'P_"&G$16&"'!$n$5:$n$494")),0) -> 0 | K41: 0 | L41: 0 | M41: 0 | N41: 0
B42: TOTAL LOSSES | C42: =SUM(C39:C41) -> 135223 | D42: =SUM(D39:D41) -> 17967 | E42: =SUM(E39:E41) -> 475985 | F42: =SUM(F39:F41) -> 63242 | G42: =SUM(G39:G41) -> 135223 | H42: =SUM(H39:H41) -> 17967 | I42: =SUM(I39:I41) -> 475985 | J42: =SUM(J39:J41) -> 63242 | ... N42: =SUM(N39:N41) -> 0
B43: Net Profit | C43: =C35-C42 -> 920380 | D43: =D35-D42 -> 1076615 | E43: =E35-E42 -> 3239739 | F43: =F35-F42 -> 3789687 | G43: =G35-G42 -> 920380 | H43: =H35-H42 -> 1076615 | I43: =I35-I42 -> 3239739 | J43: =J35-J42 -> 3789687 | ... N43: =N35-N42 -> 0
B44: Profit (%) | C44: PREDICTED | E44: ACTUAL | G44: PREDICTED | I44: ACTUAL | K44: PREDICTED | M44: ACTUAL
C45: =ROUND(C43/C32%,2) -> 18.2 | E45: =ROUND(D43/D32%,2) -> 21.45 | G45: =ROUND(G43/G32%,2) -> 18.2 | I45: =ROUND(H43/H32%,2) -> 21.45 | K45: =ROUND(K43/K32%,2) -> #DIV/0! | M45: =ROUND(L43/L32%,2) -> #DIV/0!
B47: TOTAL AMOUNT (INV + PRO) | C47: =C35+C32-C42+C39 -> 6113257 | D47: =D35+D32-D42+D39 -> 6104372 | E47: =E35+E32-E42+E39 -> 15481458 | F47: =F35+F32-F42+F39 -> 21487390 | G47: =G35+G32-G42+G39 -> 6113256 | H47: =H35+H32-H42+H39 -> 6104372 | I47: =I35+I32-I42+I39 -> 21518660 | J47: =J35+J32-J42+J39 -> 21487390 | ... N47: =N35+N32-N42+N39 -> 0
B48: TOTAL AMOUNT TO SETTLE | C48: =C47 -> 6113257 | D48: =D47 -> 6104372 | E48: =E47 -> 15481458 | F48: =F47 -> 21487390 | G48: =G47 -> 6113256 | H48: =H47 -> 6104372 | I48: =I47 -> 21518660 | J48: =J47 -> 21487390 | ... N48: =N47 -> 0
B49: SETTLED AMOUNT | C49: =SUM(H13:N13) -> 0 | E49: =SUM(H12:N12) -> 0
B50: REMAINING | C50: =D48+C49 -> 6104372 | E50: =F48+E49 -> 21487390

Sheet InvoiceGen
J2: PKT SIZE (G) | K2: NO. BAG (QTY) | L2: UNIT/BAG | M2: GST | N2: PRICE
B3: 1 | C3: 50-50 BISCUIT 140.6 G | D3: 19053100 | E3: 400 | F3: PCS | G3: 0.22 | H3: 88 | I3: 10 | J3: 140.6 | K3: =I3 -> 10 | L3: =IF(AND(B3<>"",I3=0),E3,IF(F3="KGS",(E3*1000)/(K3*J3),E3/K3)) -> 40
B4: 2 | C4: 50-50 CHEESE DIPPER BISCUIT 150G | D4: 19053100 | E4: 600 | F4: PCS | G4: 0.44 | H4: 264 | I4: 10 | J4: 150 | K4: =I4 -> 10 | L4: =IF(AND(B4<>"",I4=0),E4,IF(F4="KGS",(E4*1000)/(K4*J4),E4/K4)) -> 60
B5: 3 | C5: GOODDAY BUTTER BISCUIT 60G | D5: 19053100 | E5: 450 | F5: PCS | G5: 0.09 | H5: 40.5 | I5: 5 | J5: 60 | K5: =I5 -> 5 | L5: =IF(AND(B5<>"",I5=0),E5,IF(F5="KGS",(E5*1000)/(K5*J5),E5/K5)) -> 90
B6: 4 | C6: GOODDAY CASHEW BISCUIT 82.7G | D6: 19053100 | E6: 1200 | F6: PCS | G6: 0.18 | H6: 216 | I6: 20 | J6: 82.7 | K6: =I6 -> 20 | L6: =IF(AND(B6<>"",I6=0),E6,IF(F6="KGS",(E6*1000)/(K6*J6),E6/K6)) -> 60
B7: 5 | C7: GOODDAY PISTA BADAM BISCUIT 112.7G | D7: 19053100 | E7: 1200 | F7: PCS | G7: 0.22 | H7: 264 | I7: 20 | J7: 112.7 | K7: =I7 -> 20 | L7: =IF(AND(B7<>"",I7=0),E7,IF(F7="KGS",(E7*1000)/(K7*J7),E7/K7)) -> 60
B8: 6 | C8: DARK FANTASY CHOCOFILLS BISCUIT 69G | D8: 19053100 | E8: 2400 | F8: PCS | G8: 0.32 | H8: 768 | I8: 20 | J8: 69 | K8: =I8 -> 20 | L8: =IF(AND(B8<>"",I8=0),E8,IF(F8="KGS",(E8*1000)/(K8*J8),E8/K8)) -> 120
B9: 7 | C9: MALKIST CHEESE BISCUIT 144G | D9: 19053100 | E9: 300 | F9: PCS | G9: 0.36 | H9: 108 | I9: 5 | J9: 144 | K9: =I9 -> 5 | L9: =IF(AND(B9<>"",I9=0),E9,IF(F9="KGS",(E9*1000)/(K9*J9),E9/K9)) -> 60
B10: 8 | C10: MALKIST CHOCOLATE BISCUIT 144G | D10: 19053100 | E10: 300 | F10: PCS | G10: 0.36 | H10: 108 | I10: 5 | J10: 144 | K10: =I10 -> 5 | L10: =IF(AND(B10<>"",I10=0),E10,IF(F10="KGS",(E10*1000)/(K10*J10),E10/K10)) -> 60
B11: 9 | C11: OREO VANILLA BISCUIT 116.9 G | D11: 19053100 | E11: 480 | F11: PCS | G11: 0.28 | H11: 134.4 | I11: 8 | J11: 116.9 | K11: =I11 -> 8 | L11: =IF(AND(B11<>"",I11=0),E11,IF(F11="KGS",(E11*1000)/(K11*J11),E11/K11)) -> 60
B12: 10 | C12: HORLICKS PLAIN BISCUIT 150G | D12: 19053100 | E12: 240 | F12: PCS | G12: 0.18 | H12: 43.2 | I12: 4 | J12: 150 | K12: =I12 -> 4 | L12: =IF(AND(B12<>"",I12=0),E12,IF(F12="KGS",(E12*1000)/(K12*J12),E12/K12)) -> 60
B13: 11 | K13: =I13 -> 0 | L13: =IF(AND(B13<>"",I13=0),E13,IF(F13="KGS",(E13*1000)/(K13*J13),E13/K13)) -> 0
B14: 12 | K14: =I14 -> 0 | L14: =IF(AND(B14<>"",I14=0),E14,IF(F14="KGS",(E14*1000)/(K14*J14),E14/K14)) -> 0
B15: 13 | K15: =I15 -> 0 | L15: =IF(AND(B15<>"",I15=0),E15,IF(F15="KGS",(E15*1000)/(K15*J15),E15/K15)) -> 0
B16: 14 | K16: =I16 -> 0 | L16: =IF(AND(B16<>"",I16=0),E16,IF(F16="KGS",(E16*1000)/(K16*J16),E16/K16)) -> 0
B17: 15 | K17: =I17 -> 0 | L17: =IF(AND(B17<>"",I17=0),E17,IF(F17="KGS",(E17*1000)/(K17*J17),E17/K17)) -> 0
B18: 16 | K18: =I18 -> 0 | L18: =IF(AND(B18<>"",I18=0),E18,IF(F18="KGS",(E18*1000)/(K18*J18),E18/K18)) -> 0
B19: 17 | K19: =I19 -> 0 | L19: =IF(AND(B19<>"",I19=0),E19,IF(F19="KGS",(E19*1000)/(K19*J19),E19/K19)) -> 0
B20: 18 | K20: =I20 -> 0 | L20: =IF(AND(B20<>"",I20=0),E20,IF(F20="KGS",(E20*1000)/(K20*J20),E20/K20)) -> 0
B21: 19 | K21: =I21 -> 0 | L21: =IF(AND(B21<>"",I21=0),E21,IF(F21="KGS",(E21*1000)/(K21*J21),E21/K21)) -> 0
B22: 20 | K22: =I22 -> 0 | L22: =IF(AND(B22<>"",I22=0),E22,IF(F22="KGS",(E22*1000)/(K22*J22),E22/K22)) -> 0
B23: 21 | K23: =I23 -> 0 | L23: =IF(AND(B23<>"",I23=0),E23,IF(F23="KGS",(E23*1000)/(K23*J23),E23/K23)) -> 0
B24: 22 | K24: =I24 -> 0 | L24: =IF(AND(B24<>"",I24=0),E24,IF(F24="KGS",(E24*1000)/(K24*J24),E24/K24)) -> 0
... B134: 132 | K134: =I134 -> 0 | L134: =IF(AND(B134<>"",I134=0),E134,IF(F134="KGS",(E134*1000)/(K134*J134),E134/K134)) -> 0

Sheet ProductList
B1: PRODUCT LIST
AG2: LKR | AP2: INR | AY2: INVOICE DETAILS
B3: S.No | C3: CUSTOMER | D3: GROUP | E3: B1G1 | F3: MATERIAL CODE | G3: S/L | H3: REJECTED | I3: CATEGORY | J3: PRODUCT NAME | K3: MRP | L3: PKT SIZE (G) | M3: NO. BAG (QTY) | N3: UNIT/BAG | O3: GST | P3: PRICE | Q3: CURRENCY | R3: PRICE DETAILS | S3: BAG SIZE (KG) | T3: GROSS WEIGHT (KG) | U3: RATE PER PKG (INR) | V3: TOTAL UNIT (KG) | W3: TOTAL GROSS WEIGHT (KG) | X3: NET PRICE | Y3: TOTAL UNIT | Z3: DUTY/KG (LKR) | AA3: GROSS (INR) | AB3: GST AMOUNT (INR) | AC3: NET PRICE (LKR) | AD3: AMOUNT IN (DLR) | AE3: FRIGHT (LKR) | AF3: CIF AMT (LKR) | AG3: DUTY (LKR) | AH3: BUNKER ADJ (LKR) | AI3: MISC (LKR) | AJ3: EXPENSES (LKR) | AK3: EXPENSES/PKT (LKR) | AL3: NET PRICE/PKT (LKR) | AM3: TOTAL PRICE/PKT (LKR) | AN3: NET BUY (LKR) | AO3: SUG.PRICE/PKT (LKR) | AP3: DUTY (INR) | AQ3: BUNKER ADJ (INR) | AR3: MISC (INR) | AS3: EXPENSES (INR) | AT3: EXPENSES/PKT (INR) | AU3: NET PRICE/PKT (INR) | AV3: TOTAL PRICE/PKT (INR) | AW3: NET BUY (INR) | AX3: SUG.PRICE/PKT (INR) | AY3: CIF AMOUNT(LKR) | AZ3: CIF AMOUNT(USD) | BA3: INVOICE AMT (LKR) | BB3: INVOICE AMT (USD) | BC3: INVOICE AMT/UNIT (USD) | BD3: INVOICE AMT/KG (USD) | BE3: INDIAN INVOICE AMT (TOT) | BF3: INDIAN INVOICE AMT (UNIT) | BG3: INDIAN INVOICE AMT (KG)
H4: NO | I4: =IF(F4<>"",IFERROR(VLOOKUP(F4,DUTY_2025!A:H,2,FALSE),""),"") | S4: =IF(AND(H4<>"YES",N4<>""),N4*L4/1000,"") | T4: =IF(S4<>"",S4*1.1,"") | U4: {=IF(AND(H4<>"YES",P4<>"",R4<>"",Q4<>""), _xlfn.SWITCH(Q4, "INR",_xlfn.SWITCH(R4,"KG",P4*S4,"CTN",P4,"UNIT",P4*N4,"NET",P4/M4,0), "USD",_xlfn.SWITCH(R4,"KG",P4*S4*SI!$C$10,"CTN",P4*SI!$C$10,"UNIT",P4*N4*SI!$C$10,"NET",P4*SI!$C$10/M4,0), "LKR",_xlfn.SWITCH(R4,"KG",P4*S4/SI!$C$9,"CTN",P4/SI!$C$9,"UNIT",P4*N4/SI!$C$9,"NET",P4/(M4*SI!$C$9),0), 0), "")} | V4: =IF(AND(S4<>"",M4<>"",N4<>""),S4*M4,"") | W4: =IF(V4<>"",V4*1.1,"") | X4: =IF(AND(U4<>"",M4<>""),U4*M4,"") | Y4: =IF(AND(H4<>"YES",M4<>"",N4<>""),IF(E4=1,(N4*M4)/2,N4*M4),"") | Z4: =IF(AND(H4<>"yes",F4<>""),IFERROR(VLOOKUP(F4,DUTY_2025!A:F,5,FALSE),""),"") | AA4: =IF(B4<>"",IF(AND(X4<>"", O4<>""),IF(ROUND(X4*100/(100+O4),0)=0,"",ROUND(X4*100/(100+O4),0)),""),"") | AB4: =IF(M4<>"",IF(AND(X4<>"",AA4<>""),X4-AA4,""),"") | AC4: =IF(AA4<>"",ROUND(AA4*SI!$C$9,2),"") | AD4: =IF(AC4<>"",ROUND(AC4/(SI!$C$9*SI!$C$10),2),"") | AE4: =IF(B4<>"",SI!$E$23,"") | AF4: =IF(AND(AC4<>"",AE4<>""),ROUND(AC4+AE4,0),"") | AG4: =IF(AND(Z4<>"",S4<>""),Z4*S4,"") | AH4: =IF(AD4<>"",ROUND(AD4*10*SI!$C$9/2,2),"") | AI4: =IF(AND(Y4<>"",S4<>""), ROUND((SI!$E$30)*(X4/SUM($X$5:$X$493)),2),"") | AJ4: =IF(AND(AG4<>"",AI4<>"",AH4<>""),AG4+AI4+AH4,"") | AK4: =IF(AND(AJ4<>"",Y4<>""),ROUND(AJ4/Y4,2),"") | AL4: =IF(AND(AC4<>"",Y4<>""),ROUND(AF4/Y4,0),"") | AM4: =IF(AND(AK4<>"",AL4<>""),AK4+AL4,"") | AO4: =IF(AND(AM4<>"",P4<>""),ROUND((AM4*((100+SI!$C$11)/100)),2),"") | AP4: =IF(AG4<>"",ROUND(AG4/SI!$C$9,2),"") | AQ4: =IF(AH4<>"",ROUND(AH4/SI!$C$9,2),"") | AR4: =IF(AI4<>"",ROUND(AI4/SI!$C$9,2),"") | AS4: =IF(AND(AP4<>"",AR4<>"",AQ4<>""),AP4+AR4+AQ4,"") | AT4: =IF(AND(AS4<>"",S4<>""),ROUND(AS4/S4,2),"") | AU4: =IF(AL4<>"",ROUND(AL4/SI!$C$9,2),"") | AV4: =IF(AM4<>"",ROUND(AM4/SI!$C$9,2),"") | AX4: =IF(AO4<>"",ROUND(AO4/SI!$C$9,2),"") | AY4: =IF(AND(AC4<>"",AI4<>""),AC4+AI4,"") | AZ4: =IF(AY4<>"",ROUND(AY4/(SI!$C$9*SI!$C$10),2),"") | BA4: =IF(AND(AY4<>"",BH4<>""),ROUND(AY4*BH4/100,2),"") | BB4: =IF(AND(AZ4<>"",BH4<>""),ROUND(AZ4*BH4/100,2),"") | BC4: =IF(AND(BB4<>"",S4<>""),ROUND(BB4/Y4,3),"") | BD4: =IF(AND(BB4<>"",T4<>""),ROUND(BB4/S4,3),"") | BF4: =IF(AND(BE4<>"",AB4<>""),ROUND(BE4/AB4,3),"") | BG4: =IF(AND(BE4<>"",W4<>""),ROUND(BE4/Y4,3),"") | BH4: =IF(F4<>"",VLOOKUP(F4,DUTY_2025!A:O,14,FALSE),"")
A5: =IF(AND(F5<>"",H5<>"YES"),IF(A4<>"",A4,0)+1,A4) -> 1 | B5: =IF(AND(F5<>"",H5<>"YES"),IF(B4<>"",B4,A4)+1,"") -> 1 | C5: 1 | F5: 09042190 | G5: =IF(F5<>"",IFERROR(VLOOKUP(F5,DUTY_2025!A:I,6,FALSE),""),"") -> 0 | H5: NO | I5: =IF(F5<>"",IFERROR(VLOOKUP(F5,DUTY_2025!A:H,2,FALSE),""),"") -> CHILLIES- OTHER | J5: SPECIAL CHILLI POWDER - 200 G | K5: 0 | L5: 200 | M5: 2 | N5: 50 | O5: 5 | P5: 5212 | Q5: INR | R5: NET | S5: =IF(AND(H5<>"YES",N5<>""),N5*L5/1000,"") -> 10 | T5: =IF(S5<>"",S5*1.1,"") -> 11 | U5: {=IF(AND(H5<>"YES",P5<>"",R5<>"",Q5<>""), _xlfn.SWITCH(Q5, "INR",_xlfn.SWITCH(R5,"KG",P5*S5,"CTN",P5,"UNIT",P5*N5,"NET",P5/M5,0), "USD",_xlfn.SWITCH(R5,"KG",P5*S5*SI!$C$10,"CTN",P5*SI!$C$10,"UNIT",P5*N5*SI!$C$10,"NET",P5*SI!$C$10/M5,0), "LKR",_xlfn.SWITCH(R5,"KG",P5*S5/SI!$C$9,"CTN",P5/SI!$C$9,"UNIT",P5*N5/SI!$C$9,"NET",P5/(M5*SI!$C$9),0), 0), "")} -> 2606 | V5: =IF(AND(S5<>"",M5<>"",N5<>""),S5*M5,"") -> 20 | W5: =IF(V5<>"",V5*1.1,"") -> 22 | X5: =IF(AND(U5<>"",M5<>""),U5*M5,"") -> 5212 | Y5: =IF(AND(H5<>"YES",M5<>"",N5<>""),IF(E5=1,(N5*M5)/2,N5*M5),"") -> 100 | Z5: =IF(AND(H5<>"yes",F5<>""),IFERROR(VLOOKUP(F5,DUTY_2025!A:F,5,FALSE),""),"") -> 705 | AA5: =IF(B5<>"",IF(AND(X5<>"", O5<>""),IF(ROUND(X5*100/(100+O5),0)=0,"",ROUND(X5*100/(100+O5),0)),""),"") -> 4964 | AB5: =IF(M5<>"",IF(AND(X5<>"",AA5<>""),X5-AA5,""),"") -> 248 | AC5: =IF(AA5<>"",ROUND(AA5*SI!$C$9,0),"") -> 17473 | AD5: =IF(AC5<>"",ROUND(AC5/(SI!$C$9*SI!$C$10),2),"") -> 52.15 | AE5: =IF(AND(X5<>""), ROUND((SI!$E$23)*(X5/SUM($X$5:$X$493)),0),"") -> 1357 | AF5: =IF(AND(AC5<>"",AE5<>""),ROUND(AC5+AE5,0),"") -> 18830 | AG5: =IF(AND(Z5<>"",V5<>""),Z5*V5,"") -> 14100 | AH5: =IF(AD5<>"",ROUND(AD5*10*SI!$C$9/2,0),"") -> 918 | AI5: =IF(AND(X5<>""), ROUND((SI!$E$28)*(X5/SUM($X$5:$X$493)),0),"") -> 3856 | AJ5: =IF(AND(AG5<>"",AI5<>"",AH5<>""),AG5+AI5+AH5,"") -> 18874 | AK5: =IF(AND(AJ5<>"",Y5<>""),ROUND(AJ5/Y5,0),"") -> 189 | AL5: =IF(AND(AC5<>"",Y5<>""),ROUND(AF5/Y5,0),"") -> 188 | AM5: =IF(AND(AK5<>"",AL5<>""),AK5+AL5,"") -> 377 | AN5: =IF(AND(AF5<>"",AG5<>"",AH5<>"",AI5<>""),AF5+AG5+AH5+AI5,"") -> 37704 | AO5: =IF(AND(AM5<>"",P5<>""),ROUND((AM5*((100+SI!$C$11)/100)),0),"") -> 434 | AP5: =IF(AG5<>"",ROUND(AG5/SI!$C$9,2),"") -> 4005.68 | AQ5: =IF(AH5<>"",ROUND(AH5/SI!$C$9,2),"") -> 260.8 | AR5: =IF(AI5<>"",ROUND(AI5/SI!$C$9,2),"") -> 1095.45 | AS5: =IF(AND(AP5<>"",AR5<>"",AQ5<>""),AP5+AR5+AQ5,"") -> 5361.93 | AT5: =IF(AND(AS5<>"",Y5<>""),ROUND(AS5/Y5,2),"") -> 53.62 | AU5: =IF(AL5<>"",ROUND(AL5/SI!$C$9,2),"") -> 53.41 | AV5: =IF(AM5<>"",ROUND(AM5/SI!$C$9,2),"") -> 107.1 | AW5: =IF(AN5<>"",ROUND(AN5/SI!$C$9,2),"") -> 10711.36 | AX5: =IF(AO5<>"",ROUND(AO5/SI!$C$9,2),"") -> 123.3 | AY5: =IF(AF5<>"",AF5,"") -> 18830 | AZ5: =IF(AY5<>"",ROUND(AY5/(SI!$C$9*SI!$C$10),2),"") -> 56.2 | BA5: =IF(AND(AY5<>"",BH5<>""),ROUND(AY5*BH5/100,2),"") -> 15064 | BB5: =IF(AND(AZ5<>"",BH5<>""),ROUND(AZ5*BH5/100,2),"") -> 44.96 | BC5: =IF(AND(BB5<>"",Y5<>""),ROUND(BB5/Y5,3),"") -> 0.45 | BD5: =IF(AND(BB5<>"",T5<>""),ROUND(BB5/V5,3),"") -> 2.248 | BE5: =IF(AND(X5<>""),ROUND(X5/SI!$C$10,2),"") -> 54.75 | BF5: =IF(AND(BE5<>"",Y5<>""),ROUND(BE5/Y5,3),"") -> 0.548 | BG5: =IF(AND(BE5<>"",V5<>""),ROUND(BE5/V5,3),"") -> 2.738 | BH5: =IF(F5<>"",VLOOKUP(F5,DUTY_2025!A:O,15,FALSE),"") -> 80
A6: =IF(AND(F6<>"",H6<>"YES"),IF(A5<>"",A5,0)+1,A5) -> 2 | B6: =IF(AND(F6<>"",H6<>"YES"),IF(B5<>"",B5,A5)+1,"") -> 2 | C6: 1 | F6: 09042190 | G6: =IF(F6<>"",IFERROR(VLOOKUP(F6,DUTY_2025!A:I,6,FALSE),""),"") -> 0 | H6: NO | I6: =IF(F6<>"",IFERROR(VLOOKUP(F6,DUTY_2025!A:H,2,FALSE),""),"") -> CHILLIES- OTHER | J6: SPECIAL CHILLI POWDER - 500 G | K6: 0 | L6: 500 | M6: 30 | N6: 40 | O6: 5 | P6: 156330 | Q6: INR | R6: NET | S6: =IF(AND(H6<>"YES",N6<>""),N6*L6/1000,"") -> 20 | T6: =IF(S6<>"",S6*1.1,"") -> 22 | U6: {=IF(AND(H6<>"YES",P6<>"",R6<>"",Q6<>""), _xlfn.SWITCH(Q6, "INR",_xlfn.SWITCH(R6,"KG",P6*S6,"CTN",P6,"UNIT",P6*N6,"NET",P6/M6,0), "USD",_xlfn.SWITCH(R6,"KG",P6*S6*SI!$C$10,"CTN",P6*SI!$C$10,"UNIT",P6*N6*SI!$C$10,"NET",P6*SI!$C$10/M6,0), "LKR",_xlfn.SWITCH(R6,"KG",P6*S6/SI!$C$9,"CTN",P6/SI!$C$9,"UNIT",P6*N6/SI!$C$9,"NET",P6/(M6*SI!$C$9),0), 0), "")} -> 5211 | V6: =IF(AND(S6<>"",M6<>"",N6<>""),S6*M6,"") -> 600 | W6: =IF(V6<>"",V6*1.1,"") -> 660 | X6: =IF(AND(U6<>"",M6<>""),U6*M6,"") -> 156330 | Y6: =IF(AND(H6<>"YES",M6<>"",N6<>""),IF(E6=1,(N6*M6)/2,N6*M6),"") -> 1200 | Z6: =IF(AND(H6<>"yes",F6<>""),IFERROR(VLOOKUP(F6,DUTY_2025!A:F,5,FALSE),""),"") -> 705 | AA6: =IF(B6<>"",IF(AND(X6<>"", O6<>""),IF(ROUND(X6*100/(100+O6),0)=0,"",ROUND(X6*100/(100+O6),0)),""),"") -> 148886 | AB6: =IF(M6<>"",IF(AND(X6<>"",AA6<>""),X6-AA6,""),"") -> 7444 | AC6: =IF(AA6<>"",ROUND(AA6*SI!$C$9,0),"") -> 524079 | AD6: =IF(AC6<>"",ROUND(AC6/(SI!$C$9*SI!$C$10),2),"") -> 1564.09 | AE6: =IF(AND(X6<>""), ROUND((SI!$E$23)*(X6/SUM($X$5:$X$493)),0),"") -> 40715 | AF6: =IF(AND(AC6<>"",AE6<>""),ROUND(AC6+AE6,0),"") -> 564794 | AG6: =IF(AND(Z6<>"",V6<>""),Z6*V6,"") -> 423000 | AH6: =IF(AD6<>"",ROUND(AD6*10*SI!$C$9/2,0),"") -> 27528 | AI6: =IF(AND(X6<>""), ROUND((SI!$E$28)*(X6/SUM($X$5:$X$493)),0),"") -> 115668 | AJ6: =IF(AND(AG6<>"",AI6<>"",AH6<>""),AG6+AI6+AH6,"") -> 566196 | AK6: =IF(AND(AJ6<>"",Y6<>""),ROUND(AJ6/Y6,0),"") -> 472 | AL6: =IF(AND(AC6<>"",Y6<>""),ROUND(AF6/Y6,0),"") -> 471 | AM6: =IF(AND(AK6<>"",AL6<>""),AK6+AL6,"") -> 943 | AN6: =IF(AND(AF6<>"",AG6<>"",AH6<>"",AI6<>""),AF6+AG6+AH6+AI6,"") -> 1130990 | AO6: =IF(AND(AM6<>"",P6<>""),ROUND((AM6*((100+SI!$C$11)/100)),0),"") -> 1084 | AP6: =IF(AG6<>"",ROUND(AG6/SI!$C$9,2),"") -> 120170.45 | AQ6: =IF(AH6<>"",ROUND(AH6/SI!$C$9,2),"") -> 7820.45 | AR6: =IF(AI6<>"",ROUND(AI6/SI!$C$9,2),"") -> 32860.23 | AS6: =IF(AND(AP6<>"",AR6<>"",AQ6<>""),AP6+AR6+AQ6,"") -> 160851.13 | AT6: =IF(AND(AS6<>"",Y6<>""),ROUND(AS6/Y6,2),"") -> 134.04 | AU6: =IF(AL6<>"",ROUND(AL6/SI!$C$9,2),"") -> 133.81 | AV6: =IF(AM6<>"",ROUND(AM6/SI!$C$9,2),"") -> 267.9 | AW6: =IF(AN6<>"",ROUND(AN6/SI!$C$9,2),"") -> 321303.98 | AX6: =IF(AO6<>"",ROUND(AO6/SI!$C$9,2),"") -> 307.95 | AY6: =IF(AF6<>"",AF6,"") -> 564794 | AZ6: =IF(AY6<>"",ROUND(AY6/(SI!$C$9*SI!$C$10),2),"") -> 1685.61 | BA6: =IF(AND(AY6<>"",BH6<>""),ROUND(AY6*BH6/100,2),"") -> 451835.2 | BB6: =IF(AND(AZ6<>"",BH6<>""),ROUND(AZ6*BH6/100,2),"") -> 1348.49 | BC6: =IF(AND(BB6<>"",Y6<>""),ROUND(BB6/Y6,3),"") -> 1.124 | BD6: =IF(AND(BB6<>"",T6<>""),ROUND(BB6/V6,3),"") -> 2.247 | BE6: =IF(AND(X6<>""),ROUND(X6/SI!$C$10,2),"") -> 1642.29 | BF6: =IF(AND(BE6<>"",Y6<>""),ROUND(BE6/Y6,3),"") -> 1.369 | BG6: =IF(AND(BE6<>"",V6<>""),ROUND(BE6/V6,3),"") -> 2.737 | BH6: =IF(F6<>"",VLOOKUP(F6,DUTY_2025!A:O,15,FALSE),"") -> 80
A7: =IF(AND(F7<>"",H7<>"YES"),IF(A6<>"",A6,0)+1,A6) -> 3 | B7: =IF(AND(F7<>"",H7<>"YES"),IF(B6<>"",B6,A6)+1,"") -> 3 | C7: 1 | F7: 11029020 | G7: =IF(F7<>"",IFERROR(VLOOKUP(F7,DUTY_2025!A:I,6,FALSE),""),"") -> L | H7: NO | I7: =IF(F7<>"",IFERROR(VLOOKUP(F7,DUTY_2025!A:H,2,FALSE),""),"") -> KURAKKAN FLOUR | J7: RAGI FLOUR 500 G | K7: 0 | L7: 500 | M7: 10 | N7: 20 | O7: 5 | P7: 6290 | Q7: INR | R7: NET | S7: =IF(AND(H7<>"YES",N7<>""),N7*L7/1000,"") -> 10 | T7: =IF(S7<>"",S7*1.1,"") -> 11 | U7: {=IF(AND(H7<>"YES",P7<>"",R7<>"",Q7<>""), _xlfn.SWITCH(Q7, "INR",_xlfn.SWITCH(R7,"KG",P7*S7,"CTN",P7,"UNIT",P7*N7,"NET",P7/M7,0), "USD",_xlfn.SWITCH(R7,"KG",P7*S7*SI!$C$10,"CTN",P7*SI!$C$10,"UNIT",P7*N7*SI!$C$10,"NET",P7*SI!$C$10/M7,0), "LKR",_xlfn.SWITCH(R7,"KG",P7*S7/SI!$C$9,"CTN",P7/SI!$C$9,"UNIT",P7*N7/SI!$C$9,"NET",P7/(M7*SI!$C$9),0), 0), "")} -> 629 | V7: =IF(AND(S7<>"",M7<>"",N7<>""),S7*M7,"") -> 100 | W7: =IF(V7<>"",V7*1.1,"") -> 110 | X7: =IF(AND(U7<>"",M7<>""),U7*M7,"") -> 6290 | Y7: =IF(AND(H7<>"YES",M7<>"",N7<>""),IF(E7=1,(N7*M7)/2,N7*M7),"") -> 200 | Z7: =IF(AND(H7<>"yes",F7<>""),IFERROR(VLOOKUP(F7,DUTY_2025!A:F,5,FALSE),""),"") -> 107 | AA7: =IF(B7<>"",IF(AND(X7<>"", O7<>""),IF(ROUND(X7*100/(100+O7),0)=0,"",ROUND(X7*100/(100+O7),0)),""),"") -> 5990 | AB7: =IF(M7<>"",IF(AND(X7<>"",AA7<>""),X7-AA7,""),"") -> 300 | AC7: =IF(AA7<>"",ROUND(AA7*SI!$C$9,0),"") -> 21085 | AD7: =IF(AC7<>"",ROUND(AC7/(SI!$C$9*SI!$C$10),2),"") -> 62.93 | AE7: =IF(AND(X7<>""), ROUND((SI!$E$23)*(X7/SUM($X$5:$X$493)),0),"") -> 1638 | AF7: =IF(AND(AC7<>"",AE7<>""),ROUND(AC7+AE7,0),"") -> 22723 | AG7: =IF(AND(Z7<>"",V7<>""),Z7*V7,"") -> 10700 | AH7: =IF(AD7<>"",ROUND(AD7*10*SI!$C$9/2,0),"") -> 1108 | AI7: =IF(AND(X7<>""), ROUND((SI!$E$28)*(X7/SUM($X$5:$X$493)),0),"") -> 4654 | AJ7: =IF(AND(AG7<>"",AI7<>"",AH7<>""),AG7+AI7+AH7,"") -> 16462 | AK7: =IF(AND(AJ7<>"",Y7<>""),ROUND(AJ7/Y7,0),"") -> 82 | AL7: =IF(AND(AC7<>"",Y7<>""),ROUND(AF7/Y7,0),"") -> 114 | AM7: =IF(AND(AK7<>"",AL7<>""),AK7+AL7,"") -> 196 | AN7: =IF(AND(AF7<>"",AG7<>"",AH7<>"",AI7<>""),AF7+AG7+AH7+AI7,"") -> 39185 | AO7: =IF(AND(AM7<>"",P7<>""),ROUND((AM7*((100+SI!$C$11)/100)),0),"") -> 225 | AP7: =IF(AG7<>"",ROUND(AG7/SI!$C$9,2),"") -> 3039.77 | AQ7: =IF(AH7<>"",ROUND(AH7/SI!$C$9,2),"") -> 314.77 | AR7: =IF(AI7<>"",ROUND(AI7/SI!$C$9,2),"") -> 1322.16 | AS7: =IF(AND(AP7<>"",AR7<>"",AQ7<>""),AP7+AR7+AQ7,"") -> 4676.7 | AT7: =IF(AND(AS7<>"",Y7<>""),ROUND(AS7/Y7,2),"") -> 23.38 | AU7: =IF(AL7<>"",ROUND(AL7/SI!$C$9,2),"") -> 32.39 | AV7: =IF(AM7<>"",ROUND(AM7/SI!$C$9,2),"") -> 55.68 | AW7: =IF(AN7<>"",ROUND(AN7/SI!$C$9,2),"") -> 11132.1 | AX7: =IF(AO7<>"",ROUND(AO7/SI!$C$9,2),"") -> 63.92 | AY7: =IF(AF7<>"",AF7,"") -> 22723 | AZ7: =IF(AY7<>"",ROUND(AY7/(SI!$C$9*SI!$C$10),2),"") -> 67.82 | BA7: =IF(AND(AY7<>"",BH7<>""),ROUND(AY7*BH7/100,2),"") -> 18178.4 | BB7: =IF(AND(AZ7<>"",BH7<>""),ROUND(AZ7*BH7/100,2),"") -> 54.26 | BC7: =IF(AND(BB7<>"",Y7<>""),ROUND(BB7/Y7,3),"") -> 0.271 | BD7: =IF(AND(BB7<>"",T7<>""),ROUND(BB7/V7,3),"") -> 0.543 | BE7: =IF(AND(X7<>""),ROUND(X7/SI!$C$10,2),"") -> 66.08 | BF7: =IF(AND(BE7<>"",Y7<>""),ROUND(BE7/Y7,3),"") -> 0.33 | BG7: =IF(AND(BE7<>"",V7<>""),ROUND(BE7/V7,3),"") -> 0.661 | BH7: =IF(F7<>"",VLOOKUP(F7,DUTY_2025!A:O,15,FALSE),"") -> 80
A8: =IF(AND(F8<>"",H8<>"YES"),IF(A7<>"",A7,0)+1,A7) -> 4 | B8: =IF(AND(F8<>"",H8<>"YES"),IF(B7<>"",B7,A7)+1,"") -> 4 | C8: 1 | F8: 09092200 | G8: =IF(F8<>"",IFERROR(VLOOKUP(F8,DUTY_2025!A:I,6,FALSE),""),"") -> S | H8: NO | I8: =IF(F8<>"",IFERROR(VLOOKUP(F8,DUTY_2025!A:H,2,FALSE),""),"") -> DHANIYA POWDER | J8: DANIYA POWDER - 500 G | K8: 0 | L8: 500 | M8: 10 | N8: 40 | O8: 5 | P8: 43130 | Q8: INR | R8: NET | S8: =IF(AND(H8<>"YES",N8<>""),N8*L8/1000,"") -> 20 | T8: =IF(S8<>"",S8*1.1,"") -> 22 | U8: {=IF(AND(H8<>"YES",P8<>"",R8<>"",Q8<>""), _xlfn.SWITCH(Q8, "INR",_xlfn.SWITCH(R8,"KG",P8*S8,"CTN",P8,"UNIT",P8*N8,"NET",P8/M8,0), "USD",_xlfn.SWITCH(R8,"KG",P8*S8*SI!$C$10,"CTN",P8*SI!$C$10,"UNIT",P8*N8*SI!$C$10,"NET",P8*SI!$C$10/M8,0), "LKR",_xlfn.SWITCH(R8,"KG",P8*S8/SI!$C$9,"CTN",P8/SI!$C$9,"UNIT",P8*N8/SI!$C$9,"NET",P8/(M8*SI!$C$9),0), 0), "")} -> 4313 | V8: =IF(AND(S8<>"",M8<>"",N8<>""),S8*M8,"") -> 200 | W8: =IF(V8<>"",V8*1.1,"") -> 220 | X8: =IF(AND(U8<>"",M8<>""),U8*M8,"") -> 43130 | Y8: =IF(AND(H8<>"YES",M8<>"",N8<>""),IF(E8=1,(N8*M8)/2,N8*M8),"") -> 400 | Z8: =IF(AND(H8<>"yes",F8<>""),IFERROR(VLOOKUP(F8,DUTY_2025!A:F,5,FALSE),""),"") -> 52 | AA8: =IF(B8<>"",IF(AND(X8<>"", O8<>""),IF(ROUND(X8*100/(100+O8),0)=0,"",ROUND(X8*100/(100+O8),0)),""),"") -> 41076 | AB8: =IF(M8<>"",IF(AND(X8<>"",AA8<>""),X8-AA8,""),"") -> 2054 | AC8: =IF(AA8<>"",ROUND(AA8*SI!$C$9,0),"") -> 144588 | AD8: =IF(AC8<>"",ROUND(AC8/(SI!$C$9*SI!$C$10),2),"") -> 431.52 | AE8: =IF(AND(X8<>""), ROUND((SI!$E$23)*(X8/SUM($X$5:$X$493)),0),"") -> 11233 | AF8: =IF(AND(AC8<>"",AE8<>""),ROUND(AC8+AE8,0),"") -> 155821 | AG8: =IF(AND(Z8<>"",V8<>""),Z8*V8,"") -> 10400 | AH8: =IF(AD8<>"",ROUND(AD8*10*SI!$C$9/2,0),"") -> 7595 | AI8: =IF(AND(X8<>""), ROUND((SI!$E$28)*(X8/SUM($X$5:$X$493)),0),"") -> 31912 | AJ8: =IF(AND(AG8<>"",AI8<>"",AH8<>""),AG8+AI8+AH8,"") -> 49907 | AK8: =IF(AND(AJ8<>"",Y8<>""),ROUND(AJ8/Y8,0),"") -> 125 | AL8: =IF(AND(AC8<>"",Y8<>""),ROUND(AF8/Y8,0),"") -> 390 | AM8: =IF(AND(AK8<>"",AL8<>""),AK8+AL8,"") -> 515 | AN8: =IF(AND(AF8<>"",AG8<>"",AH8<>"",AI8<>""),AF8+AG8+AH8+AI8,"") -> 205728 | AO8: =IF(AND(AM8<>"",P8<>""),ROUND((AM8*((100+SI!$C$11)/100)),0),"") -> 592 | AP8: =IF(AG8<>"",ROUND(AG8/SI!$C$9,2),"") -> 2954.55 | AQ8: =IF(AH8<>"",ROUND(AH8/SI!$C$9,2),"") -> 2157.67 | AR8: =IF(AI8<>"",ROUND(AI8/SI!$C$9,2),"") -> 9065.91 | AS8: =IF(AND(AP8<>"",AR8<>"",AQ8<>""),AP8+AR8+AQ8,"") -> 14178.13 | AT8: =IF(AND(AS8<>"",Y8<>""),ROUND(AS8/Y8,2),"") -> 35.45 | AU8: =IF(AL8<>"",ROUND(AL8/SI!$C$9,2),"") -> 110.8 | AV8: =IF(AM8<>"",ROUND(AM8/SI!$C$9,2),"") -> 146.31 | AW8: =IF(AN8<>"",ROUND(AN8/SI!$C$9,2),"") -> 58445.45 | AX8: =IF(AO8<>"",ROUND(AO8/SI!$C$9,2),"") -> 168.18 | AY8: =IF(AF8<>"",AF8,"") -> 155821 | AZ8: =IF(AY8<>"",ROUND(AY8/(SI!$C$9*SI!$C$10),2),"") -> 465.04 | BA8: =IF(AND(AY8<>"",BH8<>""),ROUND(AY8*BH8/100,2),"") -> 155821 | BB8: =IF(AND(AZ8<>"",BH8<>""),ROUND(AZ8*BH8/100,2),"") -> 465.04 | BC8: =IF(AND(BB8<>"",Y8<>""),ROUND(BB8/Y8,3),"") -> 1.163 | BD8: =IF(AND(BB8<>"",T8<>""),ROUND(BB8/V8,3),"") -> 2.325 | BE8: =IF(AND(X8<>""),ROUND(X8/SI!$C$10,2),"") -> 453.09 | BF8: =IF(AND(BE8<>"",Y8<>""),ROUND(BE8/Y8,3),"") -> 1.133 | BG8: =IF(AND(BE8<>"",V8<>""),ROUND(BE8/V8,3),"") -> 2.265 | BH8: =IF(F8<>"",VLOOKUP(F8,DUTY_2025!A:O,15,FALSE),"") -> 100
A9: =IF(AND(F9<>"",H9<>"YES"),IF(A8<>"",A8,0)+1,A8) -> 5 | B9: =IF(AND(F9<>"",H9<>"YES"),IF(B8<>"",B8,A8)+1,"") -> 5 | C9: 1 | F9: 21069099 | G9: =IF(F9<>"",IFERROR(VLOOKUP(F9,DUTY_2025!A:I,6,FALSE),""),"") -> 0 | H9: NO | I9: =IF(F9<>"",IFERROR(VLOOKUP(F9,DUTY_2025!A:H,2,FALSE),""),"") -> HEALTH MIXES | J9: HEALTH MIX 200 G | K9: 0 | L9: 200 | M9: 13 | N9: 40 | O9: 5 | P9: 25980 | Q9: INR | R9: NET | S9: =IF(AND(H9<>"YES",N9<>""),N9*L9/1000,"") -> 8 | T9: =IF(S9<>"",S9*1.1,"") -> 8.8 | U9: {=IF(AND(H9<>"YES",P9<>"",R9<>"",Q9<>""), _xlfn.SWITCH(Q9, "INR",_xlfn.SWITCH(R9,"KG",P9*S9,"CTN",P9,"UNIT",P9*N9,"NET",P9/M9,0), "USD",_xlfn.SWITCH(R9,"KG",P9*S9*SI!$C$10,"CTN",P9*SI!$C$10,"UNIT",P9*N9*SI!$C$10,"NET",P9*SI!$C$10/M9,0), "LKR",_xlfn.SWITCH(R9,"KG",P9*S9/SI!$C$9,"CTN",P9/SI!$C$9,"UNIT",P9*N9/SI!$C$9,"NET",P9/(M9*SI!$C$9),0), 0), "")} -> 1998.4615 | V9: =IF(AND(S9<>"",M9<>"",N9<>""),S9*M9,"") -> 104 | W9: =IF(V9<>"",V9*1.1,"") -> 114.4 | X9: =IF(AND(U9<>"",M9<>""),U9*M9,"") -> 25980 | Y9: =IF(AND(H9<>"YES",M9<>"",N9<>""),IF(E9=1,(N9*M9)/2,N9*M9),"") -> 520 | Z9: =IF(AND(H9<>"yes",F9<>""),IFERROR(VLOOKUP(F9,DUTY_2025!A:F,5,FALSE),""),"") -> 570 | AA9: =IF(B9<>"",IF(AND(X9<>"", O9<>""),IF(ROUND(X9*100/(100+O9),0)=0,"",ROUND(X9*100/(100+O9),0)),""),"") -> 24743 | AB9: =IF(M9<>"",IF(AND(X9<>"",AA9<>""),X9-AA9,""),"") -> 1237 | AC9: =IF(AA9<>"",ROUND(AA9*SI!$C$9,0),"") -> 87095 | AD9: =IF(AC9<>"",ROUND(AC9/(SI!$C$9*SI!$C$10),2),"") -> 259.93 | AE9: =IF(AND(X9<>""), ROUND((SI!$E$23)*(X9/SUM($X$5:$X$493)),0),"") -> 6766 | AF9: =IF(AND(AC9<>"",AE9<>""),ROUND(AC9+AE9,0),"") -> 93861 | AG9: =IF(AND(Z9<>"",V9<>""),Z9*V9,"") -> 59280 | AH9: =IF(AD9<>"",ROUND(AD9*10*SI!$C$9/2,0),"") -> 4575 | AI9: =IF(AND(X9<>""), ROUND((SI!$E$28)*(X9/SUM($X$5:$X$493)),0),"") -> 19223 | AJ9: =IF(AND(AG9<>"",AI9<>"",AH9<>""),AG9+AI9+AH9,"") -> 83078 | AK9: =IF(AND(AJ9<>"",Y9<>""),ROUND(AJ9/Y9,0),"") -> 160 | AL9: =IF(AND(AC9<>"",Y9<>""),ROUND(AF9/Y9,0),"") -> 181 | AM9: =IF(AND(AK9<>"",AL9<>""),AK9+AL9,"") -> 341 | AN9: =IF(AND(AF9<>"",AG9<>"",AH9<>"",AI9<>""),AF9+AG9+AH9+AI9,"") -> 176939 | AO9: =IF(AND(AM9<>"",P9<>""),ROUND((AM9*((100+SI!$C$11)/100)),0),"") -> 392 | AP9: =IF(AG9<>"",ROUND(AG9/SI!$C$9,2),"") -> 16840.91 | AQ9: =IF(AH9<>"",ROUND(AH9/SI!$C$9,2),"") -> 1299.72 | AR9: =IF(AI9<>"",ROUND(AI9/SI!$C$9,2),"") -> 5461.08 | AS9: =IF(AND(AP9<>"",AR9<>"",AQ9<>""),AP9+AR9+AQ9,"") -> 23601.71 | AT9: =IF(AND(AS9<>"",Y9<>""),ROUND(AS9/Y9,2),"") -> 45.39 | AU9: =IF(AL9<>"",ROUND(AL9/SI!$C$9,2),"") -> 51.42 | AV9: =IF(AM9<>"",ROUND(AM9/SI!$C$9,2),"") -> 96.88 | AW9: =IF(AN9<>"",ROUND(AN9/SI!$C$9,2),"") -> 50266.76 | AX9: =IF(AO9<>"",ROUND(AO9/SI!$C$9,2),"") -> 111.36 | AY9: =IF(AF9<>"",AF9,"") -> 93861 | AZ9: =IF(AY9<>"",ROUND(AY9/(SI!$C$9*SI!$C$10),2),"") -> 280.12 | BA9: =IF(AND(AY9<>"",BH9<>""),ROUND(AY9*BH9/100,2),"") -> 75088.8 | BB9: =IF(AND(AZ9<>"",BH9<>""),ROUND(AZ9*BH9/100,2),"") -> 224.1 | BC9: =IF(AND(BB9<>"",Y9<>""),ROUND(BB9/Y9,3),"") -> 0.431 | BD9: =IF(AND(BB9<>"",T9<>""),ROUND(BB9/V9,3),"") -> 2.155 | BE9: =IF(AND(X9<>""),ROUND(X9/SI!$C$10,2),"") -> 272.93 | BF9: =IF(AND(BE9<>"",Y9<>""),ROUND(BE9/Y9,3),"") -> 0.525 | BG9: =IF(AND(BE9<>"",V9<>""),ROUND(BE9/V9,3),"") -> 2.624 | BH9: =IF(F9<>"",VLOOKUP(F9,DUTY_2025!A:O,15,FALSE),"") -> 80
A10: =IF(AND(F10<>"",H10<>"YES"),IF(A9<>"",A9,0)+1,A9) -> 6 | B10: =IF(AND(F10<>"",H10<>"YES"),IF(B9<>"",B9,A9)+1,"") -> 6 | C10: 1 | F10: 13012000 | G10: =IF(F10<>"",IFERROR(VLOOKUP(F10,DUTY_2025!A:I,6,FALSE),""),"") -> 0 | H10: NO | I10: =IF(F10<>"",IFERROR(VLOOKUP(F10,DUTY_2025!A:H,2,FALSE),""),"") -> GUM ARABIC | J10: ASAFOETIDA POWDER 50 G | K10: 0 | L10: 50 | M10: 10 | N10: 120 | O10: 5 | P10: 67530 | Q10: INR | R10: NET | S10: =IF(AND(H10<>"YES",N10<>""),N10*L10/1000,"") -> 6 | T10: =IF(S10<>"",S10*1.1,"") -> 6.6 | U10: {=IF(AND(H10<>"YES",P10<>"",R10<>"",Q10<>""), _xlfn.SWITCH(Q10, "INR",_xlfn.SWITCH(R10,"KG",P10*S10,"CTN",P10,"UNIT",P10*N10,"NET",P10/M10,0), "USD",_xlfn.SWITCH(R10,"KG",P10*S10*SI!$C$10,"CTN",P10*SI!$C$10,"UNIT",P10*N10*SI!$C$10,"NET",P10*SI!$C$10/M10,0), "LKR",_xlfn.SWITCH(R10,"KG",P10*S10/SI!$C$9,"CTN",P10/SI!$C$9,"UNIT",P10*N10/SI!$C$9,"NET",P10/(M10*SI!$C$9),0), 0), "")} -> 6753 | V10: =IF(AND(S10<>"",M10<>"",N10<>""),S10*M10,"") -> 60 | W10: =IF(V10<>"",V10*1.1,"") -> 66 | X10: =IF(AND(U10<>"",M10<>""),U10*M10,"") -> 67530 | Y10: =IF(AND(H10<>"YES",M10<>"",N10<>""),IF(E10=1,(N10*M10)/2,N10*M10),"") -> 1200 | Z10: =IF(AND(H10<>"yes",F10<>""),IFERROR(VLOOKUP(F10,DUTY_2025!A:F,5,FALSE),""),"") -> 1130 | AA10: =IF(B10<>"",IF(AND(X10<>"", O10<>""),IF(ROUND(X10*100/(100+O10),0)=0,"",ROUND(X10*100/(100+O10),0)),""),"") -> 64314 | AB10: =IF(M10<>"",IF(AND(X10<>"",AA10<>""),X10-AA10,""),"") -> 3216 | AC10: =IF(AA10<>"",ROUND(AA10*SI!$C$9,0),"") -> 226385 | AD10: =IF(AC10<>"",ROUND(AC10/(SI!$C$9*SI!$C$10),2),"") -> 675.64 | AE10: =IF(AND(X10<>""), ROUND((SI!$E$23)*(X10/SUM($X$5:$X$493)),0),"") -> 17588 | AF10: =IF(AND(AC10<>"",AE10<>""),ROUND(AC10+AE10,0),"") -> 243973 | AG10: =IF(AND(Z10<>"",V10<>""),Z10*V10,"") -> 67800 | AH10: =IF(AD10<>"",ROUND(AD10*10*SI!$C$9/2,0),"") -> 11891 | AI10: =IF(AND(X10<>""), ROUND((SI!$E$28)*(X10/SUM($X$5:$X$493)),0),"") -> 49965 | AJ10: =IF(AND(AG10<>"",AI10<>"",AH10<>""),AG10+AI10+AH10,"") -> 129656 | AK10: =IF(AND(AJ10<>"",Y10<>""),ROUND(AJ10/Y10,0),"") -> 108 | AL10: =IF(AND(AC10<>"",Y10<>""),ROUND(AF10/Y10,0),"") -> 203 | AM10: =IF(AND(AK10<>"",AL10<>""),AK10+AL10,"") -> 311 | AN10: =IF(AND(AF10<>"",AG10<>"",AH10<>"",AI10<>""),AF10+AG10+AH10+AI10,"") -> 373629 | AO10: =IF(AND(AM10<>"",P10<>""),ROUND((AM10*((100+SI!$C$11)/100)),0),"") -> 358 | AP10: =IF(AG10<>"",ROUND(AG10/SI!$C$9,2),"") -> 19261.36 | AQ10: =IF(AH10<>"",ROUND(AH10/SI!$C$9,2),"") -> 3378.13 | AR10: =IF(AI10<>"",ROUND(AI10/SI!$C$9,2),"") -> 14194.6 | AS10: =IF(AND(AP10<>"",AR10<>"",AQ10<>""),AP10+AR10+AQ10,"") -> 36834.09 | AT10: =IF(AND(AS10<>"",Y10<>""),ROUND(AS10/Y10,2),"") -> 30.7 | AU10: =IF(AL10<>"",ROUND(AL10/SI!$C$9,2),"") -> 57.67 | AV10: =IF(AM10<>"",ROUND(AM10/SI!$C$9,2),"") -> 88.35 | AW10: =IF(AN10<>"",ROUND(AN10/SI!$C$9,2),"") -> 106144.6 | AX10: =IF(AO10<>"",ROUND(AO10/SI!$C$9,2),"") -> 101.7 | AY10: =IF(AF10<>"",AF10,"") -> 243973 | AZ10: =IF(AY10<>"",ROUND(AY10/(SI!$C$9*SI!$C$10),2),"") -> 728.13 | BA10: =IF(AND(AY10<>"",BH10<>""),ROUND(AY10*BH10/100,2),"") -> 195178.4 | BB10: =IF(AND(AZ10<>"",BH10<>""),ROUND(AZ10*BH10/100,2),"") -> 582.5 | BC10: =IF(AND(BB10<>"",Y10<>""),ROUND(BB10/Y10,3),"") -> 0.485 | BD10: =IF(AND(BB10<>"",T10<>""),ROUND(BB10/V10,3),"") -> 9.708 | BE10: =IF(AND(X10<>""),ROUND(X10/SI!$C$10,2),"") -> 709.42 | BF10: =IF(AND(BE10<>"",Y10<>""),ROUND(BE10/Y10,3),"") -> 0.591 | BG10: =IF(AND(BE10<>"",V10<>""),ROUND(BE10/V10,3),"") -> 11.824 | BH10: =IF(F10<>"",VLOOKUP(F10,DUTY_2025!A:O,15,FALSE),"") -> 80
A11: =IF(AND(F11<>"",H11<>"YES"),IF(A10<>"",A10,0)+1,A10) -> 7 | B11: =IF(AND(F11<>"",H11<>"YES"),IF(B10<>"",B10,A10)+1,"") -> 7 | C11: 1 | F11: 21069099 | G11: =IF(F11<>"",IFERROR(VLOOKUP(F11,DUTY_2025!A:I,6,FALSE),""),"") -> 0 | H11: NO | I11: =IF(F11<>"",IFERROR(VLOOKUP(F11,DUTY_2025!A:H,2,FALSE),""),"") -> HEALTH MIXES | J11: ROYAL PAYASAMMIX 175 G | K11: 0 | L11: 175 | M11: 10 | N11: 40 | O11: 5 | P11: 17840 | Q11: INR | R11: NET | S11: =IF(AND(H11<>"YES",N11<>""),N11*L11/1000,"") -> 7 | T11: =IF(S11<>"",S11*1.1,"") -> 7.7 | U11: {=IF(AND(H11<>"YES",P11<>"",R11<>"",Q11<>""), _xlfn.SWITCH(Q11, "INR",_xlfn.SWITCH(R11,"KG",P11*S11,"CTN",P11,"UNIT",P11*N11,"NET",P11/M11,0), "USD",_xlfn.SWITCH(R11,"KG",P11*S11*SI!$C$10,"CTN",P11*SI!$C$10,"UNIT",P11*N11*SI!$C$10,"NET",P11*SI!$C$10/M11,0), "LKR",_xlfn.SWITCH(R11,"KG",P11*S11/SI!$C$9,"CTN",P11/SI!$C$9,"UNIT",P11*N11/SI!$C$9,"NET",P11/(M11*SI!$C$9),0), 0), "")} -> 1784 | V11: =IF(AND(S11<>"",M11<>"",N11<>""),S11*M11,"") -> 70 | W11: =IF(V11<>"",V11*1.1,"") -> 77 | X11: =IF(AND(U11<>"",M11<>""),U11*M11,"") -> 17840 | Y11: =IF(AND(H11<>"YES",M11<>"",N11<>""),IF(E11=1,(N11*M11)/2,N11*M11),"") -> 400 | Z11: =IF(AND(H11<>"yes",F11<>""),IFERROR(VLOOKUP(F11,DUTY_2025!A:F,5,FALSE),""),"") -> 570 | AA11: =IF(B11<>"",IF(AND(X11<>"", O11<>""),IF(ROUND(X11*100/(100+O11),0)=0,"",ROUND(X11*100/(100+O11),0)),""),"") -> 16990 | AB11: =IF(M11<>"",IF(AND(X11<>"",AA11<>""),X11-AA11,""),"") -> 850 | AC11: =IF(AA11<>"",ROUND(AA11*SI!$C$9,0),"") -> 59805 | AD11: =IF(AC11<>"",ROUND(AC11/(SI!$C$9*SI!$C$10),2),"") -> 178.49 | AE11: =IF(AND(X11<>""), ROUND((SI!$E$23)*(X11/SUM($X$5:$X$493)),0),"") -> 4646 | AF11: =IF(AND(AC11<>"",AE11<>""),ROUND(AC11+AE11,0),"") -> 64451 | AG11: =IF(AND(Z11<>"",V11<>""),Z11*V11,"") -> 39900 | AH11: =IF(AD11<>"",ROUND(AD11*10*SI!$C$9/2,0),"") -> 3141 | AI11: =IF(AND(X11<>""), ROUND((SI!$E$28)*(X11/SUM($X$5:$X$493)),0),"") -> 13200 | AJ11: =IF(AND(AG11<>"",AI11<>"",AH11<>""),AG11+AI11+AH11,"") -> 56241 | AK11: =IF(AND(AJ11<>"",Y11<>""),ROUND(AJ11/Y11,0),"") -> 141 | AL11: =IF(AND(AC11<>"",Y11<>""),ROUND(AF11/Y11,0),"") -> 161 | AM11: =IF(AND(AK11<>"",AL11<>""),AK11+AL11,"") -> 302 | AN11: =IF(AND(AF11<>"",AG11<>"",AH11<>"",AI11<>""),AF11+AG11+AH11+AI11,"") -> 120692 | AO11: =IF(AND(AM11<>"",P11<>""),ROUND((AM11*((100+SI!$C$11)/100)),0),"") -> 347 | AP11: =IF(AG11<>"",ROUND(AG11/SI!$C$9,2),"") -> 11335.23 | AQ11: =IF(AH11<>"",ROUND(AH11/SI!$C$9,2),"") -> 892.33 | AR11: =IF(AI11<>"",ROUND(AI11/SI!$C$9,2),"") -> 3750 | AS11: =IF(AND(AP11<>"",AR11<>"",AQ11<>""),AP11+AR11+AQ11,"") -> 15977.56 | AT11: =IF(AND(AS11<>"",Y11<>""),ROUND(AS11/Y11,2),"") -> 39.94 | AU11: =IF(AL11<>"",ROUND(AL11/SI!$C$9,2),"") -> 45.74 | AV11: =IF(AM11<>"",ROUND(AM11/SI!$C$9,2),"") -> 85.8 | AW11: =IF(AN11<>"",ROUND(AN11/SI!$C$9,2),"") -> 34287.5 | AX11: =IF(AO11<>"",ROUND(AO11/SI!$C$9,2),"") -> 98.58 | AY11: =IF(AF11<>"",AF11,"") -> 64451 | AZ11: =IF(AY11<>"",ROUND(AY11/(SI!$C$9*SI!$C$10),2),"") -> 192.35 | BA11: =IF(AND(AY11<>"",BH11<>""),ROUND(AY11*BH11/100,2),"") -> 51560.8 | BB11: =IF(AND(AZ11<>"",BH11<>""),ROUND(AZ11*BH11/100,2),"") -> 153.88 | BC11: =IF(AND(BB11<>"",Y11<>""),ROUND(BB11/Y11,3),"") -> 0.385 | BD11: =IF(AND(BB11<>"",T11<>""),ROUND(BB11/V11,3),"") -> 2.198 | BE11: =IF(AND(X11<>""),ROUND(X11/SI!$C$10,2),"") -> 187.41 | BF11: =IF(AND(BE11<>"",Y11<>""),ROUND(BE11/Y11,3),"") -> 0.469 | BG11: =IF(AND(BE11<>"",V11<>""),ROUND(BE11/V11,3),"") -> 2.677 | BH11: =IF(F11<>"",VLOOKUP(F11,DUTY_2025!A:O,15,FALSE),"") -> 80
A12: =IF(AND(F12<>"",H12<>"YES"),IF(A11<>"",A11,0)+1,A11) -> 8 | B12: =IF(AND(F12<>"",H12<>"YES"),IF(B11<>"",B11,A11)+1,"") -> 8 | C12: 1 | F12: 21069060 | G12: =IF(F12<>"",IFERROR(VLOOKUP(F12,DUTY_2025!A:I,6,FALSE),""),"") -> 0 | H12: NO | I12: =IF(F12<>"",IFERROR(VLOOKUP(F12,DUTY_2025!A:H,2,FALSE),""),"") -> PAPADS - OTHERS | J12: PANI PURI KIT FAMILY 266 G | K12: 0 | L12: 266 | M12: 22 | N12: 20 | O12: 5 | P12: 22500 | Q12: INR | R12: NET | S12: =IF(AND(H12<>"YES",N12<>""),N12*L12/1000,"") -> 5.32 | T12: =IF(S12<>"",S12*1.1,"") -> 5.852 | U12: {=IF(AND(H12<>"YES",P12<>"",R12<>"",Q12<>""), _xlfn.SWITCH(Q12, "INR",_xlfn.SWITCH(R12,"KG",P12*S12,"CTN",P12,"UNIT",P12*N12,"NET",P12/M12,0), "USD",_xlfn.SWITCH(R12,"KG",P12*S12*SI!$C$10,"CTN",P12*SI!$C$10,"UNIT",P12*N12*SI!$C$10,"NET",P12*SI!$C$10/M12,0), "LKR",_xlfn.SWITCH(R12,"KG",P12*S12/SI!$C$9,"CTN",P12/SI!$C$9,"UNIT",P12*N12/SI!$C$9,"NET",P12/(M12*SI!$C$9),0), 0), "")} -> 1022.7273 | V12: =IF(AND(S12<>"",M12<>"",N12<>""),S12*M12,"") -> 117.04 | W12: =IF(V12<>"",V12*1.1,"") -> 128.744 | X12: =IF(AND(U12<>"",M12<>""),U12*M12,"") -> 22500 | Y12: =IF(AND(H12<>"YES",M12<>"",N12<>""),IF(E12=1,(N12*M12)/2,N12*M12),"") -> 440 | Z12: =IF(AND(H12<>"yes",F12<>""),IFERROR(VLOOKUP(F12,DUTY_2025!A:F,5,FALSE),""),"") -> 1120 | AA12: =IF(B12<>"",IF(AND(X12<>"", O12<>""),IF(ROUND(X12*100/(100+O12),0)=0,"",ROUND(X12*100/(100+O12),0)),""),"") -> 21429 | AB12: =IF(M12<>"",IF(AND(X12<>"",AA12<>""),X12-AA12,""),"") -> 1071 | AC12: =IF(AA12<>"",ROUND(AA12*SI!$C$9,0),"") -> 75430 | AD12: =IF(AC12<>"",ROUND(AC12/(SI!$C$9*SI!$C$10),2),"") -> 225.12 | AE12: =IF(AND(X12<>""), ROUND((SI!$E$23)*(X12/SUM($X$5:$X$493)),0),"") -> 5860 | AF12: =IF(AND(AC12<>"",AE12<>""),ROUND(AC12+AE12,0),"") -> 81290 | AG12: =IF(AND(Z12<>"",V12<>""),Z12*V12,"") -> 131084.8 | AH12: =IF(AD12<>"",ROUND(AD12*10*SI!$C$9/2,0),"") -> 3962 | AI12: =IF(AND(X12<>""), ROUND((SI!$E$28)*(X12/SUM($X$5:$X$493)),0),"") -> 16648 | AJ12: =IF(AND(AG12<>"",AI12<>"",AH12<>""),AG12+AI12+AH12,"") -> 151694.8 | AK12: =IF(AND(AJ12<>"",Y12<>""),ROUND(AJ12/Y12,0),"") -> 345 | AL12: =IF(AND(AC12<>"",Y12<>""),ROUND(AF12/Y12,0),"") -> 185 | AM12: =IF(AND(AK12<>"",AL12<>""),AK12+AL12,"") -> 530 | AN12: =IF(AND(AF12<>"",AG12<>"",AH12<>"",AI12<>""),AF12+AG12+AH12+AI12,"") -> 232984.8 | AO12: =IF(AND(AM12<>"",P12<>""),ROUND((AM12*((100+SI!$C$11)/100)),0),"") -> 610 | AP12: =IF(AG12<>"",ROUND(AG12/SI!$C$9,2),"") -> 37240 | AQ12: =IF(AH12<>"",ROUND(AH12/SI!$C$9,2),"") -> 1125.57 | AR12: =IF(AI12<>"",ROUND(AI12/SI!$C$9,2),"") -> 4729.55 | AS12: =IF(AND(AP12<>"",AR12<>"",AQ12<>""),AP12+AR12+AQ12,"") -> 43095.12 | AT12: =IF(AND(AS12<>"",Y12<>""),ROUND(AS12/Y12,2),"") -> 97.94 | AU12: =IF(AL12<>"",ROUND(AL12/SI!$C$9,2),"") -> 52.56 | AV12: =IF(AM12<>"",ROUND(AM12/SI!$C$9,2),"") -> 150.57 | AW12: =IF(AN12<>"",ROUND(AN12/SI!$C$9,2),"") -> 66188.86 | AX12: =IF(AO12<>"",ROUND(AO12/SI!$C$9,2),"") -> 173.3 | AY12: =IF(AF12<>"",AF12,"") -> 81290 | AZ12: =IF(AY12<>"",ROUND(AY12/(SI!$C$9*SI!$C$10),2),"") -> 242.61 | BA12: =IF(AND(AY12<>"",BH12<>""),ROUND(AY12*BH12/100,2),"") -> 65032 | BB12: =IF(AND(AZ12<>"",BH12<>""),ROUND(AZ12*BH12/100,2),"") -> 194.09 | BC12: =IF(AND(BB12<>"",Y12<>""),ROUND(BB12/Y12,3),"") -> 0.441 | BD12: =IF(AND(BB12<>"",T12<>""),ROUND(BB12/V12,3),"") -> 1.658 | BE12: =IF(AND(X12<>""),ROUND(X12/SI!$C$10,2),"") -> 236.37 | BF12: =IF(AND(BE12<>"",Y12<>""),ROUND(BE12/Y12,3),"") -> 0.537 | BG12: =IF(AND(BE12<>"",V12<>""),ROUND(BE12/V12,3),"") -> 2.02 | BH12: =IF(F12<>"",VLOOKUP(F12,DUTY_2025!A:O,15,FALSE),"") -> 80
A13: =IF(AND(F13<>"",H13<>"YES"),IF(A12<>"",A12,0)+1,A12) -> 9 | B13: =IF(AND(F13<>"",H13<>"YES"),IF(B12<>"",B12,A12)+1,"") -> 9 | C13: 1 | F13: 20019000 | G13: =IF(F13<>"",IFERROR(VLOOKUP(F13,DUTY_2025!A:I,6,FALSE),""),"") -> 0 | H13: NO | I13: =IF(F13<>"",IFERROR(VLOOKUP(F13,DUTY_2025!A:H,2,FALSE),""),"") -> ASSORTED PICKLES | J13: CUT MANGO PICKLE 200 G | K13: 0 | L13: 200 | M13: 43 | N13: 30 | O13: 5 | P13: 36880 | Q13: INR | R13: NET | S13: =IF(AND(H13<>"YES",N13<>""),N13*L13/1000,"") -> 6 | T13: =IF(S13<>"",S13*1.1,"") -> 6.6 | U13: {=IF(AND(H13<>"YES",P13<>"",R13<>"",Q13<>""), _xlfn.SWITCH(Q13, "INR",_xlfn.SWITCH(R13,"KG",P13*S13,"CTN",P13,"UNIT",P13*N13,"NET",P13/M13,0), "USD",_xlfn.SWITCH(R13,"KG",P13*S13*SI!$C$10,"CTN",P13*SI!$C$10,"UNIT",P13*N13*SI!$C$10,"NET",P13*SI!$C$10/M13,0), "LKR",_xlfn.SWITCH(R13,"KG",P13*S13/SI!$C$9,"CTN",P13/SI!$C$9,"UNIT",P13*N13/SI!$C$9,"NET",P13/(M13*SI!$C$9),0), 0), "")} -> 857.67442 | V13: =IF(AND(S13<>"",M13<>"",N13<>""),S13*M13,"") -> 258 | W13: =IF(V13<>"",V13*1.1,"") -> 283.8 | X13: =IF(AND(U13<>"",M13<>""),U13*M13,"") -> 36880 | Y13: =IF(AND(H13<>"YES",M13<>"",N13<>""),IF(E13=1,(N13*M13)/2,N13*M13),"") -> 1290 | Z13: =IF(AND(H13<>"yes",F13<>""),IFERROR(VLOOKUP(F13,DUTY_2025!A:F,5,FALSE),""),"") -> 561 | AA13: =IF(B13<>"",IF(AND(X13<>"", O13<>""),IF(ROUND(X13*100/(100+O13),0)=0,"",ROUND(X13*100/(100+O13),0)),""),"") -> 35124 | AB13: =IF(M13<>"",IF(AND(X13<>"",AA13<>""),X13-AA13,""),"") -> 1756 | AC13: =IF(AA13<>"",ROUND(AA13*SI!$C$9,0),"") -> 123636 | AD13: =IF(AC13<>"",ROUND(AC13/(SI!$C$9*SI!$C$10),2),"") -> 368.99 | AE13: =IF(AND(X13<>""), ROUND((SI!$E$23)*(X13/SUM($X$5:$X$493)),0),"") -> 9605 | AF13: =IF(AND(AC13<>"",AE13<>""),ROUND(AC13+AE13,0),"") -> 133241 | AG13: =IF(AND(Z13<>"",V13<>""),Z13*V13,"") -> 144738 | AH13: =IF(AD13<>"",ROUND(AD13*10*SI!$C$9/2,0),"") -> 6494 | AI13: =IF(AND(X13<>""), ROUND((SI!$E$28)*(X13/SUM($X$5:$X$493)),0),"") -> 27287 | AJ13: =IF(AND(AG13<>"",AI13<>"",AH13<>""),AG13+AI13+AH13,"") -> 178519 | AK13: =IF(AND(AJ13<>"",Y13<>""),ROUND(AJ13/Y13,0),"") -> 138 | AL13: =IF(AND(AC13<>"",Y13<>""),ROUND(AF13/Y13,0),"") -> 103 | AM13: =IF(AND(AK13<>"",AL13<>""),AK13+AL13,"") -> 241 | AN13: =IF(AND(AF13<>"",AG13<>"",AH13<>"",AI13<>""),AF13+AG13+AH13+AI13,"") -> 311760 | AO13: =IF(AND(AM13<>"",P13<>""),ROUND((AM13*((100+SI!$C$11)/100)),0),"") -> 277 | AP13: =IF(AG13<>"",ROUND(AG13/SI!$C$9,2),"") -> 41118.75 | AQ13: =IF(AH13<>"",ROUND(AH13/SI!$C$9,2),"") -> 1844.89 | AR13: =IF(AI13<>"",ROUND(AI13/SI!$C$9,2),"") -> 7751.99 | AS13: =IF(AND(AP13<>"",AR13<>"",AQ13<>""),AP13+AR13+AQ13,"") -> 50715.63 | AT13: =IF(AND(AS13<>"",Y13<>""),ROUND(AS13/Y13,2),"") -> 39.31 | AU13: =IF(AL13<>"",ROUND(AL13/SI!$C$9,2),"") -> 29.26 | AV13: =IF(AM13<>"",ROUND(AM13/SI!$C$9,2),"") -> 68.47 | AW13: =IF(AN13<>"",ROUND(AN13/SI!$C$9,2),"") -> 88568.18 | AX13: =IF(AO13<>"",ROUND(AO13/SI!$C$9,2),"") -> 78.69 | AY13: =IF(AF13<>"",AF13,"") -> 133241 | AZ13: =IF(AY13<>"",ROUND(AY13/(SI!$C$9*SI!$C$10),2),"") -> 397.65 | BA13: =IF(AND(AY13<>"",BH13<>""),ROUND(AY13*BH13/100,2),"") -> 106592.8 | BB13: =IF(AND(AZ13<>"",BH13<>""),ROUND(AZ13*BH13/100,2),"") -> 318.12 | BC13: =IF(AND(BB13<>"",Y13<>""),ROUND(BB13/Y13,3),"") -> 0.247 | BD13: =IF(AND(BB13<>"",T13<>""),ROUND(BB13/V13,3),"") -> 1.233 | BE13: =IF(AND(X13<>""),ROUND(X13/SI!$C$10,2),"") -> 387.44 | BF13: =IF(AND(BE13<>"",Y13<>""),ROUND(BE13/Y13,3),"") -> 0.3 | BG13: =IF(AND(BE13<>"",V13<>""),ROUND(BE13/V13,3),"") -> 1.502 | BH13: =IF(F13<>"",VLOOKUP(F13,DUTY_2025!A:O,15,FALSE),"") -> 80
A14: =IF(AND(F14<>"",H14<>"YES"),IF(A13<>"",A13,0)+1,A13) -> 10 | B14: =IF(AND(F14<>"",H14<>"YES"),IF(B13<>"",B13,A13)+1,"") -> 10 | C14: 1 | F14: 20019000 | G14: =IF(F14<>"",IFERROR(VLOOKUP(F14,DUTY_2025!A:I,6,FALSE),""),"") -> 0 | H14: NO | I14: =IF(F14<>"",IFERROR(VLOOKUP(F14,DUTY_2025!A:H,2,FALSE),""),"") -> ASSORTED PICKLES | J14: LEMON PICKLE 200 G | K14: 0 | L14: 200 | M14: 43 | N14: 30 | O14: 5 | P14: 36880 | Q14: INR | R14: NET | S14: =IF(AND(H14<>"YES",N14<>""),N14*L14/1000,"") -> 6 | T14: =IF(S14<>"",S14*1.1,"") -> 6.6 | U14: {=IF(AND(H14<>"YES",P14<>"",R14<>"",Q14<>""), _xlfn.SWITCH(Q14, "INR",_xlfn.SWITCH(R14,"KG",P14*S14,"CTN",P14,"UNIT",P14*N14,"NET",P14/M14,0), "USD",_xlfn.SWITCH(R14,"KG",P14*S14*SI!$C$10,"CTN",P14*SI!$C$10,"UNIT",P14*N14*SI!$C$10,"NET",P14*SI!$C$10/M14,0), "LKR",_xlfn.SWITCH(R14,"KG",P14*S14/SI!$C$9,"CTN",P14/SI!$C$9,"UNIT",P14*N14/SI!$C$9,"NET",P14/(M14*SI!$C$9),0), 0), "")} -> 857.67442 | V14: =IF(AND(S14<>"",M14<>"",N14<>""),S14*M14,"") -> 258 | W14: =IF(V14<>"",V14*1.1,"") -> 283.8 | X14: =IF(AND(U14<>"",M14<>""),U14*M14,"") -> 36880 | Y14: =IF(AND(H14<>"YES",M14<>"",N14<>""),IF(E14=1,(N14*M14)/2,N14*M14),"") -> 1290 | Z14: =IF(AND(H14<>"yes",F14<>""),IFERROR(VLOOKUP(F14,DUTY_2025!A:F,5,FALSE),""),"") -> 561 | AA14: =IF(B14<>"",IF(AND(X14<>"", O14<>""),IF(ROUND(X14*100/(100+O14),0)=0,"",ROUND(X14*100/(100+O14),0)),""),"") -> 35124 | AB14: =IF(M14<>"",IF(AND(X14<>"",AA14<>""),X14-AA14,""),"") -> 1756 | AC14: =IF(AA14<>"",ROUND(AA14*SI!$C$9,0),"") -> 123636 | AD14: =IF(AC14<>"",ROUND(AC14/(SI!$C$9*SI!$C$10),2),"") -> 368.99 | AE14: =IF(AND(X14<>""), ROUND((SI!$E$23)*(X14/SUM($X$5:$X$493)),0),"") -> 9605 | AF14: =IF(AND(AC14<>"",AE14<>""),ROUND(AC14+AE14,0),"") -> 133241 | AG14: =IF(AND(Z14<>"",V14<>""),Z14*V14,"") -> 144738 | AH14: =IF(AD14<>"",ROUND(AD14*10*SI!$C$9/2,0),"") -> 6494 | AI14: =IF(AND(X14<>""), ROUND((SI!$E$28)*(X14/SUM($X$5:$X$493)),0),"") -> 27287 | AJ14: =IF(AND(AG14<>"",AI14<>"",AH14<>""),AG14+AI14+AH14,"") -> 178519 | AK14: =IF(AND(AJ14<>"",Y14<>""),ROUND(AJ14/Y14,0),"") -> 138 | AL14: =IF(AND(AC14<>"",Y14<>""),ROUND(AF14/Y14,0),"") -> 103 | AM14: =IF(AND(AK14<>"",AL14<>""),AK14+AL14,"") -> 241 | AN14: =IF(AND(AF14<>"",AG14<>"",AH14<>"",AI14<>""),AF14+AG14+AH14+AI14,"") -> 311760 | AO14: =IF(AND(AM14<>"",P14<>""),ROUND((AM14*((100+SI!$C$11)/100)),0),"") -> 277 | AP14: =IF(AG14<>"",ROUND(AG14/SI!$C$9,2),"") -> 41118.75 | AQ14: =IF(AH14<>"",ROUND(AH14/SI!$C$9,2),"") -> 1844.89 | AR14: =IF(AI14<>"",ROUND(AI14/SI!$C$9,2),"") -> 7751.99 | AS14: =IF(AND(AP14<>"",AR14<>"",AQ14<>""),AP14+AR14+AQ14,"") -> 50715.63 | AT14: =IF(AND(AS14<>"",Y14<>""),ROUND(AS14/Y14,2),"") -> 39.31 | AU14: =IF(AL14<>"",ROUND(AL14/SI!$C$9,2),"") -> 29.26 | AV14: =IF(AM14<>"",ROUND(AM14/SI!$C$9,2),"") -> 68.47 | AW14: =IF(AN14<>"",ROUND(AN14/SI!$C$9,2),"") -> 88568.18 | AX14: =IF(AO14<>"",ROUND(AO14/SI!$C$9,2),"") -> 78.69 | AY14: =IF(AF14<>"",AF14,"") -> 133241 | AZ14: =IF(AY14<>"",ROUND(AY14/(SI!$C$9*SI!$C$10),2),"") -> 397.65 | BA14: =IF(AND(AY14<>"",BH14<>""),ROUND(AY14*BH14/100,2),"") -> 106592.8 | BB14: =IF(AND(AZ14<>"",BH14<>""),ROUND(AZ14*BH14/100,2),"") -> 318.12 | BC14: =IF(AND(BB14<>"",Y14<>""),ROUND(BB14/Y14,3),"") -> 0.247 | BD14: =IF(AND(BB14<>"",T14<>""),ROUND(BB14/V14,3),"") -> 1.233 | BE14: =IF(AND(X14<>""),ROUND(X14/SI!$C$10,2),"") -> 387.44 | BF14: =IF(AND(BE14<>"",Y14<>""),ROUND(BE14/Y14,3),"") -> 0.3 | BG14: =IF(AND(BE14<>"",V14<>""),ROUND(BE14/V14,3),"") -> 1.502 | BH14: =IF(F14<>"",VLOOKUP(F14,DUTY_2025!A:O,15,FALSE),"") -> 80
A15: =IF(AND(F15<>"",H15<>"YES"),IF(A14<>"",A14,0)+1,A14) -> 11 | B15: =IF(AND(F15<>"",H15<>"YES"),IF(B14<>"",B14,A14)+1,"") -> 11 | C15: 1 | F15: 20019000 | G15: =IF(F15<>"",IFERROR(VLOOKUP(F15,DUTY_2025!A:I,6,FALSE),""),"") -> 0 | H15: NO | I15: =IF(F15<>"",IFERROR(VLOOKUP(F15,DUTY_2025!A:H,2,FALSE),""),"") -> ASSORTED PICKLES | J15: GARLIC PICKLE 200 G | K15: 0 | L15: 200 | M15: 43 | N15: 30 | O15: 5 | P15: 39480 | Q15: INR | R15: NET | S15: =IF(AND(H15<>"YES",N15<>""),N15*L15/1000,"") -> 6 | T15: =IF(S15<>"",S15*1.1,"") -> 6.6 | U15: {=IF(AND(H15<>"YES",P15<>"",R15<>"",Q15<>""), _xlfn.SWITCH(Q15, "INR",_xlfn.SWITCH(R15,"KG",P15*S15,"CTN",P15,"UNIT",P15*N15,"NET",P15/M15,0), "USD",_xlfn.SWITCH(R15,"KG",P15*S15*SI!$C$10,"CTN",P15*SI!$C$10,"UNIT",P15*N15*SI!$C$10,"NET",P15*SI!$C$10/M15,0), "LKR",_xlfn.SWITCH(R15,"KG",P15*S15/SI!$C$9,"CTN",P15/SI!$C$9,"UNIT",P15*N15/SI!$C$9,"NET",P15/(M15*SI!$C$9),0), 0), "")} -> 918.13953 | V15: =IF(AND(S15<>"",M15<>"",N15<>""),S15*M15,"") -> 258 | W15: =IF(V15<>"",V15*1.1,"") -> 283.8 | X15: =IF(AND(U15<>"",M15<>""),U15*M15,"") -> 39480 | Y15: =IF(AND(H15<>"YES",M15<>"",N15<>""),IF(E15=1,(N15*M15)/2,N15*M15),"") -> 1290 | Z15: =IF(AND(H15<>"yes",F15<>""),IFERROR(VLOOKUP(F15,DUTY_2025!A:F,5,FALSE),""),"") -> 561 | AA15: =IF(B15<>"",IF(AND(X15<>"", O15<>""),IF(ROUND(X15*100/(100+O15),0)=0,"",ROUND(X15*100/(100+O15),0)),""),"") -> 37600 | AB15: =IF(M15<>"",IF(AND(X15<>"",AA15<>""),X15-AA15,""),"") -> 1880 | AC15: =IF(AA15<>"",ROUND(AA15*SI!$C$9,0),"") -> 132352 | AD15: =IF(AC15<>"",ROUND(AC15/(SI!$C$9*SI!$C$10),2),"") -> 395 | AE15: =IF(AND(X15<>""), ROUND((SI!$E$23)*(X15/SUM($X$5:$X$493)),0),"") -> 10282 | AF15: =IF(AND(AC15<>"",AE15<>""),ROUND(AC15+AE15,0),"") -> 142634 | AG15: =IF(AND(Z15<>"",V15<>""),Z15*V15,"") -> 144738 | AH15: =IF(AD15<>"",ROUND(AD15*10*SI!$C$9/2,0),"") -> 6952 | AI15: =IF(AND(X15<>""), ROUND((SI!$E$28)*(X15/SUM($X$5:$X$493)),0),"") -> 29211 | AJ15: =IF(AND(AG15<>"",AI15<>"",AH15<>""),AG15+AI15+AH15,"") -> 180901 | AK15: =IF(AND(AJ15<>"",Y15<>""),ROUND(AJ15/Y15,0),"") -> 140 | AL15: =IF(AND(AC15<>"",Y15<>""),ROUND(AF15/Y15,0),"") -> 111 | AM15: =IF(AND(AK15<>"",AL15<>""),AK15+AL15,"") -> 251 | AN15: =IF(AND(AF15<>"",AG15<>"",AH15<>"",AI15<>""),AF15+AG15+AH15+AI15,"") -> 323535 | AO15: =IF(AND(AM15<>"",P15<>""),ROUND((AM15*((100+SI!$C$11)/100)),0),"") -> 289 | AP15: =IF(AG15<>"",ROUND(AG15/SI!$C$9,2),"") -> 41118.75 | AQ15: =IF(AH15<>"",ROUND(AH15/SI!$C$9,2),"") -> 1975 | AR15: =IF(AI15<>"",ROUND(AI15/SI!$C$9,2),"") -> 8298.58 | AS15: =IF(AND(AP15<>"",AR15<>"",AQ15<>""),AP15+AR15+AQ15,"") -> 51392.33 | AT15: =IF(AND(AS15<>"",Y15<>""),ROUND(AS15/Y15,2),"") -> 39.84 | AU15: =IF(AL15<>"",ROUND(AL15/SI!$C$9,2),"") -> 31.53 | AV15: =IF(AM15<>"",ROUND(AM15/SI!$C$9,2),"") -> 71.31 | AW15: =IF(AN15<>"",ROUND(AN15/SI!$C$9,2),"") -> 91913.35 | AX15: =IF(AO15<>"",ROUND(AO15/SI!$C$9,2),"") -> 82.1 | AY15: =IF(AF15<>"",AF15,"") -> 142634 | AZ15: =IF(AY15<>"",ROUND(AY15/(SI!$C$9*SI!$C$10),2),"") -> 425.69 | BA15: =IF(AND(AY15<>"",BH15<>""),ROUND(AY15*BH15/100,2),"") -> 114107.2 | BB15: =IF(AND(AZ15<>"",BH15<>""),ROUND(AZ15*BH15/100,2),"") -> 340.55 | BC15: =IF(AND(BB15<>"",Y15<>""),ROUND(BB15/Y15,3),"") -> 0.264 | BD15: =IF(AND(BB15<>"",T15<>""),ROUND(BB15/V15,3),"") -> 1.32 | BE15: =IF(AND(X15<>""),ROUND(X15/SI!$C$10,2),"") -> 414.75 | BF15: =IF(AND(BE15<>"",Y15<>""),ROUND(BE15/Y15,3),"") -> 0.322 | BG15: =IF(AND(BE15<>"",V15<>""),ROUND(BE15/V15,3),"") -> 1.608 | BH15: =IF(F15<>"",VLOOKUP(F15,DUTY_2025!A:O,15,FALSE),"") -> 80
A16: =IF(AND(F16<>"",H16<>"YES"),IF(A15<>"",A15,0)+1,A15) -> 12 | B16: =IF(AND(F16<>"",H16<>"YES"),IF(B15<>"",B15,A15)+1,"") -> 12 | C16: 1 | F16: 20019000 | G16: =IF(F16<>"",IFERROR(VLOOKUP(F16,DUTY_2025!A:I,6,FALSE),""),"") -> 0 | H16: NO | I16: =IF(F16<>"",IFERROR(VLOOKUP(F16,DUTY_2025!A:H,2,FALSE),""),"") -> ASSORTED PICKLES | J16: MIXED VEG PICKLE 200 G | K16: 0 | L16: 200 | M16: 16 | N16: 30 | O16: 5 | P16: 128.64 | Q16: USD | R16: NET | S16: =IF(AND(H16<>"YES",N16<>""),N16*L16/1000,"") -> 6 | T16: =IF(S16<>"",S16*1.1,"") -> 6.6 | U16: {=IF(AND(H16<>"YES",P16<>"",R16<>"",Q16<>""), _xlfn.SWITCH(Q16, "INR",_xlfn.SWITCH(R16,"KG",P16*S16,"CTN",P16,"UNIT",P16*N16,"NET",P16/M16,0), "USD",_xlfn.SWITCH(R16,"KG",P16*S16*SI!$C$10,"CTN",P16*SI!$C$10,"UNIT",P16*N16*SI!$C$10,"NET",P16*SI!$C$10/M16,0), "LKR",_xlfn.SWITCH(R16,"KG",P16*S16/SI!$C$9,"CTN",P16/SI!$C$9,"UNIT",P16*N16/SI!$C$9,"NET",P16/(M16*SI!$C$9),0), 0), "")} -> 765.3276 | V16: =IF(AND(S16<>"",M16<>"",N16<>""),S16*M16,"") -> 96 | W16: =IF(V16<>"",V16*1.1,"") -> 105.6 | X16: =IF(AND(U16<>"",M16<>""),U16*M16,"") -> 12245.242 | Y16: =IF(AND(H16<>"YES",M16<>"",N16<>""),IF(E16=1,(N16*M16)/2,N16*M16),"") -> 480 | Z16: =IF(AND(H16<>"yes",F16<>""),IFERROR(VLOOKUP(F16,DUTY_2025!A:F,5,FALSE),""),"") -> 561 | AA16: =IF(B16<>"",IF(AND(X16<>"", O16<>""),IF(ROUND(X16*100/(100+O16),0)=0,"",ROUND(X16*100/(100+O16),0)),""),"") -> 11662 | AB16: =IF(M16<>"",IF(AND(X16<>"",AA16<>""),X16-AA16,""),"") -> 583.2416 | AC16: =IF(AA16<>"",ROUND(AA16*SI!$C$9,0),"") -> 41050 | AD16: =IF(AC16<>"",ROUND(AC16/(SI!$C$9*SI!$C$10),2),"") -> 122.51 | AE16: =IF(AND(X16<>""), ROUND((SI!$E$23)*(X16/SUM($X$5:$X$493)),0),"") -> 3189 | AF16: =IF(AND(AC16<>"",AE16<>""),ROUND(AC16+AE16,0),"") -> 44239 | AG16: =IF(AND(Z16<>"",V16<>""),Z16*V16,"") -> 53856 | AH16: =IF(AD16<>"",ROUND(AD16*10*SI!$C$9/2,0),"") -> 2156 | AI16: =IF(AND(X16<>""), ROUND((SI!$E$28)*(X16/SUM($X$5:$X$493)),0),"") -> 9060 | AJ16: =IF(AND(AG16<>"",AI16<>"",AH16<>""),AG16+AI16+AH16,"") -> 65072 | AK16: =IF(AND(AJ16<>"",Y16<>""),ROUND(AJ16/Y16,0),"") -> 136 | AL16: =IF(AND(AC16<>"",Y16<>""),ROUND(AF16/Y16,0),"") -> 92 | AM16: =IF(AND(AK16<>"",AL16<>""),AK16+AL16,"") -> 228 | AN16: =IF(AND(AF16<>"",AG16<>"",AH16<>"",AI16<>""),AF16+AG16+AH16+AI16,"") -> 109311 | AO16: =IF(AND(AM16<>"",P16<>""),ROUND((AM16*((100+SI!$C$11)/100)),0),"") -> 262 | AP16: =IF(AG16<>"",ROUND(AG16/SI!$C$9,2),"") -> 15300 | AQ16: =IF(AH16<>"",ROUND(AH16/SI!$C$9,2),"") -> 612.5 | AR16: =IF(AI16<>"",ROUND(AI16/SI!$C$9,2),"") -> 2573.86 | AS16: =IF(AND(AP16<>"",AR16<>"",AQ16<>""),AP16+AR16+AQ16,"") -> 18486.36 | AT16: =IF(AND(AS16<>"",Y16<>""),ROUND(AS16/Y16,2),"") -> 38.51 | AU16: =IF(AL16<>"",ROUND(AL16/SI!$C$9,2),"") -> 26.14 | AV16: =IF(AM16<>"",ROUND(AM16/SI!$C$9,2),"") -> 64.77 | AW16: =IF(AN16<>"",ROUND(AN16/SI!$C$9,2),"") -> 31054.26 | AX16: =IF(AO16<>"",ROUND(AO16/SI!$C$9,2),"") -> 74.43 | AY16: =IF(AF16<>"",AF16,"") -> 44239 | AZ16: =IF(AY16<>"",ROUND(AY16/(SI!$C$9*SI!$C$10),2),"") -> 132.03 | BA16: =IF(AND(AY16<>"",BH16<>""),ROUND(AY16*BH16/100,2),"") -> 35391.2 | BB16: =IF(AND(AZ16<>"",BH16<>""),ROUND(AZ16*BH16/100,2),"") -> 105.62 | BC16: =IF(AND(BB16<>"",Y16<>""),ROUND(BB16/Y16,3),"") -> 0.22 | BD16: =IF(AND(BB16<>"",T16<>""),ROUND(BB16/V16,3),"") -> 1.1 | BE16: =IF(AND(X16<>""),ROUND(X16/SI!$C$10,2),"") -> 128.64 | BF16: =IF(AND(BE16<>"",Y16<>""),ROUND(BE16/Y16,3),"") -> 0.268 | BG16: =IF(AND(BE16<>"",V16<>""),ROUND(BE16/V16,3),"") -> 1.34 | BH16: =IF(F16<>"",VLOOKUP(F16,DUTY_2025!A:O,15,FALSE),"") -> 80
A17: =IF(AND(F17<>"",H17<>"YES"),IF(A16<>"",A16,0)+1,A16) -> 13 | B17: =IF(AND(F17<>"",H17<>"YES"),IF(B16<>"",B16,A16)+1,"") -> 13 | C17: 1 | F17: 20019000 | G17: =IF(F17<>"",IFERROR(VLOOKUP(F17,DUTY_2025!A:I,6,FALSE),""),"") -> 0 | H17: NO | I17: =IF(F17<>"",IFERROR(VLOOKUP(F17,DUTY_2025!A:H,2,FALSE),""),"") -> ASSORTED PICKLES | J17: MANGOTHOKKU PICKLE 200 G | K17: 0 | L17: 200 | M17: 5 | N17: 30 | O17: 5 | P17: 40.2 | Q17: USD | R17: NET | S17: =IF(AND(H17<>"YES",N17<>""),N17*L17/1000,"") -> 6 | T17: =IF(S17<>"",S17*1.1,"") -> 6.6 | U17: {=IF(AND(H17<>"YES",P17<>"",R17<>"",Q17<>""), _xlfn.SWITCH(Q17, "INR",_xlfn.SWITCH(R17,"KG",P17*S17,"CTN",P17,"UNIT",P17*N17,"NET",P17/M17,0), "USD",_xlfn.SWITCH(R17,"KG",P17*S17*SI!$C$10,"CTN",P17*SI!$C$10,"UNIT",P17*N17*SI!$C$10,"NET",P17*SI!$C$10/M17,0), "LKR",_xlfn.SWITCH(R17,"KG",P17*S17/SI!$C$9,"CTN",P17/SI!$C$9,"UNIT",P17*N17/SI!$C$9,"NET",P17/(M17*SI!$C$9),0), 0), "")} -> 765.3276 | V17: =IF(AND(S17<>"",M17<>"",N17<>""),S17*M17,"") -> 30 | W17: =IF(V17<>"",V17*1.1,"") -> 33 | X17: =IF(AND(U17<>"",M17<>""),U17*M17,"") -> 3826.638 | Y17: =IF(AND(H17<>"YES",M17<>"",N17<>""),IF(E17=1,(N17*M17)/2,N17*M17),"") -> 150 | Z17: =IF(AND(H17<>"yes",F17<>""),IFERROR(VLOOKUP(F17,DUTY_2025!A:F,5,FALSE),""),"") -> 561 | AA17: =IF(B17<>"",IF(AND(X17<>"", O17<>""),IF(ROUND(X17*100/(100+O17),0)=0,"",ROUND(X17*100/(100+O17),0)),""),"") -> 3644 | AB17: =IF(M17<>"",IF(AND(X17<>"",AA17<>""),X17-AA17,""),"") -> 182.638 | AC17: =IF(AA17<>"",ROUND(AA17*SI!$C$9,0),"") -> 12827 | AD17: =IF(AC17<>"",ROUND(AC17/(SI!$C$9*SI!$C$10),2),"") -> 38.28 | AE17: =IF(AND(X17<>""), ROUND((SI!$E$23)*(X17/SUM($X$5:$X$493)),0),"") -> 997 | AF17: =IF(AND(AC17<>"",AE17<>""),ROUND(AC17+AE17,0),"") -> 13824 | AG17: =IF(AND(Z17<>"",V17<>""),Z17*V17,"") -> 16830 | AH17: =IF(AD17<>"",ROUND(AD17*10*SI!$C$9/2,0),"") -> 674 | AI17: =IF(AND(X17<>""), ROUND((SI!$E$28)*(X17/SUM($X$5:$X$493)),0),"") -> 2831 | AJ17: =IF(AND(AG17<>"",AI17<>"",AH17<>""),AG17+AI17+AH17,"") -> 20335 | AK17: =IF(AND(AJ17<>"",Y17<>""),ROUND(AJ17/Y17,0),"") -> 136 | AL17: =IF(AND(AC17<>"",Y17<>""),ROUND(AF17/Y17,0),"") -> 92 | AM17: =IF(AND(AK17<>"",AL17<>""),AK17+AL17,"") -> 228 | AN17: =IF(AND(AF17<>"",AG17<>"",AH17<>"",AI17<>""),AF17+AG17+AH17+AI17,"") -> 34159 | AO17: =IF(AND(AM17<>"",P17<>""),ROUND((AM17*((100+SI!$C$11)/100)),0),"") -> 262 | AP17: =IF(AG17<>"",ROUND(AG17/SI!$C$9,2),"") -> 4781.25 | AQ17: =IF(AH17<>"",ROUND(AH17/SI!$C$9,2),"") -> 191.48 | AR17: =IF(AI17<>"",ROUND(AI17/SI!$C$9,2),"") -> 804.26 | AS17: =IF(AND(AP17<>"",AR17<>"",AQ17<>""),AP17+AR17+AQ17,"") -> 5776.99 | AT17: =IF(AND(AS17<>"",Y17<>""),ROUND(AS17/Y17,2),"") -> 38.51 | AU17: =IF(AL17<>"",ROUND(AL17/SI!$C$9,2),"") -> 26.14 | AV17: =IF(AM17<>"",ROUND(AM17/SI!$C$9,2),"") -> 64.77 | AW17: =IF(AN17<>"",ROUND(AN17/SI!$C$9,2),"") -> 9704.26 | AX17: =IF(AO17<>"",ROUND(AO17/SI!$C$9,2),"") -> 74.43 | AY17: =IF(AF17<>"",AF17,"") -> 13824 | AZ17: =IF(AY17<>"",ROUND(AY17/(SI!$C$9*SI!$C$10),2),"") -> 41.26 | BA17: =IF(AND(AY17<>"",BH17<>""),ROUND(AY17*BH17/100,2),"") -> 11059.2 | BB17: =IF(AND(AZ17<>"",BH17<>""),ROUND(AZ17*BH17/100,2),"") -> 33.01 | BC17: =IF(AND(BB17<>"",Y17<>""),ROUND(BB17/Y17,3),"") -> 0.22 | BD17: =IF(AND(BB17<>"",T17<>""),ROUND(BB17/V17,3),"") -> 1.1 | BE17: =IF(AND(X17<>""),ROUND(X17/SI!$C$10,2),"") -> 40.2 | BF17: =IF(AND(BE17<>"",Y17<>""),ROUND(BE17/Y17,3),"") -> 0.268 | BG17: =IF(AND(BE17<>"",V17<>""),ROUND(BE17/V17,3),"") -> 1.34 | BH17: =IF(F17<>"",VLOOKUP(F17,DUTY_2025!A:O,15,FALSE),"") -> 80
A18: =IF(AND(F18<>"",H18<>"YES"),IF(A17<>"",A17,0)+1,A17) -> 14 | B18: =IF(AND(F18<>"",H18<>"YES"),IF(B17<>"",B17,A17)+1,"") -> 14 | C18: 1 | F18: 21069099 | G18: =IF(F18<>"",IFERROR(VLOOKUP(F18,DUTY_2025!A:I,6,FALSE),""),"") -> 0 | H18: NO | I18: =IF(F18<>"",IFERROR(VLOOKUP(F18,DUTY_2025!A:H,2,FALSE),""),"") -> HEALTH MIXES | J18: SAKTHI MUTTON MASALA 50G | K18: 0 | L18: 50 | M18: 1 | N18: 600 | O18: 5 | P18: =ROUND(12205.5*1.05,2) -> 12815.78 | Q18: INR | R18: NET | S18: =IF(AND(H18<>"YES",N18<>""),N18*L18/1000,"") -> 30 | T18: =IF(S18<>"",S18*1.1,"") -> 33 | U18: {=IF(AND(H18<>"YES",P18<>"",R18<>"",Q18<>""), _xlfn.SWITCH(Q18, "INR",_xlfn.SWITCH(R18,"KG",P18*S18,"CTN",P18,"UNIT",P18*N18,"NET",P18/M18,0), "USD",_xlfn.SWITCH(R18,"KG",P18*S18*SI!$C$10,"CTN",P18*SI!$C$10,"UNIT",P18*N18*SI!$C$10,"NET",P18*SI!$C$10/M18,0), "LKR",_xlfn.SWITCH(R18,"KG",P18*S18/SI!$C$9,"CTN",P18/SI!$C$9,"UNIT",P18*N18/SI!$C$9,"NET",P18/(M18*SI!$C$9),0), 0), "")} -> 12815.78 | V18: =IF(AND(S18<>"",M18<>"",N18<>""),S18*M18,"") -> 30 | W18: =IF(V18<>"",V18*1.1,"") -> 33 | X18: =IF(AND(U18<>"",M18<>""),U18*M18,"") -> 12815.78 | Y18: =IF(AND(H18<>"YES",M18<>"",N18<>""),IF(E18=1,(N18*M18)/2,N18*M18),"") -> 600 | Z18: =IF(AND(H18<>"yes",F18<>""),IFERROR(VLOOKUP(F18,DUTY_2025!A:F,5,FALSE),""),"") -> 570 | AA18: =IF(B18<>"",IF(AND(X18<>"", O18<>""),IF(ROUND(X18*100/(100+O18),0)=0,"",ROUND(X18*100/(100+O18),0)),""),"") -> 12206 | AB18: =IF(M18<>"",IF(AND(X18<>"",AA18<>""),X18-AA18,""),"") -> 609.78 | AC18: =IF(AA18<>"",ROUND(AA18*SI!$C$9,0),"") -> 42965 | AD18: =IF(AC18<>"",ROUND(AC18/(SI!$C$9*SI!$C$10),2),"") -> 128.23 | AE18: =IF(AND(X18<>""), ROUND((SI!$E$23)*(X18/SUM($X$5:$X$493)),0),"") -> 3338 | AF18: =IF(AND(AC18<>"",AE18<>""),ROUND(AC18+AE18,0),"") -> 46303 | AG18: =IF(AND(Z18<>"",V18<>""),Z18*V18,"") -> 17100 | AH18: =IF(AD18<>"",ROUND(AD18*10*SI!$C$9/2,0),"") -> 2257 | AI18: =IF(AND(X18<>""), ROUND((SI!$E$28)*(X18/SUM($X$5:$X$493)),0),"") -> 9482 | AJ18: =IF(AND(AG18<>"",AI18<>"",AH18<>""),AG18+AI18+AH18,"") -> 28839 | AK18: =IF(AND(AJ18<>"",Y18<>""),ROUND(AJ18/Y18,0),"") -> 48 | AL18: =IF(AND(AC18<>"",Y18<>""),ROUND(AF18/Y18,0),"") -> 77 | AM18: =IF(AND(AK18<>"",AL18<>""),AK18+AL18,"") -> 125 | AN18: =IF(AND(AF18<>"",AG18<>"",AH18<>"",AI18<>""),AF18+AG18+AH18+AI18,"") -> 75142 | AO18: =IF(AND(AM18<>"",P18<>""),ROUND((AM18*((100+SI!$C$11)/100)),0),"") -> 144 | AP18: =IF(AG18<>"",ROUND(AG18/SI!$C$9,2),"") -> 4857.95 | AQ18: =IF(AH18<>"",ROUND(AH18/SI!$C$9,2),"") -> 641.19 | AR18: =IF(AI18<>"",ROUND(AI18/SI!$C$9,2),"") -> 2693.75 | AS18: =IF(AND(AP18<>"",AR18<>"",AQ18<>""),AP18+AR18+AQ18,"") -> 8192.89 | AT18: =IF(AND(AS18<>"",Y18<>""),ROUND(AS18/Y18,2),"") -> 13.65 | AU18: =IF(AL18<>"",ROUND(AL18/SI!$C$9,2),"") -> 21.88 | AV18: =IF(AM18<>"",ROUND(AM18/SI!$C$9,2),"") -> 35.51 | AW18: =IF(AN18<>"",ROUND(AN18/SI!$C$9,2),"") -> 21347.16 | AX18: =IF(AO18<>"",ROUND(AO18/SI!$C$9,2),"") -> 40.91 | AY18: =IF(AF18<>"",AF18,"") -> 46303 | AZ18: =IF(AY18<>"",ROUND(AY18/(SI!$C$9*SI!$C$10),2),"") -> 138.19 | BA18: =IF(AND(AY18<>"",BH18<>""),ROUND(AY18*BH18/100,2),"") -> 37042.4 | BB18: =IF(AND(AZ18<>"",BH18<>""),ROUND(AZ18*BH18/100,2),"") -> 110.55 | BC18: =IF(AND(BB18<>"",Y18<>""),ROUND(BB18/Y18,3),"") -> 0.184 | BD18: =IF(AND(BB18<>"",T18<>""),ROUND(BB18/V18,3),"") -> 3.685 | BE18: =IF(AND(X18<>""),ROUND(X18/SI!$C$10,2),"") -> 134.63 | BF18: =IF(AND(BE18<>"",Y18<>""),ROUND(BE18/Y18,3),"") -> 0.224 | BG18: =IF(AND(BE18<>"",V18<>""),ROUND(BE18/V18,3),"") -> 4.488 | BH18: =IF(F18<>"",VLOOKUP(F18,DUTY_2025!A:O,15,FALSE),"") -> 80
A19: =IF(AND(F19<>"",H19<>"YES"),IF(A18<>"",A18,0)+1,A18) -> 15 | B19: =IF(AND(F19<>"",H19<>"YES"),IF(B18<>"",B18,A18)+1,"") -> 15 | C19: 1 | F19: 21069099 | G19: =IF(F19<>"",IFERROR(VLOOKUP(F19,DUTY_2025!A:I,6,FALSE),""),"") -> 0 | H19: NO | I19: =IF(F19<>"",IFERROR(VLOOKUP(F19,DUTY_2025!A:H,2,FALSE),""),"") -> HEALTH MIXES | J19: SAKTHI RASAM POWER 50G | K19: 0 | L19: 50 | M19: 1 | N19: 600 | O19: 5 | P19: =ROUND(13592.4*1.05,2) -> 14272.02 | Q19: INR | R19: NET | S19: =IF(AND(H19<>"YES",N19<>""),N19*L19/1000,"") -> 30 | T19: =IF(S19<>"",S19*1.1,"") -> 33 | U19: {=IF(AND(H19<>"YES",P19<>"",R19<>"",Q19<>""), _xlfn.SWITCH(Q19, "INR",_xlfn.SWITCH(R19,"KG",P19*S19,"CTN",P19,"UNIT",P19*N19,"NET",P19/M19,0), "USD",_xlfn.SWITCH(R19,"KG",P19*S19*SI!$C$10,"CTN",P19*SI!$C$10,"UNIT",P19*N19*SI!$C$10,"NET",P19*SI!$C$10/M19,0), "LKR",_xlfn.SWITCH(R19,"KG",P19*S19/SI!$C$9,"CTN",P19/SI!$C$9,"UNIT",P19*N19/SI!$C$9,"NET",P19/(M19*SI!$C$9),0), 0), "")} -> 14272.02 | V19: =IF(AND(S19<>"",M19<>"",N19<>""),S19*M19,"") -> 30 | W19: =IF(V19<>"",V19*1.1,"") -> 33 | X19: =IF(AND(U19<>"",M19<>""),U19*M19,"") -> 14272.02 | Y19: =IF(AND(H19<>"YES",M19<>"",N19<>""),IF(E19=1,(N19*M19)/2,N19*M19),"") -> 600 | Z19: =IF(AND(H19<>"yes",F19<>""),IFERROR(VLOOKUP(F19,DUTY_2025!A:F,5,FALSE),""),"") -> 570 | AA19: =IF(B19<>"",IF(AND(X19<>"", O19<>""),IF(ROUND(X19*100/(100+O19),0)=0,"",ROUND(X19*100/(100+O19),0)),""),"") -> 13592 | AB19: =IF(M19<>"",IF(AND(X19<>"",AA19<>""),X19-AA19,""),"") -> 680.02 | AC19: =IF(AA19<>"",ROUND(AA19*SI!$C$9,0),"") -> 47844 | AD19: =IF(AC19<>"",ROUND(AC19/(SI!$C$9*SI!$C$10),2),"") -> 142.79 | AE19: =IF(AND(X19<>""), ROUND((SI!$E$23)*(X19/SUM($X$5:$X$493)),0),"") -> 3717 | AF19: =IF(AND(AC19<>"",AE19<>""),ROUND(AC19+AE19,0),"") -> 51561 | AG19: =IF(AND(Z19<>"",V19<>""),Z19*V19,"") -> 17100 | AH19: =IF(AD19<>"",ROUND(AD19*10*SI!$C$9/2,0),"") -> 2513 | AI19: =IF(AND(X19<>""), ROUND((SI!$E$28)*(X19/SUM($X$5:$X$493)),0),"") -> 10560 | AJ19: =IF(AND(AG19<>"",AI19<>"",AH19<>""),AG19+AI19+AH19,"") -> 30173 | AK19: =IF(AND(AJ19<>"",Y19<>""),ROUND(AJ19/Y19,0),"") -> 50 | AL19: =IF(AND(AC19<>"",Y19<>""),ROUND(AF19/Y19,0),"") -> 86 | AM19: =IF(AND(AK19<>"",AL19<>""),AK19+AL19,"") -> 136 | AN19: =IF(AND(AF19<>"",AG19<>"",AH19<>"",AI19<>""),AF19+AG19+AH19+AI19,"") -> 81734 | AO19: =IF(AND(AM19<>"",P19<>""),ROUND((AM19*((100+SI!$C$11)/100)),0),"") -> 156 | AP19: =IF(AG19<>"",ROUND(AG19/SI!$C$9,2),"") -> 4857.95 | AQ19: =IF(AH19<>"",ROUND(AH19/SI!$C$9,2),"") -> 713.92 | AR19: =IF(AI19<>"",ROUND(AI19/SI!$C$9,2),"") -> 3000 | AS19: =IF(AND(AP19<>"",AR19<>"",AQ19<>""),AP19+AR19+AQ19,"") -> 8571.87 | AT19: =IF(AND(AS19<>"",Y19<>""),ROUND(AS19/Y19,2),"") -> 14.29 | AU19: =IF(AL19<>"",ROUND(AL19/SI!$C$9,2),"") -> 24.43 | AV19: =IF(AM19<>"",ROUND(AM19/SI!$C$9,2),"") -> 38.64 | AW19: =IF(AN19<>"",ROUND(AN19/SI!$C$9,2),"") -> 23219.89 | AX19: =IF(AO19<>"",ROUND(AO19/SI!$C$9,2),"") -> 44.32 | AY19: =IF(AF19<>"",AF19,"") -> 51561 | AZ19: =IF(AY19<>"",ROUND(AY19/(SI!$C$9*SI!$C$10),2),"") -> 153.88 | BA19: =IF(AND(AY19<>"",BH19<>""),ROUND(AY19*BH19/100,2),"") -> 41248.8 | BB19: =IF(AND(AZ19<>"",BH19<>""),ROUND(AZ19*BH19/100,2),"") -> 123.1 | BC19: =IF(AND(BB19<>"",Y19<>""),ROUND(BB19/Y19,3),"") -> 0.205 | BD19: =IF(AND(BB19<>"",T19<>""),ROUND(BB19/V19,3),"") -> 4.103 | BE19: =IF(AND(X19<>""),ROUND(X19/SI!$C$10,2),"") -> 149.93 | BF19: =IF(AND(BE19<>"",Y19<>""),ROUND(BE19/Y19,3),"") -> 0.25 | BG19: =IF(AND(BE19<>"",V19<>""),ROUND(BE19/V19,3),"") -> 4.998 | BH19: =IF(F19<>"",VLOOKUP(F19,DUTY_2025!A:O,15,FALSE),"") -> 80
A20: =IF(AND(F20<>"",H20<>"YES"),IF(A19<>"",A19,0)+1,A19) -> 16 | B20: =IF(AND(F20<>"",H20<>"YES"),IF(B19<>"",B19,A19)+1,"") -> 16 | C20: 1 | F20: 21069099 | G20: =IF(F20<>"",IFERROR(VLOOKUP(F20,DUTY_2025!A:I,6,FALSE),""),"") -> 0 | H20: NO | I20: =IF(F20<>"",IFERROR(VLOOKUP(F20,DUTY_2025!A:H,2,FALSE),""),"") -> HEALTH MIXES | J20: SAKTHI CURRY MASAL POWDER 50G | K20: 0 | L20: 50 | M20: 1 | N20: 600 | O20: 5 | P20: =ROUND(11928*1.05,2) -> 12524.4 | Q20: INR | R20: NET | S20: =IF(AND(H20<>"YES",N20<>""),N20*L20/1000,"") -> 30 | T20: =IF(S20<>"",S20*1.1,"") -> 33 | U20: {=IF(AND(H20<>"YES",P20<>"",R20<>"",Q20<>""), _xlfn.SWITCH(Q20, "INR",_xlfn.SWITCH(R20,"KG",P20*S20,"CTN",P20,"UNIT",P20*N20,"NET",P20/M20,0), "USD",_xlfn.SWITCH(R20,"KG",P20*S20*SI!$C$10,"CTN",P20*SI!$C$10,"UNIT",P20*N20*SI!$C$10,"NET",P20*SI!$C$10/M20,0), "LKR",_xlfn.SWITCH(R20,"KG",P20*S20/SI!$C$9,"CTN",P20/SI!$C$9,"UNIT",P20*N20/SI!$C$9,"NET",P20/(M20*SI!$C$9),0), 0), "")} -> 12524.4 | V20: =IF(AND(S20<>"",M20<>"",N20<>""),S20*M20,"") -> 30 | W20: =IF(V20<>"",V20*1.1,"") -> 33 | X20: =IF(AND(U20<>"",M20<>""),U20*M20,"") -> 12524.4 | Y20: =IF(AND(H20<>"YES",M20<>"",N20<>""),IF(E20=1,(N20*M20)/2,N20*M20),"") -> 600 | Z20: =IF(AND(H20<>"yes",F20<>""),IFERROR(VLOOKUP(F20,DUTY_2025!A:F,5,FALSE),""),"") -> 570 | AA20: =IF(B20<>"",IF(AND(X20<>"", O20<>""),IF(ROUND(X20*100/(100+O20),0)=0,"",ROUND(X20*100/(100+O20),0)),""),"") -> 11928 | AB20: =IF(M20<>"",IF(AND(X20<>"",AA20<>""),X20-AA20,""),"") -> 596.4 | AC20: =IF(AA20<>"",ROUND(AA20*SI!$C$9,0),"") -> 41987 | AD20: =IF(AC20<>"",ROUND(AC20/(SI!$C$9*SI!$C$10),2),"") -> 125.31 | AE20: =IF(AND(X20<>""), ROUND((SI!$E$23)*(X20/SUM($X$5:$X$493)),0),"") -> 3262 | AF20: =IF(AND(AC20<>"",AE20<>""),ROUND(AC20+AE20,0),"") -> 45249 | AG20: =IF(AND(Z20<>"",V20<>""),Z20*V20,"") -> 17100 | AH20: =IF(AD20<>"",ROUND(AD20*10*SI!$C$9/2,0),"") -> 2205 | AI20: =IF(AND(X20<>""), ROUND((SI!$E$28)*(X20/SUM($X$5:$X$493)),0),"") -> 9267 | AJ20: =IF(AND(AG20<>"",AI20<>"",AH20<>""),AG20+AI20+AH20,"") -> 28572 | AK20: =IF(AND(AJ20<>"",Y20<>""),ROUND(AJ20/Y20,0),"") -> 48 | AL20: =IF(AND(AC20<>"",Y20<>""),ROUND(AF20/Y20,0),"") -> 75 | AM20: =IF(AND(AK20<>"",AL20<>""),AK20+AL20,"") -> 123 | AN20: =IF(AND(AF20<>"",AG20<>"",AH20<>"",AI20<>""),AF20+AG20+AH20+AI20,"") -> 73821 | AO20: =IF(AND(AM20<>"",P20<>""),ROUND((AM20*((100+SI!$C$11)/100)),0),"") -> 141 | AP20: =IF(AG20<>"",ROUND(AG20/SI!$C$9,2),"") -> 4857.95 | AQ20: =IF(AH20<>"",ROUND(AH20/SI!$C$9,2),"") -> 626.42 | AR20: =IF(AI20<>"",ROUND(AI20/SI!$C$9,2),"") -> 2632.67 | AS20: =IF(AND(AP20<>"",AR20<>"",AQ20<>""),AP20+AR20+AQ20,"") -> 8117.04 | AT20: =IF(AND(AS20<>"",Y20<>""),ROUND(AS20/Y20,2),"") -> 13.53 | AU20: =IF(AL20<>"",ROUND(AL20/SI!$C$9,2),"") -> 21.31 | AV20: =IF(AM20<>"",ROUND(AM20/SI!$C$9,2),"") -> 34.94 | AW20: =IF(AN20<>"",ROUND(AN20/SI!$C$9,2),"") -> 20971.88 | AX20: =IF(AO20<>"",ROUND(AO20/SI!$C$9,2),"") -> 40.06 | AY20: =IF(AF20<>"",AF20,"") -> 45249 | AZ20: =IF(AY20<>"",ROUND(AY20/(SI!$C$9*SI!$C$10),2),"") -> 135.04 | BA20: =IF(AND(AY20<>"",BH20<>""),ROUND(AY20*BH20/100,2),"") -> 36199.2 | BB20: =IF(AND(AZ20<>"",BH20<>""),ROUND(AZ20*BH20/100,2),"") -> 108.03 | BC20: =IF(AND(BB20<>"",Y20<>""),ROUND(BB20/Y20,3),"") -> 0.18 | BD20: =IF(AND(BB20<>"",T20<>""),ROUND(BB20/V20,3),"") -> 3.601 | BE20: =IF(AND(X20<>""),ROUND(X20/SI!$C$10,2),"") -> 131.57 | BF20: =IF(AND(BE20<>"",Y20<>""),ROUND(BE20/Y20,3),"") -> 0.219 | BG20: =IF(AND(BE20<>"",V20<>""),ROUND(BE20/V20,3),"") -> 4.386 | BH20: =IF(F20<>"",VLOOKUP(F20,DUTY_2025!A:O,15,FALSE),"") -> 80
A21: =IF(AND(F21<>"",H21<>"YES"),IF(A20<>"",A20,0)+1,A20) -> 17 | B21: =IF(AND(F21<>"",H21<>"YES"),IF(B20<>"",B20,A20)+1,"") -> 17 | C21: 1 | F21: 21069099 | G21: =IF(F21<>"",IFERROR(VLOOKUP(F21,DUTY_2025!A:I,6,FALSE),""),"") -> 0 | H21: NO | I21: =IF(F21<>"",IFERROR(VLOOKUP(F21,DUTY_2025!A:H,2,FALSE),""),"") -> HEALTH MIXES | J21: SAKTHI FISH CURRY MASALA 50G | K21: 0 | L21: 50 | M21: 1 | N21: 600 | O21: 5 | P21: =ROUND(9292.8*1.05,2) -> 9757.44 | Q21: INR | R21: NET | S21: =IF(AND(H21<>"YES",N21<>""),N21*L21/1000,"") -> 30 | T21: =IF(S21<>"",S21*1.1,"") -> 33 | U21: {=IF(AND(H21<>"YES",P21<>"",R21<>"",Q21<>""), _xlfn.SWITCH(Q21, "INR",_xlfn.SWITCH(R21,"KG",P21*S21,"CTN",P21,"UNIT",P21*N21,"NET",P21/M21,0), "USD",_xlfn.SWITCH(R21,"KG",P21*S21*SI!$C$10,"CTN",P21*SI!$C$10,"UNIT",P21*N21*SI!$C$10,"NET",P21*SI!$C$10/M21,0), "LKR",_xlfn.SWITCH(R21,"KG",P21*S21/SI!$C$9,"CTN",P21/SI!$C$9,"UNIT",P21*N21/SI!$C$9,"NET",P21/(M21*SI!$C$9),0), 0), "")} -> 9757.44 | V21: =IF(AND(S21<>"",M21<>"",N21<>""),S21*M21,"") -> 30 | W21: =IF(V21<>"",V21*1.1,"") -> 33 | X21: =IF(AND(U21<>"",M21<>""),U21*M21,"") -> 9757.44 | Y21: =IF(AND(H21<>"YES",M21<>"",N21<>""),IF(E21=1,(N21*M21)/2,N21*M21),"") -> 600 | Z21: =IF(AND(H21<>"yes",F21<>""),IFERROR(VLOOKUP(F21,DUTY_2025!A:F,5,FALSE),""),"") -> 570 | AA21: =IF(B21<>"",IF(AND(X21<>"", O21<>""),IF(ROUND(X21*100/(100+O21),0)=0,"",ROUND(X21*100/(100+O21),0)),""),"") -> 9293 | AB21: =IF(M21<>"",IF(AND(X21<>"",AA21<>""),X21-AA21,""),"") -> 464.44 | AC21: =IF(AA21<>"",ROUND(AA21*SI!$C$9,0),"") -> 32711 | AD21: =IF(AC21<>"",ROUND(AC21/(SI!$C$9*SI!$C$10),2),"") -> 97.62 | AE21: =IF(AND(X21<>""), ROUND((SI!$E$23)*(X21/SUM($X$5:$X$493)),0),"") -> 2541 | AF21: =IF(AND(AC21<>"",AE21<>""),ROUND(AC21+AE21,0),"") -> 35252 | AG21: =IF(AND(Z21<>"",V21<>""),Z21*V21,"") -> 17100 | AH21: =IF(AD21<>"",ROUND(AD21*10*SI!$C$9/2,0),"") -> 1718 | AI21: =IF(AND(X21<>""), ROUND((SI!$E$28)*(X21/SUM($X$5:$X$493)),0),"") -> 7220 | AJ21: =IF(AND(AG21<>"",AI21<>"",AH21<>""),AG21+AI21+AH21,"") -> 26038 | AK21: =IF(AND(AJ21<>"",Y21<>""),ROUND(AJ21/Y21,0),"") -> 43 | AL21: =IF(AND(AC21<>"",Y21<>""),ROUND(AF21/Y21,0),"") -> 59 | AM21: =IF(AND(AK21<>"",AL21<>""),AK21+AL21,"") -> 102 | AN21: =IF(AND(AF21<>"",AG21<>"",AH21<>"",AI21<>""),AF21+AG21+AH21+AI21,"") -> 61290 | AO21: =IF(AND(AM21<>"",P21<>""),ROUND((AM21*((100+SI!$C$11)/100)),0),"") -> 117 | AP21: =IF(AG21<>"",ROUND(AG21/SI!$C$9,2),"") -> 4857.95 | AQ21: =IF(AH21<>"",ROUND(AH21/SI!$C$9,2),"") -> 488.07 | AR21: =IF(AI21<>"",ROUND(AI21/SI!$C$9,2),"") -> 2051.14 | AS21: =IF(AND(AP21<>"",AR21<>"",AQ21<>""),AP21+AR21+AQ21,"") -> 7397.16 | AT21: =IF(AND(AS21<>"",Y21<>""),ROUND(AS21/Y21,2),"") -> 12.33 | AU21: =IF(AL21<>"",ROUND(AL21/SI!$C$9,2),"") -> 16.76 | AV21: =IF(AM21<>"",ROUND(AM21/SI!$C$9,2),"") -> 28.98 | AW21: =IF(AN21<>"",ROUND(AN21/SI!$C$9,2),"") -> 17411.93 | AX21: =IF(AO21<>"",ROUND(AO21/SI!$C$9,2),"") -> 33.24 | AY21: =IF(AF21<>"",AF21,"") -> 35252 | AZ21: =IF(AY21<>"",ROUND(AY21/(SI!$C$9*SI!$C$10),2),"") -> 105.21 | BA21: =IF(AND(AY21<>"",BH21<>""),ROUND(AY21*BH21/100,2),"") -> 28201.6 | BB21: =IF(AND(AZ21<>"",BH21<>""),ROUND(AZ21*BH21/100,2),"") -> 84.17 | BC21: =IF(AND(BB21<>"",Y21<>""),ROUND(BB21/Y21,3),"") -> 0.14 | BD21: =IF(AND(BB21<>"",T21<>""),ROUND(BB21/V21,3),"") -> 2.806 | BE21: =IF(AND(X21<>""),ROUND(X21/SI!$C$10,2),"") -> 102.5 | BF21: =IF(AND(BE21<>"",Y21<>""),ROUND(BE21/Y21,3),"") -> 0.171 | BG21: =IF(AND(BE21<>"",V21<>""),ROUND(BE21/V21,3),"") -> 3.417 | BH21: =IF(F21<>"",VLOOKUP(F21,DUTY_2025!A:O,15,FALSE),"") -> 80
A22: =IF(AND(F22<>"",H22<>"YES"),IF(A21<>"",A21,0)+1,A21) -> 18 | B22: =IF(AND(F22<>"",H22<>"YES"),IF(B21<>"",B21,A21)+1,"") -> 18 | C22: 1 | F22: 21069099 | G22: =IF(F22<>"",IFERROR(VLOOKUP(F22,DUTY_2025!A:I,6,FALSE),""),"") -> 0 | H22: NO | I22: =IF(F22<>"",IFERROR(VLOOKUP(F22,DUTY_2025!A:H,2,FALSE),""),"") -> HEALTH MIXES | J22: SAKTHI FISH FRY 50G | K22: 0 | L22: 50 | M22: 1 | N22: 600 | O22: 5 | P22: =ROUND(12898.8*1.05,2) -> 13543.74 | Q22: INR | R22: NET | S22: =IF(AND(H22<>"YES",N22<>""),N22*L22/1000,"") -> 30 | T22: =IF(S22<>"",S22*1.1,"") -> 33 | U22: {=IF(AND(H22<>"YES",P22<>"",R22<>"",Q22<>""), _xlfn.SWITCH(Q22, "INR",_xlfn.SWITCH(R22,"KG",P22*S22,"CTN",P22,"UNIT",P22*N22,"NET",P22/M22,0), "USD",_xlfn.SWITCH(R22,"KG",P22*S22*SI!$C$10,"CTN",P22*SI!$C$10,"UNIT",P22*N22*SI!$C$10,"NET",P22*SI!$C$10/M22,0), "LKR",_xlfn.SWITCH(R22,"KG",P22*S22/SI!$C$9,"CTN",P22/SI!$C$9,"UNIT",P22*N22/SI!$C$9,"NET",P22/(M22*SI!$C$9),0), 0), "")} -> 13543.74 | V22: =IF(AND(S22<>"",M22<>"",N22<>""),S22*M22,"") -> 30 | W22: =IF(V22<>"",V22*1.1,"") -> 33 | X22: =IF(AND(U22<>"",M22<>""),U22*M22,"") -> 13543.74 | Y22: =IF(AND(H22<>"YES",M22<>"",N22<>""),IF(E22=1,(N22*M22)/2,N22*M22),"") -> 600 | Z22: =IF(AND(H22<>"yes",F22<>""),IFERROR(VLOOKUP(F22,DUTY_2025!A:F,5,FALSE),""),"") -> 570 | AA22: =IF(B22<>"",IF(AND(X22<>"", O22<>""),IF(ROUND(X22*100/(100+O22),0)=0,"",ROUND(X22*100/(100+O22),0)),""),"") -> 12899 | AB22: =IF(M22<>"",IF(AND(X22<>"",AA22<>""),X22-AA22,""),"") -> 644.74 | AC22: =IF(AA22<>"",ROUND(AA22*SI!$C$9,0),"") -> 45404 | AD22: =IF(AC22<>"",ROUND(AC22/(SI!$C$9*SI!$C$10),2),"") -> 135.51 | AE22: =IF(AND(X22<>""), ROUND((SI!$E$23)*(X22/SUM($X$5:$X$493)),0),"") -> 3527 | AF22: =IF(AND(AC22<>"",AE22<>""),ROUND(AC22+AE22,0),"") -> 48931 | AG22: =IF(AND(Z22<>"",V22<>""),Z22*V22,"") -> 17100 | AH22: =IF(AD22<>"",ROUND(AD22*10*SI!$C$9/2,0),"") -> 2385 | AI22: =IF(AND(X22<>""), ROUND((SI!$E$28)*(X22/SUM($X$5:$X$493)),0),"") -> 10021 | AJ22: =IF(AND(AG22<>"",AI22<>"",AH22<>""),AG22+AI22+AH22,"") -> 29506 | AK22: =IF(AND(AJ22<>"",Y22<>""),ROUND(AJ22/Y22,0),"") -> 49 | AL22: =IF(AND(AC22<>"",Y22<>""),ROUND(AF22/Y22,0),"") -> 82 | AM22: =IF(AND(AK22<>"",AL22<>""),AK22+AL22,"") -> 131 | AN22: =IF(AND(AF22<>"",AG22<>"",AH22<>"",AI22<>""),AF22+AG22+AH22+AI22,"") -> 78437 | AO22: =IF(AND(AM22<>"",P22<>""),ROUND((AM22*((100+SI!$C$11)/100)),0),"") -> 151 | AP22: =IF(AG22<>"",ROUND(AG22/SI!$C$9,2),"") -> 4857.95 | AQ22: =IF(AH22<>"",ROUND(AH22/SI!$C$9,2),"") -> 677.56 | AR22: =IF(AI22<>"",ROUND(AI22/SI!$C$9,2),"") -> 2846.88 | AS22: =IF(AND(AP22<>"",AR22<>"",AQ22<>""),AP22+AR22+AQ22,"") -> 8382.39 | AT22: =IF(AND(AS22<>"",Y22<>""),ROUND(AS22/Y22,2),"") -> 13.97 | AU22: =IF(AL22<>"",ROUND(AL22/SI!$C$9,2),"") -> 23.3 | AV22: =IF(AM22<>"",ROUND(AM22/SI!$C$9,2),"") -> 37.22 | AW22: =IF(AN22<>"",ROUND(AN22/SI!$C$9,2),"") -> 22283.24 | AX22: =IF(AO22<>"",ROUND(AO22/SI!$C$9,2),"") -> 42.9 | AY22: =IF(AF22<>"",AF22,"") -> 48931 | AZ22: =IF(AY22<>"",ROUND(AY22/(SI!$C$9*SI!$C$10),2),"") -> 146.03 | BA22: =IF(AND(AY22<>"",BH22<>""),ROUND(AY22*BH22/100,2),"") -> 39144.8 | BB22: =IF(AND(AZ22<>"",BH22<>""),ROUND(AZ22*BH22/100,2),"") -> 116.82 | BC22: =IF(AND(BB22<>"",Y22<>""),ROUND(BB22/Y22,3),"") -> 0.195 | BD22: =IF(AND(BB22<>"",T22<>""),ROUND(BB22/V22,3),"") -> 3.894 | BE22: =IF(AND(X22<>""),ROUND(X22/SI!$C$10,2),"") -> 142.28 | BF22: =IF(AND(BE22<>"",Y22<>""),ROUND(BE22/Y22,3),"") -> 0.237 | BG22: =IF(AND(BE22<>"",V22<>""),ROUND(BE22/V22,3),"") -> 4.743 | BH22: =IF(F22<>"",VLOOKUP(F22,DUTY_2025!A:O,15,FALSE),"") -> 80
A23: =IF(AND(F23<>"",H23<>"YES"),IF(A22<>"",A22,0)+1,A22) -> 19 | B23: =IF(AND(F23<>"",H23<>"YES"),IF(B22<>"",B22,A22)+1,"") -> 19 | C23: 1 | F23: 21069099 | G23: =IF(F23<>"",IFERROR(VLOOKUP(F23,DUTY_2025!A:I,6,FALSE),""),"") -> 0 | H23: NO | I23: =IF(F23<>"",IFERROR(VLOOKUP(F23,DUTY_2025!A:H,2,FALSE),""),"") -> HEALTH MIXES | J23: SAKTHI IDLI CHILLI POWDER 50G | K23: 0 | L23: 50 | M23: 2 | N23: 600 | O23: 5 | P23: =ROUND(14979.6*1.05,2) -> 15728.58 | Q23: INR | R23: NET | S23: =IF(AND(H23<>"YES",N23<>""),N23*L23/1000,"") -> 30 | T23: =IF(S23<>"",S23*1.1,"") -> 33 | U23: {=IF(AND(H23<>"YES",P23<>"",R23<>"",Q23<>""), _xlfn.SWITCH(Q23, "INR",_xlfn.SWITCH(R23,"KG",P23*S23,"CTN",P23,"UNIT",P23*N23,"NET",P23/M23,0), "USD",_xlfn.SWITCH(R23,"KG",P23*S23*SI!$C$10,"CTN",P23*SI!$C$10,"UNIT",P23*N23*SI!$C$10,"NET",P23*SI!$C$10/M23,0), "LKR",_xlfn.SWITCH(R23,"KG",P23*S23/SI!$C$9,"CTN",P23/SI!$C$9,"UNIT",P23*N23/SI!$C$9,"NET",P23/(M23*SI!$C$9),0), 0), "")} -> 7864.29 | V23: =IF(AND(S23<>"",M23<>"",N23<>""),S23*M23,"") -> 60 | W23: =IF(V23<>"",V23*1.1,"") -> 66 | X23: =IF(AND(U23<>"",M23<>""),U23*M23,"") -> 15728.58 | Y23: =IF(AND(H23<>"YES",M23<>"",N23<>""),IF(E23=1,(N23*M23)/2,N23*M23),"") -> 1200 | Z23: =IF(AND(H23<>"yes",F23<>""),IFERROR(VLOOKUP(F23,DUTY_2025!A:F,5,FALSE),""),"") -> 570 | AA23: =IF(B23<>"",IF(AND(X23<>"", O23<>""),IF(ROUND(X23*100/(100+O23),0)=0,"",ROUND(X23*100/(100+O23),0)),""),"") -> 14980 | AB23: =IF(M23<>"",IF(AND(X23<>"",AA23<>""),X23-AA23,""),"") -> 748.58 | AC23: =IF(AA23<>"",ROUND(AA23*SI!$C$9,0),"") -> 52730 | AD23: =IF(AC23<>"",ROUND(AC23/(SI!$C$9*SI!$C$10),2),"") -> 157.37 | AE23: =IF(AND(X23<>""), ROUND((SI!$E$23)*(X23/SUM($X$5:$X$493)),0),"") -> 4096 | AF23: =IF(AND(AC23<>"",AE23<>""),ROUND(AC23+AE23,0),"") -> 56826 | AG23: =IF(AND(Z23<>"",V23<>""),Z23*V23,"") -> 34200 | AH23: =IF(AD23<>"",ROUND(AD23*10*SI!$C$9/2,0),"") -> 2770 | AI23: =IF(AND(X23<>""), ROUND((SI!$E$28)*(X23/SUM($X$5:$X$493)),0),"") -> 11638 | AJ23: =IF(AND(AG23<>"",AI23<>"",AH23<>""),AG23+AI23+AH23,"") -> 48608 | AK23: =IF(AND(AJ23<>"",Y23<>""),ROUND(AJ23/Y23,0),"") -> 41 | AL23: =IF(AND(AC23<>"",Y23<>""),ROUND(AF23/Y23,0),"") -> 47 | AM23: =IF(AND(AK23<>"",AL23<>""),AK23+AL23,"") -> 88 | AN23: =IF(AND(AF23<>"",AG23<>"",AH23<>"",AI23<>""),AF23+AG23+AH23+AI23,"") -> 105434 | AO23: =IF(AND(AM23<>"",P23<>""),ROUND((AM23*((100+SI!$C$11)/100)),0),"") -> 101 | AP23: =IF(AG23<>"",ROUND(AG23/SI!$C$9,2),"") -> 9715.91 | AQ23: =IF(AH23<>"",ROUND(AH23/SI!$C$9,2),"") -> 786.93 | AR23: =IF(AI23<>"",ROUND(AI23/SI!$C$9,2),"") -> 3306.25 | AS23: =IF(AND(AP23<>"",AR23<>"",AQ23<>""),AP23+AR23+AQ23,"") -> 13809.09 | AT23: =IF(AND(AS23<>"",Y23<>""),ROUND(AS23/Y23,2),"") -> 11.51 | AU23: =IF(AL23<>"",ROUND(AL23/SI!$C$9,2),"") -> 13.35 | AV23: =IF(AM23<>"",ROUND(AM23/SI!$C$9,2),"") -> 25 | AW23: =IF(AN23<>"",ROUND(AN23/SI!$C$9,2),"") -> 29952.84 | AX23: =IF(AO23<>"",ROUND(AO23/SI!$C$9,2),"") -> 28.69 | AY23: =IF(AF23<>"",AF23,"") -> 56826 | AZ23: =IF(AY23<>"",ROUND(AY23/(SI!$C$9*SI!$C$10),2),"") -> 169.6 | BA23: =IF(AND(AY23<>"",BH23<>""),ROUND(AY23*BH23/100,2),"") -> 45460.8 | BB23: =IF(AND(AZ23<>"",BH23<>""),ROUND(AZ23*BH23/100,2),"") -> 135.68 | BC23: =IF(AND(BB23<>"",Y23<>""),ROUND(BB23/Y23,3),"") -> 0.113 | BD23: =IF(AND(BB23<>"",T23<>""),ROUND(BB23/V23,3),"") -> 2.261 | BE23: =IF(AND(X23<>""),ROUND(X23/SI!$C$10,2),"") -> 165.23 | BF23: =IF(AND(BE23<>"",Y23<>""),ROUND(BE23/Y23,3),"") -> 0.138 | BG23: =IF(AND(BE23<>"",V23<>""),ROUND(BE23/V23,3),"") -> 2.754 | BH23: =IF(F23<>"",VLOOKUP(F23,DUTY_2025!A:O,15,FALSE),"") -> 80
A24: =IF(AND(F24<>"",H24<>"YES"),IF(A23<>"",A23,0)+1,A23) -> 20 | B24: =IF(AND(F24<>"",H24<>"YES"),IF(B23<>"",B23,A23)+1,"") -> 20 | C24: 1 | F24: 09092200 | G24: =IF(F24<>"",IFERROR(VLOOKUP(F24,DUTY_2025!A:I,6,FALSE),""),"") -> S | H24: NO | I24: =IF(F24<>"",IFERROR(VLOOKUP(F24,DUTY_2025!A:H,2,FALSE),""),"") -> DHANIYA POWDER | J24: SAKTHI CORIANDER POWDER 500G | K24: 0 | L24: 500 | M24: 42 | N24: 60 | O24: 5 | P24: =ROUND(306406.8*1.05,2) -> 321727.14 | Q24: INR | R24: NET | S24: =IF(AND(H24<>"YES",N24<>""),N24*L24/1000,"") -> 30 | T24: =IF(S24<>"",S24*1.1,"") -> 33 | U24: {=IF(AND(H24<>"YES",P24<>"",R24<>"",Q24<>""), _xlfn.SWITCH(Q24, "INR",_xlfn.SWITCH(R24,"KG",P24*S24,"CTN",P24,"UNIT",P24*N24,"NET",P24/M24,0), "USD",_xlfn.SWITCH(R24,"KG",P24*S24*SI!$C$10,"CTN",P24*SI!$C$10,"UNIT",P24*N24*SI!$C$10,"NET",P24*SI!$C$10/M24,0), "LKR",_xlfn.SWITCH(R24,"KG",P24*S24/SI!$C$9,"CTN",P24/SI!$C$9,"UNIT",P24*N24/SI!$C$9,"NET",P24/(M24*SI!$C$9),0), 0), "")} -> 7660.17 | V24: =IF(AND(S24<>"",M24<>"",N24<>""),S24*M24,"") -> 1260 | W24: =IF(V24<>"",V24*1.1,"") -> 1386 | X24: =IF(AND(U24<>"",M24<>""),U24*M24,"") -> 321727.14 | Y24: =IF(AND(H24<>"YES",M24<>"",N24<>""),IF(E24=1,(N24*M24)/2,N24*M24),"") -> 2520 | Z24: =IF(AND(H24<>"yes",F24<>""),IFERROR(VLOOKUP(F24,DUTY_2025!A:F,5,FALSE),""),"") -> 52 | AA24: =IF(B24<>"",IF(AND(X24<>"", O24<>""),IF(ROUND(X24*100/(100+O24),0)=0,"",ROUND(X24*100/(100+O24),0)),""),"") -> 306407 | AB24: =IF(M24<>"",IF(AND(X24<>"",AA24<>""),X24-AA24,""),"") -> 15320.14 | AC24: =IF(AA24<>"",ROUND(AA24*SI!$C$9,0),"") -> 1078553 | AD24: =IF(AC24<>"",ROUND(AC24/(SI!$C$9*SI!$C$10),2),"") -> 3218.9 | AE24: =IF(AND(X24<>""), ROUND((SI!$E$23)*(X24/SUM($X$5:$X$493)),0),"") -> 83792 | AF24: =IF(AND(AC24<>"",AE24<>""),ROUND(AC24+AE24,0),"") -> 1162345 | AG24: =IF(AND(Z24<>"",V24<>""),Z24*V24,"") -> 65520 | AH24: =IF(AD24<>"",ROUND(AD24*10*SI!$C$9/2,0),"") -> 56653 | AI24: =IF(AND(X24<>""), ROUND((SI!$E$28)*(X24/SUM($X$5:$X$493)),0),"") -> 238046 | AJ24: =IF(AND(AG24<>"",AI24<>"",AH24<>""),AG24+AI24+AH24,"") -> 360219 | AK24: =IF(AND(AJ24<>"",Y24<>""),ROUND(AJ24/Y24,0),"") -> 143 | AL24: =IF(AND(AC24<>"",Y24<>""),ROUND(AF24/Y24,0),"") -> 461 | AM24: =IF(AND(AK24<>"",AL24<>""),AK24+AL24,"") -> 604 | AN24: =IF(AND(AF24<>"",AG24<>"",AH24<>"",AI24<>""),AF24+AG24+AH24+AI24,"") -> 1522564 | AO24: =IF(AND(AM24<>"",P24<>""),ROUND((AM24*((100+SI!$C$11)/100)),0),"") -> 695 | AP24: =IF(AG24<>"",ROUND(AG24/SI!$C$9,2),"") -> 18613.64 | AQ24: =IF(AH24<>"",ROUND(AH24/SI!$C$9,2),"") -> 16094.6 | AR24: =IF(AI24<>"",ROUND(AI24/SI!$C$9,2),"") -> 67626.7 | AS24: =IF(AND(AP24<>"",AR24<>"",AQ24<>""),AP24+AR24+AQ24,"") -> 102334.94 | AT24: =IF(AND(AS24<>"",Y24<>""),ROUND(AS24/Y24,2),"") -> 40.61 | AU24: =IF(AL24<>"",ROUND(AL24/SI!$C$9,2),"") -> 130.97 | AV24: =IF(AM24<>"",ROUND(AM24/SI!$C$9,2),"") -> 171.59 | AW24: =IF(AN24<>"",ROUND(AN24/SI!$C$9,2),"") -> 432546.59 | AX24: =IF(AO24<>"",ROUND(AO24/SI!$C$9,2),"") -> 197.44 | AY24: =IF(AF24<>"",AF24,"") -> 1162345 | AZ24: =IF(AY24<>"",ROUND(AY24/(SI!$C$9*SI!$C$10),2),"") -> 3468.97 | BA24: =IF(AND(AY24<>"",BH24<>""),ROUND(AY24*BH24/100,2),"") -> 1162345 | BB24: =IF(AND(AZ24<>"",BH24<>""),ROUND(AZ24*BH24/100,2),"") -> 3468.97 | BC24: =IF(AND(BB24<>"",Y24<>""),ROUND(BB24/Y24,3),"") -> 1.377 | BD24: =IF(AND(BB24<>"",T24<>""),ROUND(BB24/V24,3),"") -> 2.753 | BE24: =IF(AND(X24<>""),ROUND(X24/SI!$C$10,2),"") -> 3379.84 | BF24: =IF(AND(BE24<>"",Y24<>""),ROUND(BE24/Y24,3),"") -> 1.341 | BG24: =IF(AND(BE24<>"",V24<>""),ROUND(BE24/V24,3),"") -> 2.682 | BH24: =IF(F24<>"",VLOOKUP(F24,DUTY_2025!A:O,15,FALSE),"") -> 100
A25: =IF(AND(F25<>"",H25<>"YES"),IF(A24<>"",A24,0)+1,A24) -> 21 | B25: =IF(AND(F25<>"",H25<>"YES"),IF(B24<>"",B24,A24)+1,"") -> 21 | C25: 1 | F25: 09042190 | G25: =IF(F25<>"",IFERROR(VLOOKUP(F25,DUTY_2025!A:I,6,FALSE),""),"") -> 0 | H25: NO | I25: =IF(F25<>"",IFERROR(VLOOKUP(F25,DUTY_2025!A:H,2,FALSE),""),"") -> CHILLIES- OTHER | J25: SAKTHI CHILLI POWDER 500G | K25: 0 | L25: 500 | M25: 15 | N25: 60 | O25: 5 | P25: =ROUND(126081*1.05,2) -> 132385.05 | Q25: INR | R25: NET | S25: =IF(AND(H25<>"YES",N25<>""),N25*L25/1000,"") -> 30 | T25: =IF(S25<>"",S25*1.1,"") -> 33 | U25: {=IF(AND(H25<>"YES",P25<>"",R25<>"",Q25<>""), _xlfn.SWITCH(Q25, "INR",_xlfn.SWITCH(R25,"KG",P25*S25,"CTN",P25,"UNIT",P25*N25,"NET",P25/M25,0), "USD",_xlfn.SWITCH(R25,"KG",P25*S25*SI!$C$10,"CTN",P25*SI!$C$10,"UNIT",P25*N25*SI!$C$10,"NET",P25*SI!$C$10/M25,0), "LKR",_xlfn.SWITCH(R25,"KG",P25*S25/SI!$C$9,"CTN",P25/SI!$C$9,"UNIT",P25*N25/SI!$C$9,"NET",P25/(M25*SI!$C$9),0), 0), "")} -> 8825.67 | V25: =IF(AND(S25<>"",M25<>"",N25<>""),S25*M25,"") -> 450 | W25: =IF(V25<>"",V25*1.1,"") -> 495 | X25: =IF(AND(U25<>"",M25<>""),U25*M25,"") -> 132385.05 | Y25: =IF(AND(H25<>"YES",M25<>"",N25<>""),IF(E25=1,(N25*M25)/2,N25*M25),"") -> 900 | Z25: =IF(AND(H25<>"yes",F25<>""),IFERROR(VLOOKUP(F25,DUTY_2025!A:F,5,FALSE),""),"") -> 705 | AA25: =IF(B25<>"",IF(AND(X25<>"", O25<>""),IF(ROUND(X25*100/(100+O25),0)=0,"",ROUND(X25*100/(100+O25),0)),""),"") -> 126081 | AB25: =IF(M25<>"",IF(AND(X25<>"",AA25<>""),X25-AA25,""),"") -> 6304.05 | AC25: =IF(AA25<>"",ROUND(AA25*SI!$C$9,0),"") -> 443805 | AD25: =IF(AC25<>"",ROUND(AC25/(SI!$C$9*SI!$C$10),2),"") -> 1324.52 | AE25: =IF(AND(X25<>""), ROUND((SI!$E$23)*(X25/SUM($X$5:$X$493)),0),"") -> 34479 | AF25: =IF(AND(AC25<>"",AE25<>""),ROUND(AC25+AE25,0),"") -> 478284 | AG25: =IF(AND(Z25<>"",V25<>""),Z25*V25,"") -> 317250 | AH25: =IF(AD25<>"",ROUND(AD25*10*SI!$C$9/2,0),"") -> 23312 | AI25: =IF(AND(X25<>""), ROUND((SI!$E$28)*(X25/SUM($X$5:$X$493)),0),"") -> 97952 | AJ25: =IF(AND(AG25<>"",AI25<>"",AH25<>""),AG25+AI25+AH25,"") -> 438514 | AK25: =IF(AND(AJ25<>"",Y25<>""),ROUND(AJ25/Y25,0),"") -> 487 | AL25: =IF(AND(AC25<>"",Y25<>""),ROUND(AF25/Y25,0),"") -> 531 | AM25: =IF(AND(AK25<>"",AL25<>""),AK25+AL25,"") -> 1018 | AN25: =IF(AND(AF25<>"",AG25<>"",AH25<>"",AI25<>""),AF25+AG25+AH25+AI25,"") -> 916798 | AO25: =IF(AND(AM25<>"",P25<>""),ROUND((AM25*((100+SI!$C$11)/100)),0),"") -> 1171 | AP25: =IF(AG25<>"",ROUND(AG25/SI!$C$9,2),"") -> 90127.84 | AQ25: =IF(AH25<>"",ROUND(AH25/SI!$C$9,2),"") -> 6622.73 | AR25: =IF(AI25<>"",ROUND(AI25/SI!$C$9,2),"") -> 27827.27 | AS25: =IF(AND(AP25<>"",AR25<>"",AQ25<>""),AP25+AR25+AQ25,"") -> 124577.84 | AT25: =IF(AND(AS25<>"",Y25<>""),ROUND(AS25/Y25,2),"") -> 138.42 | AU25: =IF(AL25<>"",ROUND(AL25/SI!$C$9,2),"") -> 150.85 | AV25: =IF(AM25<>"",ROUND(AM25/SI!$C$9,2),"") -> 289.2 | AW25: =IF(AN25<>"",ROUND(AN25/SI!$C$9,2),"") -> 260453.98 | AX25: =IF(AO25<>"",ROUND(AO25/SI!$C$9,2),"") -> 332.67 | AY25: =IF(AF25<>"",AF25,"") -> 478284 | AZ25: =IF(AY25<>"",ROUND(AY25/(SI!$C$9*SI!$C$10),2),"") -> 1427.42 | BA25: =IF(AND(AY25<>"",BH25<>""),ROUND(AY25*BH25/100,2),"") -> 382627.2 | BB25: =IF(AND(AZ25<>"",BH25<>""),ROUND(AZ25*BH25/100,2),"") -> 1141.94 | BC25: =IF(AND(BB25<>"",Y25<>""),ROUND(BB25/Y25,3),"") -> 1.269 | BD25: =IF(AND(BB25<>"",T25<>""),ROUND(BB25/V25,3),"") -> 2.538 | BE25: =IF(AND(X25<>""),ROUND(X25/SI!$C$10,2),"") -> 1390.75 | BF25: =IF(AND(BE25<>"",Y25<>""),ROUND(BE25/Y25,3),"") -> 1.545 | BG25: =IF(AND(BE25<>"",V25<>""),ROUND(BE25/V25,3),"") -> 3.091 | BH25: =IF(F25<>"",VLOOKUP(F25,DUTY_2025!A:O,15,FALSE),"") -> 80
A26: =IF(AND(F26<>"",H26<>"YES"),IF(A25<>"",A25,0)+1,A25) -> 22 | B26: =IF(AND(F26<>"",H26<>"YES"),IF(B25<>"",B25,A25)+1,"") -> 22 | C26: 1 | F26: 11042200 | G26: =IF(F26<>"",IFERROR(VLOOKUP(F26,DUTY_2025!A:I,6,FALSE),""),"") -> 0 | H26: NO | I26: =IF(F26<>"",IFERROR(VLOOKUP(F26,DUTY_2025!A:H,2,FALSE),""),"") -> OATS | J26: OATS 400 G | K26: 0 | L26: 400 | M26: 10 | N26: 24 | O26: 5 | P26: 15600 | Q26: INR | R26: NET | S26: =IF(AND(H26<>"YES",N26<>""),N26*L26/1000,"") -> 9.6 | T26: =IF(S26<>"",S26*1.1,"") -> 10.56 | U26: {=IF(AND(H26<>"YES",P26<>"",R26<>"",Q26<>""), _xlfn.SWITCH(Q26, "INR",_xlfn.SWITCH(R26,"KG",P26*S26,"CTN",P26,"UNIT",P26*N26,"NET",P26/M26,0), "USD",_xlfn.SWITCH(R26,"KG",P26*S26*SI!$C$10,"CTN",P26*SI!$C$10,"UNIT",P26*N26*SI!$C$10,"NET",P26*SI!$C$10/M26,0), "LKR",_xlfn.SWITCH(R26,"KG",P26*S26/SI!$C$9,"CTN",P26/SI!$C$9,"UNIT",P26*N26/SI!$C$9,"NET",P26/(M26*SI!$C$9),0), 0), "")} -> 1560 | V26: =IF(AND(S26<>"",M26<>"",N26<>""),S26*M26,"") -> 96 | W26: =IF(V26<>"",V26*1.1,"") -> 105.6 | X26: =IF(AND(U26<>"",M26<>""),U26*M26,"") -> 15600 | Y26: =IF(AND(H26<>"YES",M26<>"",N26<>""),IF(E26=1,(N26*M26)/2,N26*M26),"") -> 240 | Z26: =IF(AND(H26<>"yes",F26<>""),IFERROR(VLOOKUP(F26,DUTY_2025!A:F,5,FALSE),""),"") -> 441 | AA26: =IF(B26<>"",IF(AND(X26<>"", O26<>""),IF(ROUND(X26*100/(100+O26),0)=0,"",ROUND(X26*100/(100+O26),0)),""),"") -> 14857 | AB26: =IF(M26<>"",IF(AND(X26<>"",AA26<>""),X26-AA26,""),"") -> 743 | AC26: =IF(AA26<>"",ROUND(AA26*SI!$C$9,0),"") -> 52297 | AD26: =IF(AC26<>"",ROUND(AC26/(SI!$C$9*SI!$C$10),2),"") -> 156.08 | AE26: =IF(AND(X26<>""), ROUND((SI!$E$23)*(X26/SUM($X$5:$X$493)),0),"") -> 4063 | AF26: =IF(AND(AC26<>"",AE26<>""),ROUND(AC26+AE26,0),"") -> 56360 | AG26: =IF(AND(Z26<>"",V26<>""),Z26*V26,"") -> 42336 | AH26: =IF(AD26<>"",ROUND(AD26*10*SI!$C$9/2,0),"") -> 2747 | AI26: =IF(AND(X26<>""), ROUND((SI!$E$28)*(X26/SUM($X$5:$X$493)),0),"") -> 11542 | AJ26: =IF(AND(AG26<>"",AI26<>"",AH26<>""),AG26+AI26+AH26,"") -> 56625 | AK26: =IF(AND(AJ26<>"",Y26<>""),ROUND(AJ26/Y26,0),"") -> 236 | AL26: =IF(AND(AC26<>"",Y26<>""),ROUND(AF26/Y26,0),"") -> 235 | AM26: =IF(AND(AK26<>"",AL26<>""),AK26+AL26,"") -> 471 | AN26: =IF(AND(AF26<>"",AG26<>"",AH26<>"",AI26<>""),AF26+AG26+AH26+AI26,"") -> 112985 | AO26: =IF(AND(AM26<>"",P26<>""),ROUND((AM26*((100+SI!$C$11)/100)),0),"") -> 542 | AP26: =IF(AG26<>"",ROUND(AG26/SI!$C$9,2),"") -> 12027.27 | AQ26: =IF(AH26<>"",ROUND(AH26/SI!$C$9,2),"") -> 780.4 | AR26: =IF(AI26<>"",ROUND(AI26/SI!$C$9,2),"") -> 3278.98 | AS26: =IF(AND(AP26<>"",AR26<>"",AQ26<>""),AP26+AR26+AQ26,"") -> 16086.65 | AT26: =IF(AND(AS26<>"",Y26<>""),ROUND(AS26/Y26,2),"") -> 67.03 | AU26: =IF(AL26<>"",ROUND(AL26/SI!$C$9,2),"") -> 66.76 | AV26: =IF(AM26<>"",ROUND(AM26/SI!$C$9,2),"") -> 133.81 | AW26: =IF(AN26<>"",ROUND(AN26/SI!$C$9,2),"") -> 32098.01 | AX26: =IF(AO26<>"",ROUND(AO26/SI!$C$9,2),"") -> 153.98 | AY26: =IF(AF26<>"",AF26,"") -> 56360 | AZ26: =IF(AY26<>"",ROUND(AY26/(SI!$C$9*SI!$C$10),2),"") -> 168.2 | BA26: =IF(AND(AY26<>"",BH26<>""),ROUND(AY26*BH26/100,2),"") -> 45088 | BB26: =IF(AND(AZ26<>"",BH26<>""),ROUND(AZ26*BH26/100,2),"") -> 134.56 | BC26: =IF(AND(BB26<>"",Y26<>""),ROUND(BB26/Y26,3),"") -> 0.561 | BD26: =IF(AND(BB26<>"",T26<>""),ROUND(BB26/V26,3),"") -> 1.402 | BE26: =IF(AND(X26<>""),ROUND(X26/SI!$C$10,2),"") -> 163.88 | BF26: =IF(AND(BE26<>"",Y26<>""),ROUND(BE26/Y26,3),"") -> 0.683 | BG26: =IF(AND(BE26<>"",V26<>""),ROUND(BE26/V26,3),"") -> 1.707 | BH26: =IF(F26<>"",VLOOKUP(F26,DUTY_2025!A:O,15,FALSE),"") -> 80
A27: =IF(AND(F27<>"",H27<>"YES"),IF(A26<>"",A26,0)+1,A26) -> 23 | B27: =IF(AND(F27<>"",H27<>"YES"),IF(B26<>"",B26,A26)+1,"") -> 23 | C27: 1 | F27: 11042200 | G27: =IF(F27<>"",IFERROR(VLOOKUP(F27,DUTY_2025!A:I,6,FALSE),""),"") -> 0 | H27: NO | I27: =IF(F27<>"",IFERROR(VLOOKUP(F27,DUTY_2025!A:H,2,FALSE),""),"") -> OATS | J27: OATS 1 KG | K27: 0 | L27: 1000 | M27: 10 | N27: 12 | O27: 5 | P27: 18600 | Q27: INR | R27: NET | S27: =IF(AND(H27<>"YES",N27<>""),N27*L27/1000,"") -> 12 | T27: =IF(S27<>"",S27*1.1,"") -> 13.2 | U27: {=IF(AND(H27<>"YES",P27<>"",R27<>"",Q27<>""), _xlfn.SWITCH(Q27, "INR",_xlfn.SWITCH(R27,"KG",P27*S27,"CTN",P27,"UNIT",P27*N27,"NET",P27/M27,0), "USD",_xlfn.SWITCH(R27,"KG",P27*S27*SI!$C$10,"CTN",P27*SI!$C$10,"UNIT",P27*N27*SI!$C$10,"NET",P27*SI!$C$10/M27,0), "LKR",_xlfn.SWITCH(R27,"KG",P27*S27/SI!$C$9,"CTN",P27/SI!$C$9,"UNIT",P27*N27/SI!$C$9,"NET",P27/(M27*SI!$C$9),0), 0), "")} -> 1860 | V27: =IF(AND(S27<>"",M27<>"",N27<>""),S27*M27,"") -> 120 | W27: =IF(V27<>"",V27*1.1,"") -> 132 | X27: =IF(AND(U27<>"",M27<>""),U27*M27,"") -> 18600 | Y27: =IF(AND(H27<>"YES",M27<>"",N27<>""),IF(E27=1,(N27*M27)/2,N27*M27),"") -> 120 | Z27: =IF(AND(H27<>"yes",F27<>""),IFERROR(VLOOKUP(F27,DUTY_2025!A:F,5,FALSE),""),"") -> 441 | AA27: =IF(B27<>"",IF(AND(X27<>"", O27<>""),IF(ROUND(X27*100/(100+O27),0)=0,"",ROUND(X27*100/(100+O27),0)),""),"") -> 17714 | AB27: =IF(M27<>"",IF(AND(X27<>"",AA27<>""),X27-AA27,""),"") -> 886 | AC27: =IF(AA27<>"",ROUND(AA27*SI!$C$9,0),"") -> 62353 | AD27: =IF(AC27<>"",ROUND(AC27/(SI!$C$9*SI!$C$10),2),"") -> 186.09 | AE27: =IF(AND(X27<>""), ROUND((SI!$E$23)*(X27/SUM($X$5:$X$493)),0),"") -> 4844 | AF27: =IF(AND(AC27<>"",AE27<>""),ROUND(AC27+AE27,0),"") -> 67197 | AG27: =IF(AND(Z27<>"",V27<>""),Z27*V27,"") -> 52920 | AH27: =IF(AD27<>"",ROUND(AD27*10*SI!$C$9/2,0),"") -> 3275 | AI27: =IF(AND(X27<>""), ROUND((SI!$E$28)*(X27/SUM($X$5:$X$493)),0),"") -> 13762 | AJ27: =IF(AND(AG27<>"",AI27<>"",AH27<>""),AG27+AI27+AH27,"") -> 69957 | AK27: =IF(AND(AJ27<>"",Y27<>""),ROUND(AJ27/Y27,0),"") -> 583 | AL27: =IF(AND(AC27<>"",Y27<>""),ROUND(AF27/Y27,0),"") -> 560 | AM27: =IF(AND(AK27<>"",AL27<>""),AK27+AL27,"") -> 1143 | AN27: =IF(AND(AF27<>"",AG27<>"",AH27<>"",AI27<>""),AF27+AG27+AH27+AI27,"") -> 137154 | AO27: =IF(AND(AM27<>"",P27<>""),ROUND((AM27*((100+SI!$C$11)/100)),0),"") -> 1314 | AP27: =IF(AG27<>"",ROUND(AG27/SI!$C$9,2),"") -> 15034.09 | AQ27: =IF(AH27<>"",ROUND(AH27/SI!$C$9,2),"") -> 930.4 | AR27: =IF(AI27<>"",ROUND(AI27/SI!$C$9,2),"") -> 3909.66 | AS27: =IF(AND(AP27<>"",AR27<>"",AQ27<>""),AP27+AR27+AQ27,"") -> 19874.15 | AT27: =IF(AND(AS27<>"",Y27<>""),ROUND(AS27/Y27,2),"") -> 165.62 | AU27: =IF(AL27<>"",ROUND(AL27/SI!$C$9,2),"") -> 159.09 | AV27: =IF(AM27<>"",ROUND(AM27/SI!$C$9,2),"") -> 324.72 | AW27: =IF(AN27<>"",ROUND(AN27/SI!$C$9,2),"") -> 38964.2 | AX27: =IF(AO27<>"",ROUND(AO27/SI!$C$9,2),"") -> 373.3 | AY27: =IF(AF27<>"",AF27,"") -> 67197 | AZ27: =IF(AY27<>"",ROUND(AY27/(SI!$C$9*SI!$C$10),2),"") -> 200.55 | BA27: =IF(AND(AY27<>"",BH27<>""),ROUND(AY27*BH27/100,2),"") -> 53757.6 | BB27: =IF(AND(AZ27<>"",BH27<>""),ROUND(AZ27*BH27/100,2),"") -> 160.44 | BC27: =IF(AND(BB27<>"",Y27<>""),ROUND(BB27/Y27,3),"") -> 1.337 | BD27: =IF(AND(BB27<>"",T27<>""),ROUND(BB27/V27,3),"") -> 1.337 | BE27: =IF(AND(X27<>""),ROUND(X27/SI!$C$10,2),"") -> 195.4 | BF27: =IF(AND(BE27<>"",Y27<>""),ROUND(BE27/Y27,3),"") -> 1.628 | BG27: =IF(AND(BE27<>"",V27<>""),ROUND(BE27/V27,3),"") -> 1.628 | BH27: =IF(F27<>"",VLOOKUP(F27,DUTY_2025!A:O,15,FALSE),"") -> 80
